Workbook

Sheet Read me
A1: Case 4 - value at risk
A3: What this is
A4: A value-at-risk model for the three leaks in Case 4, built so that every number can be traced to where it came from.
A6: How to use it
A7: Change any value in column C of the Assumptions sheet, or a low or high in columns D and E. Every other sheet is formulas, so the answer moves with it. No input is typed into a formula anywhere in this workbook; the only literals are unit conversions, the halving of a two-sided spread, the floor at zero on leak 3's expected level and curve line, and the month arithmetic on the upgrade-timing sheet.
A9: The five tiers
A10: MEASURED (456 inputs) - our own analysis of 3.9 million used-car listings from 29 sources. The source column names the report and `check_assumptions.py` re-reads the figure out of it.
A11: SOURCED (354 inputs) - published figures with a URL: Stellantis's FY2025 results and Form 20-F, Eurostat and ONS price indices, published studies.
A12: ASSUMPTION (29 inputs) - our judgement, each with a low and a high and a caveat saying what it rests on. These are the rows a pilot should replace with evidence.
A13: TARGET (31 inputs) - a level the team chose rather than found: a phase gate or a KPI threshold. These are commitments, not findings, so `check_assumptions.py` refuses to let one feed a value-at-risk formula, and the audit keeps every one out of every formula.
A14: SYNTHETIC (50 inputs) - results of the leak-1 test harness, a world we or a blind red team built, and of the ledger prototype built on it. They measure the tool, not the group, so they are quoted only as rankings, failures and engineering facts, and both checkers refuse to let one feed a formula.
A16: Which of them move the answer
... A36: .venv/bin/python build_var_model.py # rebuilds this workbook

Sheet Assumptions
A1: id | B1: label | C1: value | D1: low | E1: high | F1: unit | G1: tier | H1: source | I1: url | J1: as of | K1: caveat | L1: used in
A2: eu_shipments | B2: Enlarged Europe consolidated shipments | C2: 2490000 | F2: units | G2: SOURCED | H2: Stellantis FY2025 results press release (SEC-filed) | I2: https://www.sec.gov/Archives/edgar/data/1605484/000160548426000019/stellantisnvfy2025pressrel.htm | J2: FY2025 | K2: Down from 2,576k in FY2024. Enlarged Europe is the EU-27, the UK and EFTA (plus Israel and Palestine from 2025); Middle East & Africa is a separate segment. | L2: Leak 1;Leak 2
A3: eu_revenue_eur_m | B3: Enlarged Europe net revenues | C3: 57773 | F3: EUR m | G3: SOURCED | H3: Stellantis FY2025 results press release (SEC-filed) | I3: https://www.sec.gov/Archives/edgar/data/1605484/000160548426000019/stellantisnvfy2025pressrel.htm | J3: FY2025 | K3: Segment revenue; not only new-vehicle sales. | L3: Leak 1
A4: eu_aoi_eur_m | B4: Enlarged Europe adjusted operating income | C4: -651 | F4: EUR m | G4: SOURCED | H4: Stellantis FY2025 results press release (SEC-filed) | I4: https://www.sec.gov/Archives/edgar/data/1605484/000160548426000019/stellantisnvfy2025pressrel.htm | J4: FY2025 | K4: A swing of -3,070m from +2,419m in FY2024. Context for urgency; not an input to the VaR. | L4: Context
A5: group_shipments | B5: Group consolidated shipments | C5: 5484000 | F5: units | G5: SOURCED | H5: Stellantis FY2025 results press release (SEC-filed) | I5: https://www.sec.gov/Archives/edgar/data/1605484/000160548426000019/stellantisnvfy2025pressrel.htm | J5: FY2025 | L5: Context
A6: group_revenue_eur_m | B6: Group net revenues | C6: 153508 | F6: EUR m | G6: SOURCED | H6: Stellantis FY2025 results press release (SEC-filed) | I6: https://www.sec.gov/Archives/edgar/data/1605484/000160548426000019/stellantisnvfy2025pressrel.htm | J6: FY2025 | L6: Context
A7: buyback_payables_eur_m | B7: Payables for buy-back agreements | C7: 7889 | F7: EUR m | G7: SOURCED | H7: Stellantis Form 20-F FY2025 Note 24 Other liabilities | I7: https://www.sec.gov/Archives/edgar/data/1605484/000160548426000021/stellantis-20251231.htm | J7: 2025-12-31 | K7: Current 5313 + non-current 2576. The residual exposure base. Note 24 defines it as the price received, recognised as an advance at sale, and subsequently the repurchase price and the remaining lease installments yet to be recognized: so it is the repurchase price plus lease income not yet recognised, an upper bound on the repurchase amount (close to it near maturity, which is the current part) (X18). | L7: Leak 3
A8: buyback_payables_current_eur_m | B8: Payables for buy-back agreements due within one year | C8: 5313 | F8: EUR m | G8: SOURCED | H8: Stellantis Form 20-F FY2025 Note 24 Other liabilities, current column | I8: https://www.sec.gov/Archives/edgar/data/1605484/000160548426000021/stellantis-20251231.htm | J8: 2025-12-31 | K8: The part of the 7,889m that comes back within twelve months, so the base of a per-year figure. The 2,576m due after one year is counted in the year it falls due. | L8: Leak 3
A9: buyback_term_policy | B9: Contracts of 12 months or less are booked as assets sold with a buy-back commitment | F9: text | G9: SOURCED | H9: Stellantis Form 20-F FY2025, revenue recognition: "recorded within Assets sold with a buy-back commitment if the contract term is 12 months or less, and recorded in Property, plant and equipment if the contract term is greater than 12 months" | I9: https://www.sec.gov/Archives/edgar/data/1605484/000160548426000021/stellantis-20251231.htm | J9: FY2025 | K9: Why most of the book is short-dated. | L9: Context
A10: buyback_value_decrease_2025_eur_m | B10: Decrease in value booked on assets sold with a buy-back commitment - 2025 | C10: 358 | F10: EUR m | G10: SOURCED | H10: Stellantis Form 20-F FY2025, cost of revenues: "EUR 358 million, EUR 179 million and EUR 82 million related to the decrease in value for assets sold with buy-back commitments" (2025, 2024, 2023) | I10: https://www.sec.gov/Archives/edgar/data/1605484/000160548426000021/stellantis-20251231.htm | J10: FY2025 | K10: Scheduled depreciation, not a loss: the 20-F FY2025 policy says 'the difference between the cost of the vehicle and the estimated net residual value is recognized within Cost of revenues ... over the contractual term'. Contracts of 12 months or less. As a share of year-end buy-back assets it is about a year's ordinary depreciation (X6 part 4), so it cannot check leak 3. The group discloses no gains or losses at disposal for this book. | L10: Context
A11: buyback_value_decrease_2024_eur_m | B11: Decrease in value booked on assets sold with a buy-back commitment - 2024 | C11: 179 | F11: EUR m | G11: SOURCED | H11: Stellantis Form 20-F FY2025, cost of revenues (same sentence) | I11: https://www.sec.gov/Archives/edgar/data/1605484/000160548426000021/stellantis-20251231.htm | J11: FY2024 | K11: See buyback_value_decrease_2025_eur_m. | L11: Context
A12: buyback_value_decrease_2023_eur_m | B12: Decrease in value booked on assets sold with a buy-back commitment - 2023 | C12: 82 | F12: EUR m | G12: SOURCED | H12: Stellantis Form 20-F FY2025, cost of revenues (same sentence) | I12: https://www.sec.gov/Archives/edgar/data/1605484/000160548426000021/stellantis-20251231.htm | J12: FY2023 | K12: See buyback_value_decrease_2025_eur_m. | L12: Context
A13: buyback_assets_eur_m | B13: Assets sold with a buy-back commitment | C13: 3616 | F13: EUR m | G13: SOURCED | H13: Stellantis Form 20-F FY2025 consolidated balance sheet | I13: https://www.sec.gov/Archives/edgar/data/1605484/000160548426000021/stellantis-20251231.htm | J13: 2025-12-31 | K13: Asset side of the same arrangements; 1938m in 2024. Shown for scale only to avoid double counting. | L13: Context
A14: rv_review_months | B14: Frequency of residual-value review today | C14: 3 | F14: months | G14: SOURCED | H14: Stellantis Form 20-F FY2025: "Expected residual values are analyzed quarterly and depreciation rates are adjusted accordingly" | I14: https://www.sec.gov/Archives/edgar/data/1605484/000160548426000021/stellantis-20251231.htm | J14: FY2025 | K14: The group's stated practice. Our recommendation is monthly. | L14: Leak 3
A15: rv_method_today | B15: Residual values use third-party estimates plus in-house modelling | F15: text | G15: SOURCED | H15: Stellantis Form 20-F FY2025: "Third party estimates are utilized in conjunction with proprietary modelling" | I15: https://www.sec.gov/Archives/edgar/data/1605484/000160548426000021/stellantis-20251231.htm | J15: FY2025 | K15: Answers the build-vs-buy question: they already buy; the gap is their own discount and launch plans. | L15: Context
A16: lev_residual_uncertainty | B16: Electrified residuals are harder because resale history is thin | F16: text | G16: SOURCED | H16: Stellantis Form 20-F FY2025: "Residual values for LEVs are subject to greater uncertainty than for ICE vehicles, due to limited historical resale data" | I16: https://www.sec.gov/Archives/edgar/data/1605484/000160548426000021/stellantis-20251231.htm | J16: FY2025 | K16: The group's own words for the little-history problem our pooling result addresses. | L16: Leak 3
A17: schloter_ev_dep_month | B17: Depreciation of used electric cars a month (Schloter 2022) | C17: 1.16 | F17: % a month | G17: SOURCED | H17: Schloter, Empirical analysis of the depreciation of electric vehicles compared to gasoline vehicles, Transport Policy 126 (2022) 268-279, abstract (TRID record) | I17: https://trid.trb.org/View/2005004 | J17: 2022 | K17: 24,000 used-vehicle sales across several countries and segments, web data of 2020-21 (not Norway, as the user's research report said). A benchmark for ev_level_report.md's curve, not an input. | L17: Context: X9 (EV residual risk)
A18: schloter_petrol_dep_month | B18: Depreciation of used petrol cars a month (Schloter 2022) | C18: 0.87 | F18: % a month | G18: SOURCED | H18: Schloter, Empirical analysis of the depreciation of electric vehicles compared to gasoline vehicles, Transport Policy 126 (2022) 268-279, abstract (TRID record) | I18: https://trid.trb.org/View/2005004 | J18: 2022 | K18: As schloter_ev_dep_month. | L18: Context: X9 (EV residual risk)
A19: fitch_eu_abs_bev_share_q3_2024 | B19: BEV share of Fitch-rated European loan and lease ABS, Q3 2024 | C19: 11 | F19: % | G19: SOURCED | H19: Fitch Ratings, Higher BEV Exposures Increase RV Risk in European Auto Lease ABS (27 January 2025), as reported by Motor Finance Online, 12 February 2025 | I19: https://www.motorfinanceonline.com/news/bev-exposure-in-european-auto-lease-abs-raises-residual-value-risk-fitch/ | J19: 2024-09-30 | K19: 'Close to 11%'; about 6% in 2023. Secondary source: Fitch's page refuses automated reading. Fitch: 'Since 2023, used BEV prices have fallen more sharply than those of other powertrains'; one Dutch lease portfolio is nearly 50% BEV. | L19: Context: X9 (EV residual risk)
A20: euro7_battery_mpr_m1_5y | B20: Euro 7 minimum battery energy for M1 cars (BEV and PHEV), start of life to 5 years or 100,000 km | C20: 80 | F20: % of certified energy | G20: SOURCED | H20: Regulation (EU) 2024/1257 (Euro 7), Annex II Table 1 | I20: https://eur-lex.europa.eu/legal-content/EN/TXT/HTML/?uri=CELEX:32024R1257 | J20: 2024-04-24 | K20: A type-approval requirement checked on the vehicle type in service, not a per-car warranty; applies to new M1 types from 29 November 2026 and all new M1 cars from 29 November 2027 (Article 21). N1 vans: 75% (Table 2). | L20: Context: X9 (EV residual risk)
A21: euro7_battery_mpr_m1_8y | B21: The same, more than 5 years or 100,000 km and up to 8 years or 160,000 km | C21: 72 | F21: % of certified energy | G21: SOURCED | H21: Regulation (EU) 2024/1257 (Euro 7), Annex II Table 1 | I21: https://eur-lex.europa.eu/legal-content/EN/TXT/HTML/?uri=CELEX:32024R1257 | J21: 2024-04-24 | K21: As euro7_battery_mpr_m1_5y. N1 vans: 67% (Table 2). Battery durability data readable through the OBD port. | L21: Context: X9 (EV residual risk)
A22: battreg_soh_access_from | B22: EV battery state of health held in the battery management system, readable by the battery's legal purchaser for evaluating its residual value, from 18 August 2024 | C22: 2024.63 | F22: year | G22: SOURCED | H22: Regulation (EU) 2023/1542 (Batteries), Article 14(1)-(2) and Annex VII Part A (state of certified energy) | I22: https://eur-lex.europa.eu/legal-content/EN/TXT/HTML/?uri=CELEX:32023R1542 | J22: 2023-07-12 | K22: 18 August 2024 as a decimal year. Read-only access, respecting the battery maker's intellectual property, for the legal purchaser or a party acting for them; purpose (b) is 'evaluating the residual value'. A captive that owns its leased EVs may read each one's state of health at return. | L22: Context: X9 (EV residual risk)
A23: battreg_passport_from | B23: Battery passport required for every EV battery placed on the market, from 18 February 2027 | C23: 2027.13 | F23: year | G23: SOURCED | H23: Regulation (EU) 2023/1542 (Batteries), Article 77(1) | I23: https://eur-lex.europa.eu/legal-content/EN/TXT/HTML/?uri=CELEX:32023R1542 | J23: 2023-07-12 | K23: 18 February 2027 as a decimal year. The passport carries model and individual-battery information (Annex XIII), part public, part for persons with a legitimate interest. | L23: Context: X9 (EV residual risk)
A24: geotab_degradation_pct_year | B24: Average EV battery capacity loss a year (Geotab) | C24: 2.3 | F24: % a year | G24: SOURCED | H24: Geotab, What can 10,000+ EVs tell us about battery health? (22,700+ vehicles; 1.5% with little DC fast charging, 3.0% with frequent fast charging) | I24: https://www.geotab.com/blog/ev-battery-health/ | J24: 2024 | K24: Telematics fleet data; Geotab does not say what share is European. Checked by a research agent on 24 September. | L24: Context: X9 (EV residual risk)
A25: incentive_not_disclosed | B25: Total sales incentive spend is not disclosed | F25: text | G25: SOURCED | H25: Stellantis Form 20-F FY2025: sales incentives are a critical estimate; "estimated incentive rates are reviewed monthly" | I25: https://www.sec.gov/Archives/edgar/data/1605484/000160548426000021/stellantis-20251231.htm | J25: FY2025 | K25: This is why every Leak 1 figure below is an assumption rather than a sourced number. X14 (26 September): no regional total is disclosed, but Note 21's sales-incentive provision and its roll-forward are, worldwide (sales_incentive_*); leak 1's claims line now rests on them. | L25: Leak 1
A26: ons_uk_index_move | B26: UK second-hand car index move 2018-01 to 2022-10 | C26: 26.6 | F26: % | G26: SOURCED | H26: ONS CPI 07.1.1B second-hand cars (series D7E9) via data/reference/price_indices.parquet | I26: https://www.ons.gov.uk/economy/inflationandpriceindices | J26: 2022-10 | K26: Independent measure of the UK level move behind the Corsa example. | L26: Leak 3
A27: dealer_passthrough_low | B27: Share of a dealer discount that reaches the buyer | C27: 30 | D27: 30 | E27: 40 | F27: % | G27: SOURCED | H27: Busse, Silva-Risso & Zettelmeyer, $1,000 Cash Back, American Economic Review 2006 | I27: https://www.aeaweb.org/articles?id=10.1257/aer.96.4.1253 | J27: 2006 | K27: US data. Customer rebates pass through at 70-90%; dealer discounts at 30-40%. | L27: Leak 1
A28: dep_pooled | B28: Depreciation per year of age | C28: -9.2 | D28: -10 | E28: -7.9 | F28: % | G28: MEASURED | H28: analysis/drivers_report.md pooled effects table | J28: 2026-09-17 | K28: 16 datasets, 2,617,260 cars. Random-effects pooled; the single pooled model says -10.7%. Age alone, with mileage held fixed: a lease-age car also being driven loses about 12% a year (drivers_report.md). | L28: Leak 2;Leak 3
A29: dep_with_mileage_3y | B29: Yearly value loss at 3 years old, age plus a typical year's mileage | C29: -12 | F29: % | G29: MEASURED | H29: analysis/drivers_report.md | J29: 2026-09-17 | K29: Pooled age effect plus the pooled mileage effect for the extra mileage a steadily driven car adds between 3 and 4 years old. | L29: Context
A30: dep_market_min | B30: Fastest depreciation of any market measured | C30: -13.3 | F30: % | G30: MEASURED | H30: analysis/drivers_report.md per-dataset spread (dvm) | J30: 2026-09-17 | K30: The rate is real everywhere but its size is local. | L30: Leak 3
A31: dep_market_max | B31: Slowest depreciation of any market measured | C31: -4.9 | F31: % | G31: MEASURED | H31: analysis/drivers_report.md per-dataset spread (eg_hatla2ee) | J31: 2026-09-17 | K31: Egypt; a market unlike the group's European ones. | L31: Leak 3
A32: dep_uk | B32: UK depreciation per year of age | C32: -10.4 | F32: % | G32: MEASURED | H32: analysis/drivers_report.md per-dataset (uk_2022_10) | J32: 2026-09-17 | K32: Advert prices. | L32: Leak 2
A33: dep_stability_lo | B33: Slowest monthly estimate of the rate over 52 months | C33: -13.2 | F33: % | G33: MEASURED | H33: analysis/latvia_time_report.md | J33: 2026-09-17 | K33: Latvia, one market. The rate never left this band through the 2021-22 shortage. | L33: Leak 3
A34: dep_stability_hi | B34: Fastest monthly estimate of the rate over 52 months | C34: -11.7 | F34: % | G34: MEASURED | H34: analysis/latvia_time_report.md | J34: 2026-09-17 | K34: Latvia, one market. Standard deviation 0.38 points. | L34: Leak 3
A35: latvia_index_corr | B35: Correlation of our Latvian price index with Eurostat's | C35: 0.958 | F35: r | G35: MEASURED | H35: analysis/latvia_time_report.md | J35: 2026-09-17 | K35: Correlation of index levels, which two rising series share whatever they measure. As changes: 12-month moves agree (0.90), month-on-month moves do not (-0.03). Disagrees on size (+42% vs +8.8%). | L35: Context
A36: retained_3y_pooled | B36: Value retained at 3 years at the pooled rate | C36: 75 | F36: % of list | G36: MEASURED | H36: analysis/level_risk_report.md (derived from dep_pooled) | J36: 2026-09-17 | K36: Arithmetic on the pooled rate; the denominator for turning points of list price into a share of residual value. | L36: Leak 3
A37: retained_3y_uk | B37: Value retained at 3 years - UK (2018 adverts) | C37: 66 | F37: % of list | G37: MEASURED | H37: analysis/value_retained_report.md | J37: 2026-09-17 | K37: DVM adverts, mostly 2018, before the shortage. The UK's October 2022 scrape gives 90% (retained_3y_uk_2022); pooling the two blends eras. Entry-trim new price flatters the share. | L37: Leak 2
A38: retained_3y_uk_2022 | B38: Value retained at 3 years - UK (October 2022 adverts) | C38: 90 | F38: % of list | G38: MEASURED | H38: analysis/value_retained_report.md | J38: 2026-09-17 | K38: Shortage peak, and a different scrape from the 2018 row, so the +24-point gap mixes a market move with a source difference. | L38: Context
A39: retained_3y_nl | B39: Value retained at 3 years - Netherlands | C39: 60 | F39: % of list | G39: MEASURED | H39: analysis/value_retained_report.md | J39: 2026-09-25 | K39: Deflated by BPM registration tax in the list price. Not comparable in level with the others. | L39: Context
A40: retained_3y_us | B40: Value retained at 3 years - US | C40: 68 | F40: % of list | G40: MEASURED | H40: analysis/value_retained_report.md | J40: 2026-09-17 | K40: US data. Sample of 690 cars. | L40: Context
... A82: tesla_pre_announcement | B82: Share of the Tesla repricing that happened before the January 2023 US list-price cut | C82: 68 | F82: % | G82: MEASURED | H82: analysis/tesla_event_report.md | J82: 2026-09-17 | K82: US, Washington State, EVs only. Tesla had already cut prices in China (Oct 2022) and offered US year-end discounts (Dec 2022), so it is not ahead of every manufacturer move. The reason no discount-to-resale factor is quoted anywhere in this model. | L82: Context
A83: auction_vs_sale | B83: Auction price against an equivalent recorded sale | C83: 7.3 | D83: 5.2 | E83: 9.5 | F83: % | G83: MEASURED | H83: analysis/price_types_report.md | J83: 2026-09-17 | K83: US only. Do not read as a channel-choice rule; the two sources sell different kinds of car. | L83: Context
A84: incentive_pct_revenue | B84: Sales incentives as a share of European net revenue | C84: 8 | D84: 5 | E84: 12 | F84: % | G84: ASSUMPTION | H84: Our estimate. The group does not disclose a total - see incentive_not_disclosed. | J84: 2026-09-17 | K84: No European source found. Leak 1 is linear in this input: the one-input-at-a-time table on the Summary sheet shows the total at its low and high. Replaced in leak 1's claims line on 26 September (X14) by x14_incentive_claims_central, the group's own sales-incentive provision over net revenues (20-F Note 21, worldwide); kept so the comparison can be recomputed. | L84: Context: leak 1 (replaced by X14)
A85: x14_incentive_claims_central | B85: Incentive claims as a share of net revenue, the group's own 20-F, central | C85: 6.75 | F85: % of revenue | G85: MEASURED | H85: analysis/incentive_anchor_report.md | J85: 2026-09-26 | K85: The group's claims-based incentive programmes (Note 21's sales-incentive provision) as a share of net revenues, worldwide: the 20-F gives no regional split, so applying it to Europe is a judgement. Price discounts at invoice are outside it, so total incentive spend is higher; leak 1's claims line is about claims. 2025 additions: the incentive cost of that year's sales. | L85: Leak 1
A86: x14_incentive_claims_low | B86: The same, lowest of four ratios (2024-25, additions and settlements) | C86: 6.44 | F86: % of revenue | G86: MEASURED | H86: analysis/incentive_anchor_report.md | J86: 2026-09-26 | K86: The group's claims-based incentive programmes (Note 21's sales-incentive provision) as a share of net revenues, worldwide: the 20-F gives no regional split, so applying it to Europe is a judgement. Price discounts at invoice are outside it, so total incentive spend is higher; leak 1's claims line is about claims. 2024 settlements. | L86: Leak 1
A87: x14_incentive_claims_high | B87: The same, highest of four ratios (2024-25, additions and settlements) | C87: 7.14 | F87: % of revenue | G87: MEASURED | H87: analysis/incentive_anchor_report.md | J87: 2026-09-26 | K87: The group's claims-based incentive programmes (Note 21's sales-incentive provision) as a share of net revenues, worldwide: the 20-F gives no regional split, so applying it to Europe is a judgement. Price discounts at invoice are outside it, so total incentive spend is higher; leak 1's claims line is about claims. 2025 settlements, which paid down a provision built up in 2024. | L87: Leak 1
A88: agency_markets_2025 | B88: The group kept the dealer model in Europe except Austria, Belgium, Luxembourg and the Netherlands (agency since 2023) | F88: text | G88: SOURCED | H88: MarketScreener, 13 May 2025, quoting Jean-Philippe Imparato (head of Europe): "The sales network will therefore retain the traditional model, with the exception of Austria, Belgium, Luxembourg, and the Netherlands, where the transition to the agency model has already begun in 2023." Also WardsAuto, 19 May 2025 | I88: https://www.marketscreener.com/quote/stock/STELLANTIS-N-V-117814143/news/Stellantis-suspends-its-plan-to-reform-its-dealership-network-in-Europe-49944995/ | J88: 2025-05 | K88: Press reports of a management statement, not a filing. The Dutch start date (4 September 2023) was verified in X2. The brand split inside the four markets is not given. | L88: Context: X14 (agency and leak 1)
A89: vber_art4a_rpm | B89: EU vertical block exemption: a supplier may recommend or cap a resale price, not fix a minimum through pressure or incentives | F89: text | G89: SOURCED | H89: Commission Regulation (EU) 2022/720, Art. 4(a): "...the possibility of the supplier to impose a maximum sale price or recommend a sale price, provided that they do not amount to a fixed or minimum sale price as a result of pressure from, or incentives offered by, any of the parties"; expires 31 May 2034 | I89: https://eur-lex.europa.eu/legal-content/EN/TXT/HTML/?uri=CELEX:32022R0720 | J89: 2022-06-01 | K89: Applies to the group's dealers outside agency. A recommended used-car price or a targeted incentive is lawful; tying an incentive to the dealer holding a price is a hardcore restriction. Under genuine agency (Vertical Guidelines 2022/C 248/01, paras 30-34) the principal sets the price. | L89: Context: X14 (agency and leak 1)
A90: afca_peugeot_fine_eur_m | B90: Austria: Cartel Court fine on Peugeot Austria GmbH for abuse of dominance towards dealers (new-car sales and garage services, 2017-2021) | C90: 15 | F90: EUR m | G90: SOURCED | H90: Austrian Federal Competition Authority, Annual Report 2024, pp. 41 and 69 (case 26 Kt 5/23i; the largest abuse-of-dominance fine in Austria) | I90: https://www.bwb.gv.at/fileadmin/user_upload/ENG_BWB_Taetigkeitsbericht2024_BARRIEREFREI.cleaned.pdf | J90: 2024 | K90: The practices (arbitrary bonus conditions, unrealistic targets, onerous warranty audit procedures, a margin squeeze against independent distributors) are from a Wolters Kluwer competition blog, not the authority's report. A warning for leak 1's controls: claim holds and dealer audits must be rule-based, proportionate and the same for owned and independent dealers. | L90: Context: X14 (agency and leak 1)
A91: x14_agency_share_2024 | B91: The four agency markets' share of the group's new-car registrations, 2024 | C91: 6.7 | F91: % | G91: MEASURED | H91: analysis/agency_share_report.md | J91: 2026-09-26 | K91: Austria, Belgium, Luxembourg and the Netherlands (agency_markets_2025) over the group's registrations in the EU CO2 register (cars; EU, Norway, Iceland; no UK from 2021). The rest of the group's sales run through dealers who file incentive claims, leak 1's process. Brand split within the four markets not published. | L91: Context: X14 (agency and leak 1)
A92: x14_agency_share_2025p | B92: The four agency markets' share of the group's new-car registrations, 2025 (provisional) | C92: 7.8 | F92: % | G92: MEASURED | H92: analysis/agency_share_report.md | J92: 2026-09-26 | K92: Austria, Belgium, Luxembourg and the Netherlands (agency_markets_2025) over the group's registrations in the EU CO2 register (cars; EU, Norway, Iceland; no UK from 2021). The rest of the group's sales run through dealers who file incentive claims, leak 1's process. Brand split within the four markets not published. | L92: Context: X14 (agency and leak 1)
A93: fca_redress_total_gbp_bn | B93: UK motor-finance redress scheme: expected redress to consumers | C93: 7.5 | F93: GBP bn | G93: SOURCED | H93: FCA press release, 30 March 2026: "total redress paid would be £7.5bn" (at 75% take-up) | I93: https://www.fca.org.uk/news/press-releases/millions-car-finance-customers-payouts-fca-goes-ahead-compensation-scheme | J93: 2026-03-30 | K93: UK only. The scheme compensates buyers where the dealer or broker did not disclose a discretionary commission arrangement, a high commission (at least 39% of the total cost of credit and 10% of the loan) or a tied lender, on motor finance loans from 6 April 2007 to 1 November 2024 (PS26/3, 30 March 2026; implementation 30 June 2026 for loans from 1 April 2014, 31 August 2026 for earlier ones). Industry-wide; the group's share is not disclosed. It is a cost of the past, not a leak: context for why the ledger joins dealer pay, incentive and finance per car. | L93: Context: X14 (UK regulation)
A94: fca_redress_cost_to_firms_gbp_bn | B94: UK motor-finance redress scheme: total bill to firms, redress and non-redress costs | C94: 9.1 | F94: GBP bn | G94: SOURCED | H94: FCA statement "FCA confirms motor finance redress scheme" (first published 30 March 2026): £7.5bn redress plus £1.6bn non-redress costs, £9.1bn (£11bn at consultation) | I94: https://www.fca.org.uk/news/statements/fca-confirms-motor-finance-redress-scheme | J94: 2026-03-30 | K94: UK only. The scheme compensates buyers where the dealer or broker did not disclose a discretionary commission arrangement, a high commission (at least 39% of the total cost of credit and 10% of the loan) or a tied lender, on motor finance loans from 6 April 2007 to 1 November 2024 (PS26/3, 30 March 2026; implementation 30 June 2026 for loans from 1 April 2014, 31 August 2026 for earlier ones). Industry-wide; the group's share is not disclosed. It is a cost of the past, not a leak: context for why the ledger joins dealer pay, incentive and finance per car. | L94: Context: X14 (UK regulation)
A95: fca_redress_agreements_m | B95: UK motor-finance redress scheme: eligible agreements | C95: 12.1 | F95: million | G95: SOURCED | H95: FCA press release, 30 March 2026: "12.1 million agreements made between 2007 and 2024 are now eligible" (14.2m at consultation) | I95: https://www.fca.org.uk/news/press-releases/millions-car-finance-customers-payouts-fca-goes-ahead-compensation-scheme | J95: 2026-03-30 | K95: UK only. The scheme compensates buyers where the dealer or broker did not disclose a discretionary commission arrangement, a high commission (at least 39% of the total cost of credit and 10% of the loan) or a tied lender, on motor finance loans from 6 April 2007 to 1 November 2024 (PS26/3, 30 March 2026; implementation 30 June 2026 for loans from 1 April 2014, 31 August 2026 for earlier ones). Industry-wide; the group's share is not disclosed. It is a cost of the past, not a leak: context for why the ledger joins dealer pay, incentive and finance per car. | L95: Context: X14 (UK regulation)
A96: fca_redress_avg_gbp | B96: UK motor-finance redress scheme: average payout per agreement | C96: 830 | F96: GBP | G96: SOURCED | H96: FCA press release, 30 March 2026: "The average payout has increased to around £830 per agreement" | I96: https://www.fca.org.uk/news/press-releases/millions-car-finance-customers-payouts-fca-goes-ahead-compensation-scheme | J96: 2026-03-30 | K96: UK only. The scheme compensates buyers where the dealer or broker did not disclose a discretionary commission arrangement, a high commission (at least 39% of the total cost of credit and 10% of the loan) or a tied lender, on motor finance loans from 6 April 2007 to 1 November 2024 (PS26/3, 30 March 2026; implementation 30 June 2026 for loans from 1 April 2014, 31 August 2026 for earlier ones). Industry-wide; the group's share is not disclosed. It is a cost of the past, not a leak: context for why the ledger joins dealer pay, incentive and finance per car. | L96: Context: X14 (UK regulation)
A97: uk_redress_group_jv_2025 | B97: The group's 20-F: UK motor-finance redress reduced its share of finance joint-venture profits in 2025 | F97: text | G97: SOURCED | H97: Stellantis Form 20-F FY2025, results of operations: "lower share of profits from financial services joint ventures, in part due to the impact of the cost recorded during 2025 from the UK motor finance redress program" | I97: https://www.sec.gov/Archives/edgar/data/1605484/000160548426000021/stellantis-20251231.htm | J97: FY2025 | K97: No amount is given. The UK joint venture is with BNP Paribas PF (equity-accounted), so the cost reaches the group through its share of profit. | L97: Context: X14 (UK regulation)
A98: ccd2_intermediary_rules | B98: EU Consumer Credit Directive 2023/2225: intermediaries' remuneration and disclosure, applying from 20 November 2026 | F98: text | G98: SOURCED | H98: Directive (EU) 2023/2225, Art. 32(2) and (4) (remuneration must not impede fair treatment; Member States may ban creditor-paid commissions where advice is given), Art. 38 (say whether tied to one or more creditors; disclose fees the consumer pays), Art. 48 (apply from 20 November 2026) | I98: https://eur-lex.europa.eu/legal-content/EN/TXT/HTML/?uri=CELEX:32023L2225 | J98: 2023-10-18 | K98: No EU article requires the dealer to disclose the commission the lender pays, the UK scheme's core; national transposition may go further. The ledger records each car's dealer commission, incentive and finance terms together, so it can show any of them on request. | L98: Context: X14 (EU regulation)
A99: mobilisights_scope | B99: Mobilisights (Mobilisights Connect from March 2026): the group's wholly owned connected-data business, with consent-based access to embedded data from 14 brands | F99: text | G99: SOURCED | H99: Stellantis media, 6 March 2026 (rebrand: "remains a wholly owned data and software company of Stellantis", over 40 telematics partners in Europe and North America, data from fourteen brands) and 10 January 2024 ("the Company collects and shares data only with user's explicit consent"; odometer among the data) | I99: https://www.media.stellantis.com/em-en/mobilisights/press/mobilisights-rebrands-as-mobilisights-connect-enabling-software-solutions-powered-by-trusted-vehicle-data | J99: 2026-03-06 | K99: No count of connected cars is published in these releases or the 20-F; a blog's 13.8m and 5m were not used. Its products are sold to fleets, insurers and charging services; none published is for remarketing or contract ends. | L99: Context: X14 (connected data)
A100: mobilisights_eu_fleet_pack | B100: Mobilisights' EU fleet data pack covers Pro One vans from model year 2024, for up to four years from the warranty date | F100: text | G100: SOURCED | H100: mobilisights.com, EU Fleet Data Pack page (Citroen, Fiat, Opel, Peugeot, Vauxhall vans: Berlingo, Doblo, Combo, Partner, Jumpy, Expert, Ducato and others; "all Stellantis ProOne MY24 models") | I100: https://www.mobilisights.com/en/eu-fleetdatapack.html | J100: 2026-09 | K100: The product sold to third parties in the EU; the group's own internal access to its cars' data is not described publicly. | L100: Context: X14 (connected data)
A101: data_act_rules | B101: EU Data Act: the carmaker may use a connected car's non-personal data only under a contract with the user; the user can have it sent to a third party | F101: text | G101: SOURCED | H101: Regulation (EU) 2023/2854, Art. 4(13) ("A data holder shall only use any readily available data that is non-personal data on the basis of a contract with the user"), Art. 5(1) (sharing with a third party at the user's request), Art. 50 (applies from 12 September 2025; Art. 3(1) design duty for products placed on the market after 12 September 2026) | I101: https://eur-lex.europa.eu/legal-content/EN/TXT/HTML/?uri=CELEX:32023R2854 | J101: 2023-12-13 | K101: Personal data (a private driver's car) also needs a GDPR basis. For a leased car the lessor and the lessee can both be users. So the ledger may read a car's odometer or battery health for its own contract or buy-back cars under the contract, and competitors can get the same data from the user: it is not an exclusive edge. | L101: Context: X14 (connected data)
A102: ayvens_costs_to_achieve_eur_m | B102: Ayvens (ALD + LeasePlan): total costs to achieve the integration, 2022-2025 | C102: 525 | F102: EUR m | G102: SOURCED | H102: ALD | LeasePlan "PowerUP 2026" press release, 18 September 2023: "Total cumulated costs to achieve of EUR 525 million over 2022-2025" (EUR 128m in 2022, 170m in 2023, 190m in 2024, 37m in 2025) | I102: https://www.ayvens.com/-/media/ayvens/public/cp/files/news-press-release-pdfs/2023-09-18---ald-cmd-2023-press-release.pdf?rev=6c3b9223548240a09cab42569678a786 | J102: 2023-09-18 | K102: A whole merger of two lessors (legal entities, core IT migrations, headcount, real estate), not a data programme on top of existing systems, so it neither validates nor refutes the programme's build cost (X25's four scenarios). No separate data or IT platform spend is disclosed. | L102: Context: X14 (the programme's cost)
A103: ayvens_synergies_runrate_eur_m | B103: Ayvens: annual pre-tax synergies targeted by 2026 | C103: 440 | F103: EUR m a year | G103: SOURCED | H103: ALD | LeasePlan "PowerUP 2026" press release, 18 September 2023: "Total annual pre-tax synergies confirmed at EUR 440 million by 2026" (EUR 120m by 2024, 350m by 2025), evenly split between margin and procurement synergies and cost synergies | I103: https://www.ayvens.com/-/media/ayvens/public/cp/files/news-press-release-pdfs/2023-09-18---ald-cmd-2023-press-release.pdf?rev=6c3b9223548240a09cab42569678a786 | J103: 2023-09-18 | K103: A whole merger of two lessors (legal entities, core IT migrations, headcount, real estate), not a data programme on top of existing systems, so it neither validates nor refutes the programme's build cost (X25's four scenarios). | L103: Context: X14 (the programme's cost)
A104: ayvens_synergies_2024_eur_m | B104: Ayvens: synergies achieved in 2024 | C104: 121 | F104: EUR m | G104: SOURCED | H104: Ayvens Q4 and full-year 2024 results press release: "In 2024 synergies amounted to EUR 121 million" | I104: https://www.ayvens.com/en-cp/news/newsroom/press-releases-2025/ayvens-q4-and-full-year-2024-results/ | J104: FY2024 | K104: Against a plan of EUR 120m by 2024: the merger's synergy plan was delivered on schedule in its first full year. A whole merger of two lessors (legal entities, core IT migrations, headcount, real estate), not a data programme on top of existing systems, so it neither validates nor refutes the programme's build cost (X25's four scenarios). | L104: Context: X14 (the programme's cost)
A105: ayvens_remarketing_vehicles_k | B105: Ayvens: used vehicles sold a year through its multi-channel remarketing platform | C105: 600 | F105: thousand vehicles a year | G105: SOURCED | H105: ALD | LeasePlan "PowerUP 2026" press release, 18 September 2023: "its global multi-channel remarketing platform (600,000 vehicles sold p.a., access to a large range of buyers in 36 countries, of which 24,000 active traders)" | I105: https://www.ayvens.com/-/media/ayvens/public/cp/files/news-press-release-pdfs/2023-09-18---ald-cmd-2023-press-release.pdf?rev=6c3b9223548240a09cab42569678a786 | J105: 2023-09-18 | K105: A merged lessor's remarketing at scale: the real-world analogue for leak 3's resale (the used-car sale results per car are the ald_* and ayvens_* rows). | L105: Context: X14 (leak 3 analogue)
A106: sales_incentive_additions_2025_eur_m | B106: Sales-incentive provision: additions, 2025 (worldwide) | C106: 10362 | F106: EUR m | G106: SOURCED | H106: Stellantis Form 20-F FY2025, Note 21 Provisions, roll-forward table, Sales incentives line, Additional provisions, 2025 | I106: https://www.sec.gov/Archives/edgar/data/1605484/000160548426000021/stellantis-20251231.htm | J106: FY2025 | K106: Worldwide; no regional split is disclosed. The estimated cost of incentive programmes offered to dealers and consumers (cash offers, subvention, lease subsidies) is booked as a reduction of revenue when the car is sold to the dealer, and the provision is settled as the programmes are claimed and paid (Note 2, critical estimates). Price discounts at invoice need not pass through it, so it is the claims-based part of incentive spend. | L106: Leak 1 (via x14_incentive_claims_central)
A107: sales_incentive_settlements_2025_eur_m | B107: Sales-incentive provision: settlements, 2025 (worldwide) | C107: 10954 | F107: EUR m | G107: SOURCED | H107: Stellantis Form 20-F FY2025, Note 21 Provisions, roll-forward table, Sales incentives line, Settlements, 2025 | I107: https://www.sec.gov/Archives/edgar/data/1605484/000160548426000021/stellantis-20251231.htm | J107: FY2025 | K107: Worldwide; no regional split is disclosed. The estimated cost of incentive programmes offered to dealers and consumers (cash offers, subvention, lease subsidies) is booked as a reduction of revenue when the car is sold to the dealer, and the provision is settled as the programmes are claimed and paid (Note 2, critical estimates). Price discounts at invoice need not pass through it, so it is the claims-based part of incentive spend. | L107: Leak 1 (via x14_incentive_claims_central)
A108: sales_incentive_additions_2024_eur_m | B108: Sales-incentive provision: additions, 2024 (worldwide) | C108: 10229 | F108: EUR m | G108: SOURCED | H108: Stellantis Form 20-F FY2025, Note 21 Provisions, roll-forward table, Sales incentives line, Additional provisions, 2024 | I108: https://www.sec.gov/Archives/edgar/data/1605484/000160548426000021/stellantis-20251231.htm | J108: FY2024 | K108: Worldwide; no regional split is disclosed. The estimated cost of incentive programmes offered to dealers and consumers (cash offers, subvention, lease subsidies) is booked as a reduction of revenue when the car is sold to the dealer, and the provision is settled as the programmes are claimed and paid (Note 2, critical estimates). Price discounts at invoice need not pass through it, so it is the claims-based part of incentive spend. | L108: Leak 1 (via x14_incentive_claims_central)
A109: sales_incentive_settlements_2024_eur_m | B109: Sales-incentive provision: settlements, 2024 (worldwide) | C109: 10110 | F109: EUR m | G109: SOURCED | H109: Stellantis Form 20-F FY2025, Note 21 Provisions, roll-forward table, Sales incentives line, Settlements, 2024 | I109: https://www.sec.gov/Archives/edgar/data/1605484/000160548426000021/stellantis-20251231.htm | J109: FY2024 | K109: Worldwide; no regional split is disclosed. The estimated cost of incentive programmes offered to dealers and consumers (cash offers, subvention, lease subsidies) is booked as a reduction of revenue when the car is sold to the dealer, and the provision is settled as the programmes are claimed and paid (Note 2, critical estimates). Price discounts at invoice need not pass through it, so it is the claims-based part of incentive spend. | L109: Leak 1 (via x14_incentive_claims_central)
A110: sales_incentive_provision_2025_eur_m | B110: Sales-incentive provision at 31 December 2025 (worldwide) | C110: 5321 | F110: EUR m | G110: SOURCED | H110: Stellantis Form 20-F FY2025, Note 21 Provisions, Sales incentives, total at 31 December 2025 (2024: 6,343) | I110: https://www.sec.gov/Archives/edgar/data/1605484/000160548426000021/stellantis-20251231.htm | J110: 2025-12-31 | K110: A balance, not a year's spend: incentives accrued on cars sold to dealers and not yet claimed. Worldwide; no regional split is disclosed. The estimated cost of incentive programmes offered to dealers and consumers (cash offers, subvention, lease subsidies) is booked as a reduction of revenue when the car is sold to the dealer, and the provision is settled as the programmes are claimed and paid (Note 2, critical estimates). Price discounts at invoice need not pass through it, so it is the claims-based part of incentive spend. | L110: Context: X14
A111: group_revenue_2024_eur_m | B111: Group net revenues, 2024 | C111: 156878 | F111: EUR m | G111: SOURCED | H111: Stellantis Form 20-F FY2025, Note 29 related parties, 'Total for the Company' net revenues, 2024 (also the consolidated income statement) | I111: https://www.sec.gov/Archives/edgar/data/1605484/000160548426000021/stellantis-20251231.htm | J111: FY2024 | K111: The denominator for the 2024 incentive ratios. | L111: Leak 1 (via x14_incentive_claims_central)
A112: eca_error_complex_rules_2024 | B112: EU budget: estimated error in spending under complex rules, mainly reimbursement claims, 2024 | C112: 5.2 | F112: % | G112: SOURCED | H112: European Court of Auditors, 2024 EU audit in brief, printed p. 6 (the Court's opinion) and p. 13 (Figure 3): "expenditure subject to complex rules, mainly reimbursement-based, in which the estimated level of error is 5.2 %" (2023: 7.9%) | I112: https://www.eca.europa.eu/ECAPublications/AR-2024-AIB/AR-2024-AIB_EN.pdf | J112: FY2024 | K112: An audited error rate in payments made on beneficiaries' claims for eligible costs, after national controls: an analogue for dealer incentive claims, not a carmaker's figure. Entitlement-based payments (simple conditions) were below 2%. Brackets process_leak_pct: our 2% sits at the simple-rules end. | L112: Context: X14 (a benchmark for process_leak_pct)
A113: eca_error_overall_2024 | B113: EU budget: overall estimated level of error, 2024 | C113: 3.6 | F113: % | G113: SOURCED | H113: European Court of Auditors, 2024 EU audit in brief, printed p. 4: "Our estimate of the level of error in EU budget spending is at 3.6 % (2023: 5.6 %)"; printed p. 12: between 2.6% and 4.6% | I113: https://www.eca.europa.eu/ECAPublications/AR-2024-AIB/AR-2024-AIB_EN.pdf | J113: FY2024 | K113: All audited EU spending, claim-based and entitlement-based. An analogue, not a carmaker's figure. | L113: Context: X14 (a benchmark for process_leak_pct)
A114: process_leak_pct | B114: Claims paid twice, wrongly or too late, as a share of incentive spend | C114: 2 | D114: 0.5 | E114: 5 | F114: % | G114: ASSUMPTION | H114: Our estimate | J114: 2026-09-17 | K114: Benchmarks in circulation (2-5%) are US and unverified, so this is an assumption and not a sourced figure. Audited analogue (X14): the European Court of Auditors' 2024 error rate on EU spending paid on claims under complex rules was 5.2%, below 2% for simple entitlement payments (eca_error_*); our 2% sits at the simple-rules end. | L114: Leak 1
A115: recoverable_share | B115: Share of process leakage a controls layer actually recovers | C115: 30 | D115: 10 | E115: 50 | F115: % | G115: ASSUMPTION | H115: Our estimate, anchored on the EU's audited corrections (ec_cohesion_*) | J115: 2026-09-27 | K115: Leakage that exists is not leakage you can recover. The anchor: in EU cohesion spending, paid on beneficiaries' claims, corrections after payment recover about two-fifths of the error found (risk at payment 2.9%, at closure 1.8%; future corrections 0.5-1.4 points, a sixth to a half: ec_cohesion_*), with a legal right to claw back over years. Our 30% sits just below it and the range spans it. A public-funds analogue, not a carmaker's figure; the pilot's certified baseline replaces it. | L115: Leak 1
A116: targeting_leak_pct | B116: Incentives paid on sales that would have happened anyway | C116: 10 | D116: 5 | E116: 20 | F116: % | G116: ASSUMPTION | H116: Our estimate | J116: 2026-09-17 | K116: Only measurable with randomised holdouts; the ledger is what makes that measurable. Replaced in leak 1 on 26 September by x5_targeting_gain_central, derived in analysis/optimal_incentive_report.md; kept so the comparison there can be recomputed. | L116: Context: leak 1 (replaced by X5)
A117: thin_share_of_book | B117: Share of the buy-back book with little history | C117: 25 | D117: 10 | E117: 40 | F117: % | G117: ASSUMPTION | H117: Our estimate | J117: 2026-09-17 | K117: New brands, new markets and electrified lines with little resale history. Directionally supported by the 20-F statement that LEVs are an increasing proportion of buy-back assets. X9: the electrified part alone, the group's battery-EV plus plug-in share of its 2024 EU registrations (x9_group_bev_share_2024, x9_group_phev_share_2024), sits inside this range; the buy-back book's own mix is not published (its buyers are named only where they are the group's own leasing and rental joint ventures), so the range stands. | L117: Leak 3
A118: finance_penetration | B118: SFSE penetration: share of the group's new cars registered in its European markets that SFSE financed, 2025 | C118: 28.9 | F118: % | G118: SOURCED | H118: Stellantis Financial Services Europe, Rapport Annuel 2025, p. 9 (Europe): "une pénétration qui s'élève à 28,9%" | I118: https://www.stellantisfinancialservices.com/pdf/Rapport%20Annuel%20SFSE%202025.pdf | J118: 2025 | K118: SFSE new-car financings (cars and vans: credit sale, LOA, B2C long-term rental, subscription) over new-car registrations of the group's brands in SFSE's European markets (the definition: SFSE 2023 annual results, p. 7). Excludes Leasys, which has held the B2B long-term leases since April 2023. Second half of 2025: 30.4%. By country from 21.9% (Spain) to 56.7% (Austria). Legacy Banque PSA Finance: bpf_penetration_2021. Replaced our 40% (30-50%) ASSUMPTION on 26 September (X14). Leak 2 uses the contract count itself (sfse_eu_nv_contracts_2025). X5 reads this rate as g, the share of cars whose resale the group bears: a proxy, not a bound. A loan leaves the resale with the buyer, while buy-back sales and Leasys, outside this rate, leave it with the group. | L118: Context: X5 (g, the optimal incentive); leak 2's base is sfse_eu_nv_contracts_2025
A119: sfse_eu_nv_contracts_2025 | B119: New-car financing contracts SFSE wrote for the group's brands in Europe, 2025 | C119: 646138 | F119: contracts | G119: SOURCED | H119: Stellantis Financial Services Europe, Rapport Annuel 2025, p. 9 (Europe): "le nombre de contrats de financements de véhicules neufs pour les marques du Groupe s'établit à 646 138 en 2025" | I119: https://www.stellantisfinancialservices.com/pdf/Rapport%20Annuel%20SFSE%202025.pdf | J119: 2025 | K119: Cars and vans: credit sale, LOA (lease with purchase option), B2C long-term rental, flexible rental, subscription. Leasys B2B long-term leases are excluded (multi-brand; the group's share not disclosed), so leak 2 counts no fleet lease. Europe is SFSE's markets: France, Germany, the UK, Italy, Spain, Belgium-Luxembourg, the Netherlands, Portugal, Austria, Poland. Each contract ends in a moment to offer the next car; a year's new contracts stand in for a year's contract ends. The contracts sit in 50/50 joint ventures with Santander CF and BNP Paribas PF (Portugal a white-label agreement), so the customer data is shared with a partner bank. | L119: Leak 2
A120: bpf_penetration_2021 | B120: Banque PSA Finance penetration, legacy PSA and Opel brands, 2021 | C120: 31.9 | F120: % | G120: SOURCED | H120: Banque PSA Finance, Rapport annuel 2021, management report p. 17: "En 2021, Banque PSA Finance (BPF) a financé 31,9% des ventes de véhicules neufs du Groupe" | I120: https://www.stellantisfinancialservices.com/pdf/2021%20FR%20Rapport%20annuel.pdf | J120: 2021 | K120: Peugeot, Citroen, DS, Opel and Vauxhall only, before the 2023 finance restructuring; excluding China. History for finance_penetration. | L120: Context: X14
A121: fla_uk_private_new_pos_share | B121: UK: share of private new-car purchases funded by FLA members at the point of sale, year to March 2026 | C121: 88 | F121: % | G121: SOURCED | H121: Finance & Leasing Association, consumer car finance statistics for March 2026 (published 12 May 2026): "FLA members funding close to 88% of private new car purchases over the past year" | I121: https://fla.org.uk/news/consumer-car-finance-new-business-volumes-grew-by-8-in-march-2026/ | J121: 2026-03 | K121: UK, the whole market, private buyers only, every lender: not the group's rate. The group's UK rate over all its registrations was 22.8% in 2025, over 62% in B2C (SFSE 2025, p. 9). A rate over all registrations mixes private buyers with fleets, many of them ineligible for finance. | L121: Context: X14
A122: sfse_pen_fr_2025 | B122: SFSE penetration, France, 2025 | C122: 27.5 | F122: % | G122: SOURCED | H122: Stellantis Financial Services Europe, Rapport Annuel 2025, p. 9: "le nombre de contrats s'établit à 154 496, soit une pénétration de 27,5%" | I122: https://www.stellantisfinancialservices.com/pdf/Rapport%20Annuel%20SFSE%202025.pdf | J122: 2025 | K122: SFSE new-car financings of the group's brands over their new-car registrations (cars and vans) in the market, excluding Leasys's B2B long-term leases. Second half 31%. B2C 68.1% (sfse_pen_fr_b2c_2025). | L122: Context: X14 (the pilot by market)
A123: sfse_contracts_fr_2025 | B123: SFSE new-car financing contracts, France, 2025 | C123: 154496 | F123: contracts | G123: SOURCED | H123: Stellantis Financial Services Europe, Rapport Annuel 2025, p. 9: "le nombre de contrats s'établit à 154 496, soit une pénétration de 27,5%" | I123: https://www.stellantisfinancialservices.com/pdf/Rapport%20Annuel%20SFSE%202025.pdf | J123: 2025 | K123: SFSE new-car financings of the group's brands over their new-car registrations (cars and vans) in the market, excluding Leasys's B2B long-term leases. The one large market with a disclosed count. | L123: Context: X14 (the pilot by market)
A124: sfse_pen_fr_b2c_2025 | B124: SFSE penetration of private (B2C) sales, France, 2025 | C124: 68.1 | F124: % | G124: SOURCED | H124: Stellantis Financial Services Europe, Rapport Annuel 2025, p. 9: "Sur le B2C, la pénétration atteint 68,1%" | I124: https://www.stellantisfinancialservices.com/pdf/Rapport%20Annuel%20SFSE%202025.pdf | J124: 2025 | K124: SFSE new-car financings of the group's brands over their new-car registrations (cars and vans) in the market, excluding Leasys's B2B long-term leases. Private buyers only; the rest of registrations are B2B, many ineligible for finance. | L124: Context: X14 (the pilot by market)
A125: sfse_pen_de_2025 | B125: SFSE penetration, Germany, 2025 (a floor) | C125: 33.8 | F125: % | G125: SOURCED | H125: Stellantis Financial Services Europe, Rapport Annuel 2025, p. 9: "les performances se maintiennent à un haut niveau de pénétration, à plus de 33,8%" | I125: https://www.stellantisfinancialservices.com/pdf/Rapport%20Annuel%20SFSE%202025.pdf | J125: 2025 | K125: SFSE new-car financings of the group's brands over their new-car registrations (cars and vans) in the market, excluding Leasys's B2B long-term leases. The report says more than 33.8%, so a floor. | L125: Context: X14 (the pilot by market)
A126: sfse_pen_gb_2025 | B126: SFSE penetration, UK, 2025 | C126: 22.8 | F126: % | G126: SOURCED | H126: Stellantis Financial Services Europe, Rapport Annuel 2025, p. 9: "avec une pénétration de 22,8 %, soit en hausse de 1,1 points" | I126: https://www.stellantisfinancialservices.com/pdf/Rapport%20Annuel%20SFSE%202025.pdf | J126: 2025 | K126: SFSE new-car financings of the group's brands over their new-car registrations (cars and vans) in the market, excluding Leasys's B2B long-term leases. B2C over 62%. | L126: Context: X14 (the pilot by market)
A127: sfse_pen_es_2025 | B127: SFSE penetration, Spain, 2025 | C127: 21.9 | F127: % | G127: SOURCED | H127: Stellantis Financial Services Europe, Rapport Annuel 2025, p. 10: "les performances s'améliorent par rapport à 2024 avec une pénétration à 21,9%" | I127: https://www.stellantisfinancialservices.com/pdf/Rapport%20Annuel%20SFSE%202025.pdf | J127: 2025 | K127: SFSE new-car financings of the group's brands over their new-car registrations (cars and vans) in the market, excluding Leasys's B2B long-term leases. Second half 26.9%; a large share of B2B is key-account and direct sales. | L127: Context: X14 (the pilot by market)
A128: sfse_pen_it_2025 | B128: SFSE penetration, Italy, 2025 | C128: 28.6 | F128: % | G128: SOURCED | H128: Stellantis Financial Services Europe, Rapport Annuel 2025, p. 10: "la pénétration se maintient à 28,6%" | I128: https://www.stellantisfinancialservices.com/pdf/Rapport%20Annuel%20SFSE%202025.pdf | J128: 2025 | K128: SFSE new-car financings of the group's brands over their new-car registrations (cars and vans) in the market, excluding Leasys's B2B long-term leases. | L128: Context: X14 (the pilot by market)
A129: sfse_pen_be_lu_2025 | B129: SFSE penetration, Belgium and Luxembourg, 2025 | C129: 26.6 | F129: % | G129: SOURCED | H129: Stellantis Financial Services Europe, Rapport Annuel 2025, p. 10: "avec une pénétration stabilisée à 26,6 %" | I129: https://www.stellantisfinancialservices.com/pdf/Rapport%20Annuel%20SFSE%202025.pdf | J129: 2025 | K129: SFSE new-car financings of the group's brands over their new-car registrations (cars and vans) in the market, excluding Leasys's B2B long-term leases. B2C 38.4%. | L129: Context: X14 (the pilot by market)
... A133: sfse_pen_pl_2025 | B133: SFSE penetration, Poland, 2025 | C133: 48.8 | F133: % | G133: SOURCED | H133: Stellantis Financial Services Europe, Rapport Annuel 2025, p. 10: "avec un taux de pénétration de 48,8 %" | I133: https://www.stellantisfinancialservices.com/pdf/Rapport%20Annuel%20SFSE%202025.pdf | J133: 2025 | K133: SFSE new-car financings of the group's brands over their new-car registrations (cars and vans) in the market, excluding Leasys's B2B long-term leases. | L133: Context: X14 (the pilot by market)
A134: upgrade_capture_uplift | B134: Extra share of customers retained by contacting them at the right moment | C134: 3 | D134: 1 | E134: 6 | F134: percentage points | G134: ASSUMPTION | H134: Our estimate | J134: 2026-09-17 | K134: Must be proved with randomised control groups in the pilot rather than assumed at scale. | L134: Leak 2
A135: margin_per_repeat_sale | B135: Contribution from one retained customer's next car | C135: 2000 | D135: 1000 | E135: 3500 | F135: EUR | G135: ASSUMPTION | H135: Our estimate | J135: 2026-09-17 | K135: New-car margin plus finance income over the contract; excludes service and warranty. | L135: Leak 2
A136: loan_deposit_pct | B136: Deposit on a typical financed contract | C136: 15 | D136: 10 | E136: 25 | F136: % | G136: ASSUMPTION | H136: Our estimate | J136: 2026-09-17 | K136: Used only to locate the month when the car is worth more than the balance. | L136: Leak 2
A137: loan_term_months | B137: Term of a typical financed contract | C137: 48 | D137: 36 | E137: 60 | F137: months | G137: ASSUMPTION | H137: Our estimate | J137: 2026-09-17 | K137: As above. | L137: Leak 2
A138: loan_apr | B138: Interest rate on a typical financed contract | C138: 7 | D138: 4 | E138: 10 | F138: % | G138: ASSUMPTION | H138: Our estimate | J138: 2026-09-17 | K138: As above. | L138: Leak 2
A139: new_car_price | B139: List price of the worked example car | C139: 10420 | F139: GBP | G139: MEASURED | H139: analysis/one_car_report.md - Vauxhall Corsa entry price for the 2022 cohort | J139: 2026-09-17 | K139: DVM-CAR entry trim. Used only to make the upgrade-timing example concrete. | L139: Leak 2
A140: dep_pi_lo | B140: Depreciation per year - low end of the 95% prediction interval | C140: -13.1 | F140: % | G140: MEASURED | H140: analysis/drivers_report.md pooled effects table | J140: 2026-09-17 | K140: Where the age effect would fall in a market we have not measured. Wider than the confidence interval on the mean and the right number for a new market. | L140: Leak 3
A141: dep_pi_hi | B141: Depreciation per year - high end of the 95% prediction interval | C141: -5 | F141: % | G141: MEASURED | H141: analysis/drivers_report.md pooled effects table | J141: 2026-09-17 | K141: As above. | L141: Leak 3
A142: ev_pi_lo | B142: Electric vs petrol - low end of the 95% prediction interval | C142: -38 | F142: % | G142: MEASURED | H142: analysis/drivers_report.md pooled effects table | J142: 2026-09-17 | K142: Four datasets only. We cannot say what an electric car is worth against a petrol one in an unmeasured market - the same uncertainty Stellantis reports for electrified residuals. | L142: Context
A143: ev_pi_hi | B143: Electric vs petrol - high end of the 95% prediction interval | C143: 59.9 | F143: % | G143: MEASURED | H143: analysis/drivers_report.md pooled effects table | J143: 2026-09-17 | K143: As above. | L143: Context
A144: er_pairs_measured | B144: Confirmed duplicate pairs behind the entity-resolution test | C144: 276902 | F144: pairs | G144: MEASURED | H144: analysis/entity_resolution_report.md | J144: 2026-09-17 | K144: Five sources in four countries, each carrying the site's own advert id, which is hidden before matching. An advert relisted under a new id counts as two records, so this is a lower bound. | L144: Context
...

Sheet Summary
A1: Value at risk - summary
A2: EUR millions a year, in two measures (X18): expected a year, what to budget, and in a one-in-ten-year market, what a bad year costs. They sit side by side and are never added. Every cell is a formula over the Assumptions sheet; change an input there and this moves.
B4: expected a year | C4: in a one-in-ten-year market | F4: what drives it
A5: Leak 1 - incentives paid wrongly or needlessly | B5: =(eu_revenue_eur_m * x14_incentive_claims_central/100 * process_leak_pct/100 + eu_revenue_eur_m * x5_targeting_gain_central/100) -> 142.06381 | C5: =(eu_revenue_eur_m * x14_incentive_claims_central/100 * process_leak_pct/100 + eu_revenue_eur_m * x5_targeting_gain_central/100) -> 142.06381 | F5: claims base disclosed (worldwide), leak rate assumed; targeting derived from published studies
A6: Leak 2 - upgrade moments missed | B6: =sfse_eu_nv_contracts_2025 * upgrade_capture_uplift/100 * margin_per_repeat_sale / 1000000 -> 38.76828 | C6: =sfse_eu_nv_contracts_2025 * upgrade_capture_uplift/100 * margin_per_repeat_sale / 1000000 -> 38.76828 | F6: timing is measured, the euro conversion is assumed
A7: Leak 3 - residual value | B7: =(buyback_payables_current_eur_m * MAX(0, x18_exp_twosided_book)/100 + buyback_payables_current_eur_m * (x17_days_cut * x17_day_cost_central/10000 + x17_share_routed/100 * x17_channel_gain_after_costs/100)) -> 24.81171 | C7: =((buyback_payables_current_eur_m * (ABS(level_1y_p10_book)/100 + (curve_1y_p80_known/2/retained_1y_pooled * (1 - thin_share_of_book/100) + curve_1y_p80_unknown/2/retained_1y_pooled * thin_share_of_book/100))) * x18_joint_share_book/100 + buyback_payables_current_eur_m * (x17_days_cut * x17_day_cost_central/10000 + x17_share_routed/100 * x17_channel_gain_after_costs/100)) -> 117.28313 | F7: book due within a year disclosed. Expected: the level and curve count both ways and gained on the book's record, so zero, plus resale execution. One in ten: their joint p10, measured, plus execution
A8: Total value at risk a year | B8: =(eu_revenue_eur_m * x14_incentive_claims_central/100 * process_leak_pct/100 + eu_revenue_eur_m * x5_targeting_gain_central/100) + sfse_eu_nv_contracts_2025 * upgrade_capture_uplift/100 * margin_per_repeat_sale / 1000000 + (buyback_payables_current_eur_m * MAX(0, x18_exp_twosided_book)/100 + buyback_payables_current_eur_m * (x17_days_cut * x17_day_cost_central/10000 + x17_share_routed/100 * x17_channel_gain_after_costs/100)) -> 205.6438 | C8: =(eu_revenue_eur_m * x14_incentive_claims_central/100 * process_leak_pct/100 + eu_revenue_eur_m * x5_targeting_gain_central/100) + sfse_eu_nv_contracts_2025 * upgrade_capture_uplift/100 * margin_per_repeat_sale / 1000000 + ((buyback_payables_current_eur_m * (ABS(level_1y_p10_book)/100 + (curve_1y_p80_known/2/retained_1y_pooled * (1 - thin_share_of_book/100) + curve_1y_p80_unknown/2/retained_1y_pooled * thin_share_of_book/100))) * x18_joint_share_book/100 + buyback_payables_current_eur_m * (x17_days_cut * x17_day_cost_central/10000 + x17_share_routed/100 * x17_channel_gain_after_costs/100)) -> 298.11522 | F8: the two columns answer different questions; never add or average them
A9: Upper end, in no total | B9: =(eu_revenue_eur_m * x14_incentive_claims_central/100 * process_leak_pct/100 + eu_revenue_eur_m * x5_targeting_gain_central/100) + sfse_eu_nv_contracts_2025 * upgrade_capture_uplift/100 * margin_per_repeat_sale / 1000000 + (buyback_payables_current_eur_m * MAX(0, x18_exp_twosided_book)/100 + buyback_payables_current_eur_m * (x17_days_cut * x17_day_cost_central/10000 + x17_share_routed/100 * x17_channel_gain_after_costs/100)) + buyback_payables_current_eur_m * x18_exp_onesided_book/100 -> 266.69017 | C9: =(eu_revenue_eur_m * x14_incentive_claims_central/100 * process_leak_pct/100 + eu_revenue_eur_m * x5_targeting_gain_central/100) + sfse_eu_nv_contracts_2025 * upgrade_capture_uplift/100 * margin_per_repeat_sale / 1000000 + (buyback_payables_current_eur_m * (ABS(level_1y_p10_book)/100 + (curve_1y_p80_known/2/retained_1y_pooled * (1 - thin_share_of_book/100) + curve_1y_p80_unknown/2/retained_1y_pooled * thin_share_of_book/100)) + buyback_payables_current_eur_m * (x17_days_cut * x17_day_cost_central/10000 + x17_share_routed/100 * x17_channel_gain_after_costs/100)) -> 339.85486 | F9: expected: as if every buy-back were a customer's put at the residual; one in ten: the level and the curve at their p10s at once
A10: Stress: the whole book in a core market's bad year (-4.5%) | C10: =(eu_revenue_eur_m * x14_incentive_claims_central/100 * process_leak_pct/100 + eu_revenue_eur_m * x5_targeting_gain_central/100) + sfse_eu_nv_contracts_2025 * upgrade_capture_uplift/100 * margin_per_repeat_sale / 1000000 + ((buyback_payables_current_eur_m * (ABS(level_1y_p10_core)/100 + (curve_1y_p80_known/2/retained_1y_pooled * (1 - thin_share_of_book/100) + curve_1y_p80_unknown/2/retained_1y_pooled * thin_share_of_book/100))) * x18_joint_share_stress/100 + buyback_payables_current_eur_m * (x17_days_cut * x17_day_cost_central/10000 + x17_share_routed/100 * x17_channel_gain_after_costs/100)) -> 455.94236 | F10: a Europe-wide bad year as deep as a core market's one-in-ten; the book's short history lacks one
A11: Stress, upper end, in no total | C11: =(eu_revenue_eur_m * x14_incentive_claims_central/100 * process_leak_pct/100 + eu_revenue_eur_m * x5_targeting_gain_central/100) + sfse_eu_nv_contracts_2025 * upgrade_capture_uplift/100 * margin_per_repeat_sale / 1000000 + (buyback_payables_current_eur_m * (ABS(level_1y_p10_core)/100 + (curve_1y_p80_known/2/retained_1y_pooled * (1 - thin_share_of_book/100) + curve_1y_p80_unknown/2/retained_1y_pooled * thin_share_of_book/100)) + buyback_payables_current_eur_m * (x17_days_cut * x17_day_cost_central/10000 + x17_share_routed/100 * x17_channel_gain_after_costs/100)) -> 503.97343 | F11: the same with the level and the curve at their p10s at once
A12: Total without the targeting line | B12: =(eu_revenue_eur_m * x14_incentive_claims_central/100 * process_leak_pct/100 + eu_revenue_eur_m * x5_targeting_gain_central/100) + sfse_eu_nv_contracts_2025 * upgrade_capture_uplift/100 * margin_per_repeat_sale / 1000000 + (buyback_payables_current_eur_m * MAX(0, x18_exp_twosided_book)/100 + buyback_payables_current_eur_m * (x17_days_cut * x17_day_cost_central/10000 + x17_share_routed/100 * x17_channel_gain_after_costs/100)) - eu_revenue_eur_m * x5_targeting_gain_central/100 -> 141.57354 | C12: =(eu_revenue_eur_m * x14_incentive_claims_central/100 * process_leak_pct/100 + eu_revenue_eur_m * x5_targeting_gain_central/100) + sfse_eu_nv_contracts_2025 * upgrade_capture_uplift/100 * margin_per_repeat_sale / 1000000 + ((buyback_payables_current_eur_m * (ABS(level_1y_p10_book)/100 + (curve_1y_p80_known/2/retained_1y_pooled * (1 - thin_share_of_book/100) + curve_1y_p80_unknown/2/retained_1y_pooled * thin_share_of_book/100))) * x18_joint_share_book/100 + buyback_payables_current_eur_m * (x17_days_cut * x17_day_cost_central/10000 + x17_share_routed/100 * x17_channel_gain_after_costs/100)) - eu_revenue_eur_m * x5_targeting_gain_central/100 -> 234.04496 | F12: paying buyers who would buy anyway is the cost of any incentive
A14: What the programme gets back (the Benefits sheet, X21)
A15: Addressable: what the levers can reach, every source | B15: =eu_revenue_eur_m * x14_incentive_claims_central/100 * process_leak_pct/100 + eu_revenue_eur_m * x5_targeting_gain_central/100 * finance_penetration/100 + sfse_eu_nv_contracts_2025 * upgrade_capture_uplift/100 * margin_per_repeat_sale / 1000000 + buyback_payables_current_eur_m * (x17_days_cut * x17_day_cost_central/10000 + x17_share_routed/100 * x17_channel_gain_after_costs/100) + buyback_payables_current_eur_m * MAX(0, x18_exp_twosided_book)/100 -> 160.08984 | C15: - | F15: reach, not benefit (the Data reach sheet, X20)
A16: Planned benefit, committed levers | B16: =(eu_revenue_eur_m * x14_incentive_claims_central/100 * process_leak_pct/100 * recoverable_share/100) + (sfse_eu_nv_contracts_2025 * upgrade_capture_uplift/100 * margin_per_repeat_sale / 1000000) + (buyback_payables_current_eur_m * x17_days_cut * x17_day_cost_central/10000) + (buyback_payables_current_eur_m * x17_share_routed/100 * x17_channel_gain_after_costs/100) -> 86.978055 | C16: =(eu_revenue_eur_m * x14_incentive_claims_central/100 * process_leak_pct/100 * recoverable_share/100) + (sfse_eu_nv_contracts_2025 * upgrade_capture_uplift/100 * margin_per_repeat_sale / 1000000) + (buyback_payables_current_eur_m * x17_days_cut * x17_day_cost_central/10000) + (buyback_payables_current_eur_m * x17_share_routed/100 * x17_channel_gain_after_costs/100) + buyback_payables_current_eur_m * thin_share_of_book/100 * (curve_1y_p80_unknown - curve_1y_p80_known)/2/retained_1y_pooled * x18_joint_share_book/100 -> 107.6398 | F16: claims controls, retention, resale execution; one year in ten adds the little-history cut
A17: The same at the reference class | B17: =(1-mckox_sw_benefit_shortfall_pct/100) * ((eu_revenue_eur_m * x14_incentive_claims_central/100 * process_leak_pct/100 * recoverable_share/100) + (sfse_eu_nv_contracts_2025 * upgrade_capture_uplift/100 * margin_per_repeat_sale / 1000000) + (buyback_payables_current_eur_m * x17_days_cut * x17_day_cost_central/10000) + (buyback_payables_current_eur_m * x17_share_routed/100 * x17_channel_gain_after_costs/100)) -> 72.191786 | C17: =(1-mckox_sw_benefit_shortfall_pct/100) * ((eu_revenue_eur_m * x14_incentive_claims_central/100 * process_leak_pct/100 * recoverable_share/100) + (sfse_eu_nv_contracts_2025 * upgrade_capture_uplift/100 * margin_per_repeat_sale / 1000000) + (buyback_payables_current_eur_m * x17_days_cut * x17_day_cost_central/10000) + (buyback_payables_current_eur_m * x17_share_routed/100 * x17_channel_gain_after_costs/100) + buyback_payables_current_eur_m * thin_share_of_book/100 * (curve_1y_p80_unknown - curve_1y_p80_known)/2/retained_1y_pooled * x18_joint_share_book/100) -> 89.341036 | F17: large software projects fall short of their benefits on average (McKinsey-Oxford)
A18: Certified today | B18: 0 | C18: 0 | F18: every committed rate is an assumption; Finance certifies from Phase 1
A21: Range from the assumed inputs
B22: low | C22: base | D22: high
A23: Leak 1 | B23: =(eu_revenue_eur_m * x14_incentive_claims_low/100 * Assumptions!$D$114/100 + eu_revenue_eur_m * x5_targeting_gain_low/100) -> 48.818185 | C23: =(eu_revenue_eur_m * x14_incentive_claims_central/100 * process_leak_pct/100 + eu_revenue_eur_m * x5_targeting_gain_central/100) -> 142.06381 | D23: =(eu_revenue_eur_m * x14_incentive_claims_high/100 * Assumptions!$E$114/100 + eu_revenue_eur_m * x5_targeting_gain_high/100) -> 325.08867
A24: Leak 2 | B24: =sfse_eu_nv_contracts_2025 * Assumptions!$D$134/100 * Assumptions!$D$135 / 1000000 -> 6.46138 | C24: =sfse_eu_nv_contracts_2025 * upgrade_capture_uplift/100 * margin_per_repeat_sale / 1000000 -> 38.76828 | D24: =sfse_eu_nv_contracts_2025 * Assumptions!$E$134/100 * Assumptions!$E$135 / 1000000 -> 135.68898
A25: Leak 3, expected a year | B25: =(buyback_payables_current_eur_m * MAX(0, x18_exp_twosided_book)/100 + buyback_payables_current_eur_m * (Assumptions!$D$685 * x17_day_cost_low/10000 + Assumptions!$D$686/100 * x17_channel_gain_after_costs/100)) -> 10.99791 | C25: =(buyback_payables_current_eur_m * MAX(0, x18_exp_twosided_book)/100 + buyback_payables_current_eur_m * (x17_days_cut * x17_day_cost_central/10000 + x17_share_routed/100 * x17_channel_gain_after_costs/100)) -> 24.81171 | D25: =(buyback_payables_current_eur_m * MAX(0, x18_exp_twosided_book)/100 + buyback_payables_current_eur_m * (Assumptions!$E$685 * x17_day_cost_high/10000 + Assumptions!$E$686/100 * x17_channel_gain_before_opex/100)) -> 125.81184
A26: Leak 3, one year in ten | B26: =((buyback_payables_current_eur_m * (ABS(level_1y_p10_book)/100 + (curve_1y_p80_known/2/retained_1y_pooled * (1 - Assumptions!$D$117/100) + curve_1y_p80_unknown/2/retained_1y_pooled * Assumptions!$D$117/100))) * x18_joint_share_book/100 + buyback_payables_current_eur_m * (Assumptions!$D$685 * x17_day_cost_low/10000 + Assumptions!$D$686/100 * x17_channel_gain_after_costs/100)) -> 91.072282 | C26: =((buyback_payables_current_eur_m * (ABS(level_1y_p10_book)/100 + (curve_1y_p80_known/2/retained_1y_pooled * (1 - thin_share_of_book/100) + curve_1y_p80_unknown/2/retained_1y_pooled * thin_share_of_book/100))) * x18_joint_share_book/100 + buyback_payables_current_eur_m * (x17_days_cut * x17_day_cost_central/10000 + x17_share_routed/100 * x17_channel_gain_after_costs/100)) -> 117.28313 | D26: =((buyback_payables_current_eur_m * (ABS(level_1y_p10_book)/100 + (curve_1y_p80_known/2/retained_1y_pooled * (1 - Assumptions!$E$117/100) + curve_1y_p80_unknown/2/retained_1y_pooled * Assumptions!$E$117/100))) * x18_joint_share_book/100 + buyback_payables_current_eur_m * (Assumptions!$E$685 * x17_day_cost_high/10000 + Assumptions!$E$686/100 * x17_channel_gain_before_opex/100)) -> 230.68031
A27: Total, expected a year | B27: =(eu_revenue_eur_m * x14_incentive_claims_low/100 * Assumptions!$D$114/100 + eu_revenue_eur_m * x5_targeting_gain_low/100) + sfse_eu_nv_contracts_2025 * Assumptions!$D$134/100 * Assumptions!$D$135 / 1000000 + (buyback_payables_current_eur_m * MAX(0, x18_exp_twosided_book)/100 + buyback_payables_current_eur_m * (Assumptions!$D$685 * x17_day_cost_low/10000 + Assumptions!$D$686/100 * x17_channel_gain_after_costs/100)) -> 66.277475 | C27: =(eu_revenue_eur_m * x14_incentive_claims_central/100 * process_leak_pct/100 + eu_revenue_eur_m * x5_targeting_gain_central/100) + sfse_eu_nv_contracts_2025 * upgrade_capture_uplift/100 * margin_per_repeat_sale / 1000000 + (buyback_payables_current_eur_m * MAX(0, x18_exp_twosided_book)/100 + buyback_payables_current_eur_m * (x17_days_cut * x17_day_cost_central/10000 + x17_share_routed/100 * x17_channel_gain_after_costs/100)) -> 205.6438 | D27: =(eu_revenue_eur_m * x14_incentive_claims_high/100 * Assumptions!$E$114/100 + eu_revenue_eur_m * x5_targeting_gain_high/100) + sfse_eu_nv_contracts_2025 * Assumptions!$E$134/100 * Assumptions!$E$135 / 1000000 + (buyback_payables_current_eur_m * MAX(0, x18_exp_twosided_book)/100 + buyback_payables_current_eur_m * (Assumptions!$E$685 * x17_day_cost_high/10000 + Assumptions!$E$686/100 * x17_channel_gain_before_opex/100)) -> 586.58949
A28: Total, one year in ten | B28: =(eu_revenue_eur_m * x14_incentive_claims_low/100 * Assumptions!$D$114/100 + eu_revenue_eur_m * x5_targeting_gain_low/100) + sfse_eu_nv_contracts_2025 * Assumptions!$D$134/100 * Assumptions!$D$135 / 1000000 + ((buyback_payables_current_eur_m * (ABS(level_1y_p10_book)/100 + (curve_1y_p80_known/2/retained_1y_pooled * (1 - Assumptions!$D$117/100) + curve_1y_p80_unknown/2/retained_1y_pooled * Assumptions!$D$117/100))) * x18_joint_share_book/100 + buyback_payables_current_eur_m * (Assumptions!$D$685 * x17_day_cost_low/10000 + Assumptions!$D$686/100 * x17_channel_gain_after_costs/100)) -> 146.35185 | C28: =(eu_revenue_eur_m * x14_incentive_claims_central/100 * process_leak_pct/100 + eu_revenue_eur_m * x5_targeting_gain_central/100) + sfse_eu_nv_contracts_2025 * upgrade_capture_uplift/100 * margin_per_repeat_sale / 1000000 + ((buyback_payables_current_eur_m * (ABS(level_1y_p10_book)/100 + (curve_1y_p80_known/2/retained_1y_pooled * (1 - thin_share_of_book/100) + curve_1y_p80_unknown/2/retained_1y_pooled * thin_share_of_book/100))) * x18_joint_share_book/100 + buyback_payables_current_eur_m * (x17_days_cut * x17_day_cost_central/10000 + x17_share_routed/100 * x17_channel_gain_after_costs/100)) -> 298.11522 | D28: =(eu_revenue_eur_m * x14_incentive_claims_high/100 * Assumptions!$E$114/100 + eu_revenue_eur_m * x5_targeting_gain_high/100) + sfse_eu_nv_contracts_2025 * Assumptions!$E$134/100 * Assumptions!$E$135 / 1000000 + ((buyback_payables_current_eur_m * (ABS(level_1y_p10_book)/100 + (curve_1y_p80_known/2/retained_1y_pooled * (1 - Assumptions!$E$117/100) + curve_1y_p80_unknown/2/retained_1y_pooled * Assumptions!$E$117/100))) * x18_joint_share_book/100 + buyback_payables_current_eur_m * (Assumptions!$E$685 * x17_day_cost_high/10000 + Assumptions!$E$686/100 * x17_channel_gain_before_opex/100)) -> 691.45796
A31: How much of this is evidence?
B32: expected, EUR m | C32: share | D32: one in ten, EUR m | E32: share | F32: meaning
A33: Disclosed exposure, measured shocks (leak 3, the level and the curve) | B33: =buyback_payables_current_eur_m * MAX(0, x18_exp_twosided_book)/100 -> 0 | C33: =B33/((eu_revenue_eur_m * x14_incentive_claims_central/100 * process_leak_pct/100 + eu_revenue_eur_m * x5_targeting_gain_central/100) + sfse_eu_nv_contracts_2025 * upgrade_capture_uplift/100 * margin_per_repeat_sale / 1000000 + (buyback_payables_current_eur_m * MAX(0, x18_exp_twosided_book)/100 + buyback_payables_current_eur_m * (x17_days_cut * x17_day_cost_central/10000 + x17_share_routed/100 * x17_channel_gain_after_costs/100))) -> 0 | D33: =(buyback_payables_current_eur_m * (ABS(level_1y_p10_book)/100 + (curve_1y_p80_known/2/retained_1y_pooled * (1 - thin_share_of_book/100) + curve_1y_p80_unknown/2/retained_1y_pooled * thin_share_of_book/100))) * x18_joint_share_book/100 -> 92.471421 | E33: =D33/((eu_revenue_eur_m * x14_incentive_claims_central/100 * process_leak_pct/100 + eu_revenue_eur_m * x5_targeting_gain_central/100) + sfse_eu_nv_contracts_2025 * upgrade_capture_uplift/100 * margin_per_repeat_sale / 1000000 + ((buyback_payables_current_eur_m * (ABS(level_1y_p10_book)/100 + (curve_1y_p80_known/2/retained_1y_pooled * (1 - thin_share_of_book/100) + curve_1y_p80_unknown/2/retained_1y_pooled * thin_share_of_book/100))) * x18_joint_share_book/100 + buyback_payables_current_eur_m * (x17_days_cut * x17_day_cost_central/10000 + x17_share_routed/100 * x17_channel_gain_after_costs/100))) -> 0.31018685 | F33: our own analysis, on a disclosed exposure: nothing expected, the largest line in a bad year
A34: Measured costs, assumed reach (leak 3, resale execution) | B34: =buyback_payables_current_eur_m * (x17_days_cut * x17_day_cost_central/10000 + x17_share_routed/100 * x17_channel_gain_after_costs/100) -> 24.81171 | C34: =B34/((eu_revenue_eur_m * x14_incentive_claims_central/100 * process_leak_pct/100 + eu_revenue_eur_m * x5_targeting_gain_central/100) + sfse_eu_nv_contracts_2025 * upgrade_capture_uplift/100 * margin_per_repeat_sale / 1000000 + (buyback_payables_current_eur_m * MAX(0, x18_exp_twosided_book)/100 + buyback_payables_current_eur_m * (x17_days_cut * x17_day_cost_central/10000 + x17_share_routed/100 * x17_channel_gain_after_costs/100))) -> 0.12065382 | D34: =buyback_payables_current_eur_m * (x17_days_cut * x17_day_cost_central/10000 + x17_share_routed/100 * x17_channel_gain_after_costs/100) -> 24.81171 | E34: =D34/((eu_revenue_eur_m * x14_incentive_claims_central/100 * process_leak_pct/100 + eu_revenue_eur_m * x5_targeting_gain_central/100) + sfse_eu_nv_contracts_2025 * upgrade_capture_uplift/100 * margin_per_repeat_sale / 1000000 + ((buyback_payables_current_eur_m * (ABS(level_1y_p10_book)/100 + (curve_1y_p80_known/2/retained_1y_pooled * (1 - thin_share_of_book/100) + curve_1y_p80_unknown/2/retained_1y_pooled * thin_share_of_book/100))) * x18_joint_share_book/100 + buyback_payables_current_eur_m * (x17_days_cut * x17_day_cost_central/10000 + x17_share_routed/100 * x17_channel_gain_after_costs/100))) -> 0.083228592 | F34: a day in stock and the retail margin are measured; the days cut and the share routed are assumed
A35: Measured timing, assumed conversion (leak 2) | B35: =sfse_eu_nv_contracts_2025 * upgrade_capture_uplift/100 * margin_per_repeat_sale / 1000000 -> 38.76828 | C35: =B35/((eu_revenue_eur_m * x14_incentive_claims_central/100 * process_leak_pct/100 + eu_revenue_eur_m * x5_targeting_gain_central/100) + sfse_eu_nv_contracts_2025 * upgrade_capture_uplift/100 * margin_per_repeat_sale / 1000000 + (buyback_payables_current_eur_m * MAX(0, x18_exp_twosided_book)/100 + buyback_payables_current_eur_m * (x17_days_cut * x17_day_cost_central/10000 + x17_share_routed/100 * x17_channel_gain_after_costs/100))) -> 0.18852151 | D35: =sfse_eu_nv_contracts_2025 * upgrade_capture_uplift/100 * margin_per_repeat_sale / 1000000 -> 38.76828 | E35: =D35/((eu_revenue_eur_m * x14_incentive_claims_central/100 * process_leak_pct/100 + eu_revenue_eur_m * x5_targeting_gain_central/100) + sfse_eu_nv_contracts_2025 * upgrade_capture_uplift/100 * margin_per_repeat_sale / 1000000 + ((buyback_payables_current_eur_m * (ABS(level_1y_p10_book)/100 + (curve_1y_p80_known/2/retained_1y_pooled * (1 - thin_share_of_book/100) + curve_1y_p80_unknown/2/retained_1y_pooled * thin_share_of_book/100))) * x18_joint_share_book/100 + buyback_payables_current_eur_m * (x17_days_cut * x17_day_cost_central/10000 + x17_share_routed/100 * x17_channel_gain_after_costs/100))) -> 0.13004462 | F35: the window is measured and the contracts disclosed; the euros are not
A36: Disclosed base, assumed leak rate (leak 1, claims) | B36: =eu_revenue_eur_m * x14_incentive_claims_central/100 * process_leak_pct/100 -> 77.99355 | C36: =B36/((eu_revenue_eur_m * x14_incentive_claims_central/100 * process_leak_pct/100 + eu_revenue_eur_m * x5_targeting_gain_central/100) + sfse_eu_nv_contracts_2025 * upgrade_capture_uplift/100 * margin_per_repeat_sale / 1000000 + (buyback_payables_current_eur_m * MAX(0, x18_exp_twosided_book)/100 + buyback_payables_current_eur_m * (x17_days_cut * x17_day_cost_central/10000 + x17_share_routed/100 * x17_channel_gain_after_costs/100))) -> 0.37926527 | D36: =eu_revenue_eur_m * x14_incentive_claims_central/100 * process_leak_pct/100 -> 77.99355 | E36: =D36/((eu_revenue_eur_m * x14_incentive_claims_central/100 * process_leak_pct/100 + eu_revenue_eur_m * x5_targeting_gain_central/100) + sfse_eu_nv_contracts_2025 * upgrade_capture_uplift/100 * margin_per_repeat_sale / 1000000 + ((buyback_payables_current_eur_m * (ABS(level_1y_p10_book)/100 + (curve_1y_p80_known/2/retained_1y_pooled * (1 - thin_share_of_book/100) + curve_1y_p80_unknown/2/retained_1y_pooled * thin_share_of_book/100))) * x18_joint_share_book/100 + buyback_payables_current_eur_m * (x17_days_cut * x17_day_cost_central/10000 + x17_share_routed/100 * x17_channel_gain_after_costs/100))) -> 0.26162217 | F36: the group's own incentive claims (20-F, worldwide); the share paid wrongly is assumed
A37: Derived from published studies (leak 1, targeting) | B37: =eu_revenue_eur_m * x5_targeting_gain_central/100 -> 64.070257 | C37: =B37/((eu_revenue_eur_m * x14_incentive_claims_central/100 * process_leak_pct/100 + eu_revenue_eur_m * x5_targeting_gain_central/100) + sfse_eu_nv_contracts_2025 * upgrade_capture_uplift/100 * margin_per_repeat_sale / 1000000 + (buyback_payables_current_eur_m * MAX(0, x18_exp_twosided_book)/100 + buyback_payables_current_eur_m * (x17_days_cut * x17_day_cost_central/10000 + x17_share_routed/100 * x17_channel_gain_after_costs/100))) -> 0.3115594 | D37: =eu_revenue_eur_m * x5_targeting_gain_central/100 -> 64.070257 | E37: =D37/((eu_revenue_eur_m * x14_incentive_claims_central/100 * process_leak_pct/100 + eu_revenue_eur_m * x5_targeting_gain_central/100) + sfse_eu_nv_contracts_2025 * upgrade_capture_uplift/100 * margin_per_repeat_sale / 1000000 + ((buyback_payables_current_eur_m * (ABS(level_1y_p10_book)/100 + (curve_1y_p80_known/2/retained_1y_pooled * (1 - thin_share_of_book/100) + curve_1y_p80_unknown/2/retained_1y_pooled * thin_share_of_book/100))) * x18_joint_share_book/100 + buyback_payables_current_eur_m * (x17_days_cut * x17_day_cost_central/10000 + x17_share_routed/100 * x17_channel_gain_after_costs/100))) -> 0.21491777 | F37: Swiss price sensitivities by income, a European margin, one assumption
A38: Read the split before either total. What we measured best is a tail: leak 3's level and curve cost about nothing in an average year, because the group's buy-back contracts bring the cars back and a rising market pays for a falling one, and they are the largest measured line in a bad year. The expected column rests mostly on disclosed bases with assumed rates (leak 1's claims, leak 2, resale execution's reach), which a pilot should replace, and on leak 1's targeting line, derived from published studies and tested by the pilot's holdout.
A41: One input at a time
A42: input | B42: tier | C42: one in ten at its low | D42: one in ten at its high | E42: swing | F42: swing, expected a year
A43: Claims paid twice, wrongly or too late, as a share of incentive spend | B43: ASSUMPTION | C43: =(eu_revenue_eur_m * x14_incentive_claims_central/100 * Assumptions!$D$114/100 + eu_revenue_eur_m * x5_targeting_gain_central/100) + sfse_eu_nv_contracts_2025 * upgrade_capture_uplift/100 * margin_per_repeat_sale / 1000000 + ((buyback_payables_current_eur_m * (ABS(level_1y_p10_book)/100 + (curve_1y_p80_known/2/retained_1y_pooled * (1 - thin_share_of_book/100) + curve_1y_p80_unknown/2/retained_1y_pooled * thin_share_of_book/100))) * x18_joint_share_book/100 + buyback_payables_current_eur_m * (x17_days_cut * x17_day_cost_central/10000 + x17_share_routed/100 * x17_channel_gain_after_costs/100)) -> 239.62006 | D43: =(eu_revenue_eur_m * x14_incentive_claims_central/100 * Assumptions!$E$114/100 + eu_revenue_eur_m * x5_targeting_gain_central/100) + sfse_eu_nv_contracts_2025 * upgrade_capture_uplift/100 * margin_per_repeat_sale / 1000000 + ((buyback_payables_current_eur_m * (ABS(level_1y_p10_book)/100 + (curve_1y_p80_known/2/retained_1y_pooled * (1 - thin_share_of_book/100) + curve_1y_p80_unknown/2/retained_1y_pooled * thin_share_of_book/100))) * x18_joint_share_book/100 + buyback_payables_current_eur_m * (x17_days_cut * x17_day_cost_central/10000 + x17_share_routed/100 * x17_channel_gain_after_costs/100)) -> 415.10554 | E43: =ABS(D43-C43) -> 175.48549 | F43: =ABS(((eu_revenue_eur_m * x14_incentive_claims_central/100 * Assumptions!$E$114/100 + eu_revenue_eur_m * x5_targeting_gain_central/100) + sfse_eu_nv_contracts_2025 * upgrade_capture_uplift/100 * margin_per_repeat_sale / 1000000 + (buyback_payables_current_eur_m * MAX(0, x18_exp_twosided_book)/100 + buyback_payables_current_eur_m * (x17_days_cut * x17_day_cost_central/10000 + x17_share_routed/100 * x17_channel_gain_after_costs/100))) - ((eu_revenue_eur_m * x14_incentive_claims_central/100 * Assumptions!$D$114/100 + eu_revenue_eur_m * x5_targeting_gain_central/100) + sfse_eu_nv_contracts_2025 * upgrade_capture_uplift/100 * margin_per_repeat_sale / 1000000 + (buyback_payables_current_eur_m * MAX(0, x18_exp_twosided_book)/100 + buyback_payables_current_eur_m * (x17_days_cut * x17_day_cost_central/10000 + x17_share_routed/100 * x17_channel_gain_after_costs/100)))) -> 175.48549
A44: Extra share of customers retained by contacting them at the right moment | B44: ASSUMPTION | C44: =(eu_revenue_eur_m * x14_incentive_claims_central/100 * process_leak_pct/100 + eu_revenue_eur_m * x5_targeting_gain_central/100) + sfse_eu_nv_contracts_2025 * Assumptions!$D$134/100 * margin_per_repeat_sale / 1000000 + ((buyback_payables_current_eur_m * (ABS(level_1y_p10_book)/100 + (curve_1y_p80_known/2/retained_1y_pooled * (1 - thin_share_of_book/100) + curve_1y_p80_unknown/2/retained_1y_pooled * thin_share_of_book/100))) * x18_joint_share_book/100 + buyback_payables_current_eur_m * (x17_days_cut * x17_day_cost_central/10000 + x17_share_routed/100 * x17_channel_gain_after_costs/100)) -> 272.2697 | D44: =(eu_revenue_eur_m * x14_incentive_claims_central/100 * process_leak_pct/100 + eu_revenue_eur_m * x5_targeting_gain_central/100) + sfse_eu_nv_contracts_2025 * Assumptions!$E$134/100 * margin_per_repeat_sale / 1000000 + ((buyback_payables_current_eur_m * (ABS(level_1y_p10_book)/100 + (curve_1y_p80_known/2/retained_1y_pooled * (1 - thin_share_of_book/100) + curve_1y_p80_unknown/2/retained_1y_pooled * thin_share_of_book/100))) * x18_joint_share_book/100 + buyback_payables_current_eur_m * (x17_days_cut * x17_day_cost_central/10000 + x17_share_routed/100 * x17_channel_gain_after_costs/100)) -> 336.8835 | E44: =ABS(D44-C44) -> 64.6138 | F44: =ABS(((eu_revenue_eur_m * x14_incentive_claims_central/100 * process_leak_pct/100 + eu_revenue_eur_m * x5_targeting_gain_central/100) + sfse_eu_nv_contracts_2025 * Assumptions!$E$134/100 * margin_per_repeat_sale / 1000000 + (buyback_payables_current_eur_m * MAX(0, x18_exp_twosided_book)/100 + buyback_payables_current_eur_m * (x17_days_cut * x17_day_cost_central/10000 + x17_share_routed/100 * x17_channel_gain_after_costs/100))) - ((eu_revenue_eur_m * x14_incentive_claims_central/100 * process_leak_pct/100 + eu_revenue_eur_m * x5_targeting_gain_central/100) + sfse_eu_nv_contracts_2025 * Assumptions!$D$134/100 * margin_per_repeat_sale / 1000000 + (buyback_payables_current_eur_m * MAX(0, x18_exp_twosided_book)/100 + buyback_payables_current_eur_m * (x17_days_cut * x17_day_cost_central/10000 + x17_share_routed/100 * x17_channel_gain_after_costs/100)))) -> 64.6138
A45: Contribution from one retained customer's next car | B45: ASSUMPTION | C45: =(eu_revenue_eur_m * x14_incentive_claims_central/100 * process_leak_pct/100 + eu_revenue_eur_m * x5_targeting_gain_central/100) + sfse_eu_nv_contracts_2025 * upgrade_capture_uplift/100 * Assumptions!$D$135 / 1000000 + ((buyback_payables_current_eur_m * (ABS(level_1y_p10_book)/100 + (curve_1y_p80_known/2/retained_1y_pooled * (1 - thin_share_of_book/100) + curve_1y_p80_unknown/2/retained_1y_pooled * thin_share_of_book/100))) * x18_joint_share_book/100 + buyback_payables_current_eur_m * (x17_days_cut * x17_day_cost_central/10000 + x17_share_routed/100 * x17_channel_gain_after_costs/100)) -> 278.73108 | D45: =(eu_revenue_eur_m * x14_incentive_claims_central/100 * process_leak_pct/100 + eu_revenue_eur_m * x5_targeting_gain_central/100) + sfse_eu_nv_contracts_2025 * upgrade_capture_uplift/100 * Assumptions!$E$135 / 1000000 + ((buyback_payables_current_eur_m * (ABS(level_1y_p10_book)/100 + (curve_1y_p80_known/2/retained_1y_pooled * (1 - thin_share_of_book/100) + curve_1y_p80_unknown/2/retained_1y_pooled * thin_share_of_book/100))) * x18_joint_share_book/100 + buyback_payables_current_eur_m * (x17_days_cut * x17_day_cost_central/10000 + x17_share_routed/100 * x17_channel_gain_after_costs/100)) -> 327.19143 | E45: =ABS(D45-C45) -> 48.46035 | F45: =ABS(((eu_revenue_eur_m * x14_incentive_claims_central/100 * process_leak_pct/100 + eu_revenue_eur_m * x5_targeting_gain_central/100) + sfse_eu_nv_contracts_2025 * upgrade_capture_uplift/100 * Assumptions!$E$135 / 1000000 + (buyback_payables_current_eur_m * MAX(0, x18_exp_twosided_book)/100 + buyback_payables_current_eur_m * (x17_days_cut * x17_day_cost_central/10000 + x17_share_routed/100 * x17_channel_gain_after_costs/100))) - ((eu_revenue_eur_m * x14_incentive_claims_central/100 * process_leak_pct/100 + eu_revenue_eur_m * x5_targeting_gain_central/100) + sfse_eu_nv_contracts_2025 * upgrade_capture_uplift/100 * Assumptions!$D$135 / 1000000 + (buyback_payables_current_eur_m * MAX(0, x18_exp_twosided_book)/100 + buyback_payables_current_eur_m * (x17_days_cut * x17_day_cost_central/10000 + x17_share_routed/100 * x17_channel_gain_after_costs/100)))) -> 48.46035
A46: Share of the buy-back book with little history | B46: ASSUMPTION | C46: =(eu_revenue_eur_m * x14_incentive_claims_central/100 * process_leak_pct/100 + eu_revenue_eur_m * x5_targeting_gain_central/100) + sfse_eu_nv_contracts_2025 * upgrade_capture_uplift/100 * margin_per_repeat_sale / 1000000 + ((buyback_payables_current_eur_m * (ABS(level_1y_p10_book)/100 + (curve_1y_p80_known/2/retained_1y_pooled * (1 - Assumptions!$D$117/100) + curve_1y_p80_unknown/2/retained_1y_pooled * Assumptions!$D$117/100))) * x18_joint_share_book/100 + buyback_payables_current_eur_m * (x17_days_cut * x17_day_cost_central/10000 + x17_share_routed/100 * x17_channel_gain_after_costs/100)) -> 285.71817 | D46: =(eu_revenue_eur_m * x14_incentive_claims_central/100 * process_leak_pct/100 + eu_revenue_eur_m * x5_targeting_gain_central/100) + sfse_eu_nv_contracts_2025 * upgrade_capture_uplift/100 * margin_per_repeat_sale / 1000000 + ((buyback_payables_current_eur_m * (ABS(level_1y_p10_book)/100 + (curve_1y_p80_known/2/retained_1y_pooled * (1 - Assumptions!$E$117/100) + curve_1y_p80_unknown/2/retained_1y_pooled * Assumptions!$E$117/100))) * x18_joint_share_book/100 + buyback_payables_current_eur_m * (x17_days_cut * x17_day_cost_central/10000 + x17_share_routed/100 * x17_channel_gain_after_costs/100)) -> 310.51227 | E46: =ABS(D46-C46) -> 24.794098 | F46: =ABS(((eu_revenue_eur_m * x14_incentive_claims_central/100 * process_leak_pct/100 + eu_revenue_eur_m * x5_targeting_gain_central/100) + sfse_eu_nv_contracts_2025 * upgrade_capture_uplift/100 * margin_per_repeat_sale / 1000000 + (buyback_payables_current_eur_m * MAX(0, x18_exp_twosided_book)/100 + buyback_payables_current_eur_m * (x17_days_cut * x17_day_cost_central/10000 + x17_share_routed/100 * x17_channel_gain_after_costs/100))) - ((eu_revenue_eur_m * x14_incentive_claims_central/100 * process_leak_pct/100 + eu_revenue_eur_m * x5_targeting_gain_central/100) + sfse_eu_nv_contracts_2025 * upgrade_capture_uplift/100 * margin_per_repeat_sale / 1000000 + (buyback_payables_current_eur_m * MAX(0, x18_exp_twosided_book)/100 + buyback_payables_current_eur_m * (x17_days_cut * x17_day_cost_central/10000 + x17_share_routed/100 * x17_channel_gain_after_costs/100)))) -> 0
A47: Days cut from the average time to sale of a year's buy-back returns | B47: ASSUMPTION | C47: =(eu_revenue_eur_m * x14_incentive_claims_central/100 * process_leak_pct/100 + eu_revenue_eur_m * x5_targeting_gain_central/100) + sfse_eu_nv_contracts_2025 * upgrade_capture_uplift/100 * margin_per_repeat_sale / 1000000 + ((buyback_payables_current_eur_m * (ABS(level_1y_p10_book)/100 + (curve_1y_p80_known/2/retained_1y_pooled * (1 - thin_share_of_book/100) + curve_1y_p80_unknown/2/retained_1y_pooled * thin_share_of_book/100))) * x18_joint_share_book/100 + buyback_payables_current_eur_m * (Assumptions!$D$685 * x17_day_cost_central/10000 + x17_share_routed/100 * x17_channel_gain_after_costs/100)) -> 289.95976 | D47: =(eu_revenue_eur_m * x14_incentive_claims_central/100 * process_leak_pct/100 + eu_revenue_eur_m * x5_targeting_gain_central/100) + sfse_eu_nv_contracts_2025 * upgrade_capture_uplift/100 * margin_per_repeat_sale / 1000000 + ((buyback_payables_current_eur_m * (ABS(level_1y_p10_book)/100 + (curve_1y_p80_known/2/retained_1y_pooled * (1 - thin_share_of_book/100) + curve_1y_p80_unknown/2/retained_1y_pooled * thin_share_of_book/100))) * x18_joint_share_book/100 + buyback_payables_current_eur_m * (Assumptions!$E$685 * x17_day_cost_central/10000 + x17_share_routed/100 * x17_channel_gain_after_costs/100)) -> 314.42613 | E47: =ABS(D47-C47) -> 24.466365 | F47: =ABS(((eu_revenue_eur_m * x14_incentive_claims_central/100 * process_leak_pct/100 + eu_revenue_eur_m * x5_targeting_gain_central/100) + sfse_eu_nv_contracts_2025 * upgrade_capture_uplift/100 * margin_per_repeat_sale / 1000000 + (buyback_payables_current_eur_m * MAX(0, x18_exp_twosided_book)/100 + buyback_payables_current_eur_m * (Assumptions!$E$685 * x17_day_cost_central/10000 + x17_share_routed/100 * x17_channel_gain_after_costs/100))) - ((eu_revenue_eur_m * x14_incentive_claims_central/100 * process_leak_pct/100 + eu_revenue_eur_m * x5_targeting_gain_central/100) + sfse_eu_nv_contracts_2025 * upgrade_capture_uplift/100 * margin_per_repeat_sale / 1000000 + (buyback_payables_current_eur_m * MAX(0, x18_exp_twosided_book)/100 + buyback_payables_current_eur_m * (Assumptions!$D$685 * x17_day_cost_central/10000 + x17_share_routed/100 * x17_channel_gain_after_costs/100)))) -> 24.466365
A48: Share of a year's buy-back returns routed to the group's own retail instead of the trade | B48: ASSUMPTION | C48: =(eu_revenue_eur_m * x14_incentive_claims_central/100 * process_leak_pct/100 + eu_revenue_eur_m * x5_targeting_gain_central/100) + sfse_eu_nv_contracts_2025 * upgrade_capture_uplift/100 * margin_per_repeat_sale / 1000000 + ((buyback_payables_current_eur_m * (ABS(level_1y_p10_book)/100 + (curve_1y_p80_known/2/retained_1y_pooled * (1 - thin_share_of_book/100) + curve_1y_p80_unknown/2/retained_1y_pooled * thin_share_of_book/100))) * x18_joint_share_book/100 + buyback_payables_current_eur_m * (x17_days_cut * x17_day_cost_central/10000 + Assumptions!$D$686/100 * x17_channel_gain_after_costs/100)) -> 293.01474 | D48: =(eu_revenue_eur_m * x14_incentive_claims_central/100 * process_leak_pct/100 + eu_revenue_eur_m * x5_targeting_gain_central/100) + sfse_eu_nv_contracts_2025 * upgrade_capture_uplift/100 * margin_per_repeat_sale / 1000000 + ((buyback_payables_current_eur_m * (ABS(level_1y_p10_book)/100 + (curve_1y_p80_known/2/retained_1y_pooled * (1 - thin_share_of_book/100) + curve_1y_p80_unknown/2/retained_1y_pooled * thin_share_of_book/100))) * x18_joint_share_book/100 + buyback_payables_current_eur_m * (x17_days_cut * x17_day_cost_central/10000 + Assumptions!$E$686/100 * x17_channel_gain_after_costs/100)) -> 306.61602 | E48: =ABS(D48-C48) -> 13.60128 | F48: =ABS(((eu_revenue_eur_m * x14_incentive_claims_central/100 * process_leak_pct/100 + eu_revenue_eur_m * x5_targeting_gain_central/100) + sfse_eu_nv_contracts_2025 * upgrade_capture_uplift/100 * margin_per_repeat_sale / 1000000 + (buyback_payables_current_eur_m * MAX(0, x18_exp_twosided_book)/100 + buyback_payables_current_eur_m * (x17_days_cut * x17_day_cost_central/10000 + Assumptions!$E$686/100 * x17_channel_gain_after_costs/100))) - ((eu_revenue_eur_m * x14_incentive_claims_central/100 * process_leak_pct/100 + eu_revenue_eur_m * x5_targeting_gain_central/100) + sfse_eu_nv_contracts_2025 * upgrade_capture_uplift/100 * margin_per_repeat_sale / 1000000 + (buyback_payables_current_eur_m * MAX(0, x18_exp_twosided_book)/100 + buyback_payables_current_eur_m * (x17_days_cut * x17_day_cost_central/10000 + Assumptions!$D$686/100 * x17_channel_gain_after_costs/100)))) -> 13.60128
A49: Only assumed inputs are varied here, ranked by their swing on the one-in-ten total. The measured ones have ranges too - they are on the Assumptions sheet - but varying them would answer a different question: this table asks how much of the answer rests on judgement. The little-history share moves only the one-in-ten column, since the expected column's level and curve line is zero.

Sheet Leak 1 - Incentives
A1: Leak 1: the spend nobody can see
A3: The claims line takes the group's own claims-based incentive spend: the sales-incentive provision in its 20-F (Note 21), worldwide, as a share of net revenue (analysis/incentive_anchor_report.md). No regional total is disclosed, and the share of claims paid wrongly is an assumption. The targeting line is derived from published studies and one assumption (analysis/optimal_incentive_report.md). Neither is a measurement of the group in Europe: that is the reason the ledger has to be built.
A5: EUR millions a year, Enlarged Europe
A6: Incentive claims (the group's own share of revenue, applied to Europe) | B6: =eu_revenue_eur_m * x14_incentive_claims_central/100 -> 3899.6775 | C6: eu_revenue_eur_m x x14_incentive_claims_central (20-F Note 21, worldwide)
A7: Claims paid twice, wrongly or too late | B7: =eu_revenue_eur_m * x14_incentive_claims_central/100 * process_leak_pct/100 -> 77.99355 | C7: process_leak_pct
A8: Profit lost by giving every buyer the same incentive | B8: =eu_revenue_eur_m * x5_targeting_gain_central/100 -> 64.070257 | C8: x5_targeting_gain_central: what giving each income quartile its own incentive earns, derived in X5
A9: Value at risk, leak 1 | B9: =(eu_revenue_eur_m * x14_incentive_claims_central/100 * process_leak_pct/100 + eu_revenue_eur_m * x5_targeting_gain_central/100) -> 142.06381
A11: Of which a controls layer actually recovers | B11: =eu_revenue_eur_m * x14_incentive_claims_central/100 * process_leak_pct/100 * recoverable_share/100 -> 23.398065 | C11: leakage that exists is not leakage you can recover
A13: Not sized here, on purpose
A14: Spend above the best uniform level. The targeting line takes today's uniform incentive as the best uniform one, so it cannot say whether the group spends too much on average. Public data cannot either: the published margins and price sensitivities disagree. Only a randomised holdout on the incentive's level measures it.
A15: Pass-through leakage - money meant for the buyer that the dealer keeps - is real and measured in the literature (buyers receive 70-90% of a customer rebate but only 30-40% of a dealer discount, Busse et al. 2006, US data). It is not converted into euros here because that would need a second assumption about how the group's spend splits between the two kinds of programme. The ledger measures it per programme instead of assuming it.

Sheet Leak 2 - Upgrade timing
A1: Leak 2: the moment nobody catches
A3: The upgrade moment is when the car is worth more than the balance still owed on it. Both sides are held as a share of the list price, so no currency or exchange rate enters. The value curve is the measured UK retained-value curve from the 2018 adverts, before the shortage; the balance is a straight amortising contract.
A5: Measured value curve (share of list price)
A6: years | B6: 0 | C6: 1 | D6: 2 | E6: 3 | F6: 4 | G6: 5
A7: retained | B7: 100 | C7: =retained_1y_uk -> 91 | D7: =retained_2y_uk -> 78 | E7: =retained_3y_uk -> 66 | F7: =retained_4y_uk -> 59 | G7: =retained_5y_uk -> 52 | H7: <- analysis/value_retained_report.md (UK 2018 adverts; entry-trim caveat applies; October 2022 ran 24 points higher at three years)
A9: Contract
A10: deposit, % of list | B10: =loan_deposit_pct -> 15
A11: term, months | B11: =loan_term_months -> 48
A12: interest rate, % a year | B12: =loan_apr -> 7
A13: amount financed, % of list | B13: =100 - loan_deposit_pct -> 85 | C13: no discount assumed, so this is the conservative case
A15: The trigger is not simply positive equity. On a 48-month contract the balance falls faster than the car does, so the customer is above water almost at once. The moment that matters commercially is when the car's equity covers the deposit on the next one, which is the line used below.
A17: month | B17: balance owed | C17: car value, level as measured | D17: equity | E17: car value, level -7.7% (p10) | F17: equity at -7.7% | G17: car value, level -27.0% (worst) | H17: equity at -27.0%
A18: 0 | B18: =IF(A18>=loan_term_months,0,(100-loan_deposit_pct)*((1+loan_apr/1200)^loan_term_months-(1+loan_apr/1200)^A18)/((1+loan_apr/1200)^loan_term_months-1)) -> 85 | C18: =INDEX($B$7:$G$7,MIN(4,INT(A18/12))+1)+(A18/12-MIN(4,INT(A18/12)))*(INDEX($B$7:$G$7,MIN(4,INT(A18/12))+2)-INDEX($B$7:$G$7,MIN(4,INT(A18/12))+1)) -> 100 | D18: =C18-B18 -> 15 | E18: =C18*(1+level_3y_p10_core/100) -> 92.3 | F18: =E18-B18 -> 7.3 | G18: =C18*(1+level_3y_worst/100) -> 73 | H18: =G18-B18 -> -12
A19: 1 | B19: =IF(A19>=loan_term_months,0,(100-loan_deposit_pct)*((1+loan_apr/1200)^loan_term_months-(1+loan_apr/1200)^A19)/((1+loan_apr/1200)^loan_term_months-1)) -> 83.460403 | C19: =INDEX($B$7:$G$7,MIN(4,INT(A19/12))+1)+(A19/12-MIN(4,INT(A19/12)))*(INDEX($B$7:$G$7,MIN(4,INT(A19/12))+2)-INDEX($B$7:$G$7,MIN(4,INT(A19/12))+1)) -> 99.25 | D19: =C19-B19 -> 15.789597 | E19: =C19*(1+level_3y_p10_core/100) -> 91.60775 | F19: =E19-B19 -> 8.1473475 | G19: =C19*(1+level_3y_worst/100) -> 72.4525 | H19: =G19-B19 -> -11.007903
A20: 2 | B20: =IF(A20>=loan_term_months,0,(100-loan_deposit_pct)*((1+loan_apr/1200)^loan_term_months-(1+loan_apr/1200)^A20)/((1+loan_apr/1200)^loan_term_months-1)) -> 81.911824 | C20: =INDEX($B$7:$G$7,MIN(4,INT(A20/12))+1)+(A20/12-MIN(4,INT(A20/12)))*(INDEX($B$7:$G$7,MIN(4,INT(A20/12))+2)-INDEX($B$7:$G$7,MIN(4,INT(A20/12))+1)) -> 98.5 | D20: =C20-B20 -> 16.588176 | E20: =C20*(1+level_3y_p10_core/100) -> 90.9155 | F20: =E20-B20 -> 9.0036759 | G20: =C20*(1+level_3y_worst/100) -> 71.905 | H20: =G20-B20 -> -10.006824
A21: 3 | B21: =IF(A21>=loan_term_months,0,(100-loan_deposit_pct)*((1+loan_apr/1200)^loan_term_months-(1+loan_apr/1200)^A21)/((1+loan_apr/1200)^loan_term_months-1)) -> 80.354212 | C21: =INDEX($B$7:$G$7,MIN(4,INT(A21/12))+1)+(A21/12-MIN(4,INT(A21/12)))*(INDEX($B$7:$G$7,MIN(4,INT(A21/12))+2)-INDEX($B$7:$G$7,MIN(4,INT(A21/12))+1)) -> 97.75 | D21: =C21-B21 -> 17.395788 | E21: =C21*(1+level_3y_p10_core/100) -> 90.22325 | F21: =E21-B21 -> 9.8690377 | G21: =C21*(1+level_3y_worst/100) -> 71.3575 | H21: =G21-B21 -> -8.9967123
A22: 4 | B22: =IF(A22>=loan_term_months,0,(100-loan_deposit_pct)*((1+loan_apr/1200)^loan_term_months-(1+loan_apr/1200)^A22)/((1+loan_apr/1200)^loan_term_months-1)) -> 78.787514 | C22: =INDEX($B$7:$G$7,MIN(4,INT(A22/12))+1)+(A22/12-MIN(4,INT(A22/12)))*(INDEX($B$7:$G$7,MIN(4,INT(A22/12))+2)-INDEX($B$7:$G$7,MIN(4,INT(A22/12))+1)) -> 97 | D22: =C22-B22 -> 18.212486 | E22: =C22*(1+level_3y_p10_core/100) -> 89.531 | F22: =E22-B22 -> 10.743486 | G22: =C22*(1+level_3y_worst/100) -> 70.81 | H22: =G22-B22 -> -7.9775144
A23: 5 | B23: =IF(A23>=loan_term_months,0,(100-loan_deposit_pct)*((1+loan_apr/1200)^loan_term_months-(1+loan_apr/1200)^A23)/((1+loan_apr/1200)^loan_term_months-1)) -> 77.211677 | C23: =INDEX($B$7:$G$7,MIN(4,INT(A23/12))+1)+(A23/12-MIN(4,INT(A23/12)))*(INDEX($B$7:$G$7,MIN(4,INT(A23/12))+2)-INDEX($B$7:$G$7,MIN(4,INT(A23/12))+1)) -> 96.25 | D23: =C23-B23 -> 19.038323 | E23: =C23*(1+level_3y_p10_core/100) -> 88.83875 | F23: =E23-B23 -> 11.627073 | G23: =C23*(1+level_3y_worst/100) -> 70.2625 | H23: =G23-B23 -> -6.9491774
A24: 6 | B24: =IF(A24>=loan_term_months,0,(100-loan_deposit_pct)*((1+loan_apr/1200)^loan_term_months-(1+loan_apr/1200)^A24)/((1+loan_apr/1200)^loan_term_months-1)) -> 75.626648 | C24: =INDEX($B$7:$G$7,MIN(4,INT(A24/12))+1)+(A24/12-MIN(4,INT(A24/12)))*(INDEX($B$7:$G$7,MIN(4,INT(A24/12))+2)-INDEX($B$7:$G$7,MIN(4,INT(A24/12))+1)) -> 95.5 | D24: =C24-B24 -> 19.873352 | E24: =C24*(1+level_3y_p10_core/100) -> 88.1465 | F24: =E24-B24 -> 12.519852 | G24: =C24*(1+level_3y_worst/100) -> 69.715 | H24: =G24-B24 -> -5.9116481
A25: 7 | B25: =IF(A25>=loan_term_months,0,(100-loan_deposit_pct)*((1+loan_apr/1200)^loan_term_months-(1+loan_apr/1200)^A25)/((1+loan_apr/1200)^loan_term_months-1)) -> 74.032373 | C25: =INDEX($B$7:$G$7,MIN(4,INT(A25/12))+1)+(A25/12-MIN(4,INT(A25/12)))*(INDEX($B$7:$G$7,MIN(4,INT(A25/12))+2)-INDEX($B$7:$G$7,MIN(4,INT(A25/12))+1)) -> 94.75 | D25: =C25-B25 -> 20.717627 | E25: =C25*(1+level_3y_p10_core/100) -> 87.45425 | F25: =E25-B25 -> 13.421877 | G25: =C25*(1+level_3y_worst/100) -> 69.1675 | H25: =G25-B25 -> -4.8648727
A26: 8 | B26: =IF(A26>=loan_term_months,0,(100-loan_deposit_pct)*((1+loan_apr/1200)^loan_term_months-(1+loan_apr/1200)^A26)/((1+loan_apr/1200)^loan_term_months-1)) -> 72.428797 | C26: =INDEX($B$7:$G$7,MIN(4,INT(A26/12))+1)+(A26/12-MIN(4,INT(A26/12)))*(INDEX($B$7:$G$7,MIN(4,INT(A26/12))+2)-INDEX($B$7:$G$7,MIN(4,INT(A26/12))+1)) -> 94 | D26: =C26-B26 -> 21.571203 | E26: =C26*(1+level_3y_p10_core/100) -> 86.762 | F26: =E26-B26 -> 14.333203 | G26: =C26*(1+level_3y_worst/100) -> 68.62 | H26: =G26-B26 -> -3.8087974
A27: 9 | B27: =IF(A27>=loan_term_months,0,(100-loan_deposit_pct)*((1+loan_apr/1200)^loan_term_months-(1+loan_apr/1200)^A27)/((1+loan_apr/1200)^loan_term_months-1)) -> 70.815868 | C27: =INDEX($B$7:$G$7,MIN(4,INT(A27/12))+1)+(A27/12-MIN(4,INT(A27/12)))*(INDEX($B$7:$G$7,MIN(4,INT(A27/12))+2)-INDEX($B$7:$G$7,MIN(4,INT(A27/12))+1)) -> 93.25 | D27: =C27-B27 -> 22.434132 | E27: =C27*(1+level_3y_p10_core/100) -> 86.06975 | F27: =E27-B27 -> 15.253882 | G27: =C27*(1+level_3y_worst/100) -> 68.0725 | H27: =G27-B27 -> -2.743368
A28: 10 | B28: =IF(A28>=loan_term_months,0,(100-loan_deposit_pct)*((1+loan_apr/1200)^loan_term_months-(1+loan_apr/1200)^A28)/((1+loan_apr/1200)^loan_term_months-1)) -> 69.19353 | C28: =INDEX($B$7:$G$7,MIN(4,INT(A28/12))+1)+(A28/12-MIN(4,INT(A28/12)))*(INDEX($B$7:$G$7,MIN(4,INT(A28/12))+2)-INDEX($B$7:$G$7,MIN(4,INT(A28/12))+1)) -> 92.5 | D28: =C28-B28 -> 23.30647 | E28: =C28*(1+level_3y_p10_core/100) -> 85.3775 | F28: =E28-B28 -> 16.18397 | G28: =C28*(1+level_3y_worst/100) -> 67.525 | H28: =G28-B28 -> -1.6685297
A29: 11 | B29: =IF(A29>=loan_term_months,0,(100-loan_deposit_pct)*((1+loan_apr/1200)^loan_term_months-(1+loan_apr/1200)^A29)/((1+loan_apr/1200)^loan_term_months-1)) -> 67.561728 | C29: =INDEX($B$7:$G$7,MIN(4,INT(A29/12))+1)+(A29/12-MIN(4,INT(A29/12)))*(INDEX($B$7:$G$7,MIN(4,INT(A29/12))+2)-INDEX($B$7:$G$7,MIN(4,INT(A29/12))+1)) -> 91.75 | D29: =C29-B29 -> 24.188272 | E29: =C29*(1+level_3y_p10_core/100) -> 84.68525 | F29: =E29-B29 -> 17.123522 | G29: =C29*(1+level_3y_worst/100) -> 66.9775 | H29: =G29-B29 -> -0.58422785
... A78: 60 | B78: =IF(A78>=loan_term_months,0,(100-loan_deposit_pct)*((1+loan_apr/1200)^loan_term_months-(1+loan_apr/1200)^A78)/((1+loan_apr/1200)^loan_term_months-1)) -> 0 | C78: =INDEX($B$7:$G$7,MIN(4,INT(A78/12))+1)+(A78/12-MIN(4,INT(A78/12)))*(INDEX($B$7:$G$7,MIN(4,INT(A78/12))+2)-INDEX($B$7:$G$7,MIN(4,INT(A78/12))+1)) -> 52 | D78: =C78-B78 -> 52 | E78: =C78*(1+level_3y_p10_core/100) -> 47.996 | F78: =E78-B78 -> 47.996 | G78: =C78*(1+level_3y_worst/100) -> 37.96 | H78: =G78-B78 -> 37.96
A80: Equity covers the next deposit from month, UK curve (searched from month 12: a 12 means by month 12) | B80: =IFERROR(MATCH(TRUE(),INDEX($D$30:$D$78>=loan_deposit_pct,0),0)+11,"not within the term") -> 12 | C80: =IFERROR(MATCH(TRUE(),INDEX($F$30:$F$78>=loan_deposit_pct,0),0)+11,"not within the term") -> 12 | D80: =IFERROR(MATCH(TRUE(),INDEX($H$30:$H$78>=loan_deposit_pct,0),0)+11,"not within the term") -> 28
B81: level as measured | C81: level -7.7% | D81: level -27.0%
A82: Measured with the first year (Dutch adverts, exact ages): equity covers the next deposit from month | B82: =window_nl_measured_m -> 18 | C82: =window_nl_p10_m -> 21 | D82: =window_nl_worst_m -> 33
A84: A fall in the market level pushes the upgrade window months later, and a rise pulls it forward. That shift is the measured part of this leak: it comes from the value curve and the level moves, not from judgement. Turning it into euros needs the three assumptions below, and those should be replaced by a randomised pilot rather than defended. The UK curve's window is searched from month 12 because UK adverts carry whole-year ages, so its first twelve months are a line drawn from the list price, which would put equity equal to the deposit at month 0; a 12 there means only 'by month 12'. The months to quote are the measured row: Dutch adverts with exact ages, the first year included, within model (analysis/upgrade_window_report.md).
A86: EUR millions a year
A87: Contracts financed or leased through the group | B87: =sfse_eu_nv_contracts_2025 -> 646138 | C87: sfse_eu_nv_contracts_2025: SFSE's new-car contracts in Europe, 2025 (Leasys fleet leases excluded)
A88: Extra customers retained by contacting them at the right moment | B88: =sfse_eu_nv_contracts_2025 * upgrade_capture_uplift/100 -> 19384.14 | C88: upgrade_capture_uplift
A89: Value at risk, leak 2 | B89: =sfse_eu_nv_contracts_2025 * upgrade_capture_uplift/100 * margin_per_repeat_sale / 1000000 -> 38.76828 | C89: x margin_per_repeat_sale

Sheet Leak 3 - Residual value
A1: Leak 3: the value nobody recovers
A3: This is the leak the evidence actually reaches, and it is a yearly figure like the other two, in two measures: expected a year, and one year in ten (X18). The exposure is the part of the group's disclosed buy-back book that comes back within twelve months; the shocks are measured, not assumed.
A5: Payables for buy-back agreements, the whole book | B5: =buyback_payables_eur_m -> 7889 | C5: Stellantis 20-F FY2025, Note 24
A6: Exposure a year: the part due within one year | B6: =buyback_payables_current_eur_m -> 5313 | C6: Note 24, current column; the rest is counted in the year it falls due
A8: Market level over the next twelve months
A9: Base: the group's book, spread across its markets (p10, -1.411%) | B9: =buyback_payables_current_eur_m * ABS(level_1y_p10_book)/100 -> 74.96643 | C9: France on the euro-area index; France's own index gives 61.8m, without France 87.1m. A floor: the index understates what a lessor meets (merger_diversification_report.md)
A10: Stress: the whole book in a core market's bad year (p10, -4.5%) | B10: =buyback_payables_current_eur_m * ABS(level_1y_p10_core)/100 -> 239.085 | C10: a Europe-wide bad year the book's short history lacks; the UK market fell 5.87% one year in ten over 1988-2026 (ONS)
A11: Reference, in no total: p10 across all 26 EU markets, as if the book sat in one (-6.3%) | B11: =buyback_payables_current_eur_m * ABS(level_1y_p10)/100 -> 334.719
A12: Reference, in no total: the worst twelve-month move in any market (-14.8%) | B12: =buyback_payables_current_eur_m * ABS(level_1y_worst)/100 -> 786.324
A13: Reference, in no total: the battery-EV slice in an EV-only slump like Poland's 2022-23 (10.2% of the book at -19.1 points) | B13: =buyback_payables_current_eur_m * x9_group_bev_share_2024/100 * ABS(x9_pl_ev_slump_gap)/100 -> 103.50787 | C13: X9: the group's 2024 registrations mix as a proxy for the book; one European slump, not a one-in-ten year; on top of the market's own fall
A15: The car itself over one year - what a value model can fix
A16: Curve error on the part of the book with its own history | B16: =buyback_payables_current_eur_m * curve_1y_p80_known/2/retained_1y_pooled * (1 - thin_share_of_book/100) -> 21.942456 | C16: half of a 1.0-point p10-p90 spread, on 90.8 retained: centre to p10
A17: Curve error on little-history cars (new brands, new markets, electrified lines) | B17: =buyback_payables_current_eur_m * curve_1y_p80_unknown/2/retained_1y_pooled * thin_share_of_book/100 -> 37.302175 | C17: half of a 5.1-point 80% interval; thin_share_of_book is the one assumption here
A19: The sale itself over one year - what the group can recover (X17)
A20: Days cut from the time to sale, at the measured cost of a day in stock | B20: =buyback_payables_current_eur_m * x17_days_cut * x17_day_cost_central/10000 -> 16.31091 | C20: x17_days_cut days (an assumption, anchored to DAT, INDICATA and Auto Trader) at x17_day_cost_central per EUR 10,000 a day: ageing at fixed mileage plus financing (time_in_stock_report.md)
A21: A share of returns retailed in-house instead of sold to the trade | B21: =buyback_payables_current_eur_m * x17_share_routed/100 * x17_channel_gain_after_costs/100 -> 8.5008 | C21: x17_share_routed of returns at Aramis's EBITDA per retail car as a share of its price; before operating costs the gain is x17_channel_gain_before_opex (recovery_levers_report.md)
A22: Priced, not recovered: the level at its p10 (base) | B22: =buyback_payables_current_eur_m * ABS(level_1y_p10_book)/100 -> 74.96643 | C22: no model forecasts it (X7): priced into each contract and re-marked (X6)
A23: Recoverable: the car and its sale (the curve at its p10, plus resale execution) | B23: =buyback_payables_current_eur_m * (curve_1y_p80_known/2/retained_1y_pooled * (1 - thin_share_of_book/100) + curve_1y_p80_unknown/2/retained_1y_pooled * thin_share_of_book/100) + buyback_payables_current_eur_m * (x17_days_cut * x17_day_cost_central/10000 + x17_share_routed/100 * x17_channel_gain_after_costs/100) -> 84.056341 | C23: the curve errors a value model cuts, plus resale execution; with the line above, the level and the curve at their separate p10s
A25: Leak 3 in two measures (X18)
A26: Level and curve, expected a year, both sides counted | B26: =buyback_payables_current_eur_m * MAX(0, x18_exp_twosided_book)/100 -> 0 | C26: the 20-F's contracts bring the cars back (stellantis_buyback_forms), so gains count: on the book's own record a residual at no change gained on average (x18_exp_twosided_book); a gain is not a leak, so zero (headline_measures_report.md)
A27: Reference, in no total: the same on the UK's 1988-2026 record | B27: =buyback_payables_current_eur_m * x18_exp_twosided_uk_long/100 -> 15.88587 | C27: UK data, several cycles: a residual at no change lost a fraction of a percent a year
A28: Upper end, in no total: only losses counted, per contract | B28: =buyback_payables_current_eur_m * x18_exp_onesided_book/100 -> 61.04637 | C28: as if every buy-back were a customer's put struck at the residual (X6's case); where a put caps the group's upside, the truth lies between zero and this
A29: Value at risk, leak 3, expected a year | B29: =(buyback_payables_current_eur_m * MAX(0, x18_exp_twosided_book)/100 + buyback_payables_current_eur_m * (x17_days_cut * x17_day_cost_central/10000 + x17_share_routed/100 * x17_channel_gain_after_costs/100)) -> 24.81171 | C29: the level and curve line above plus resale execution
A30: Level and curve together, one year in ten (base) | B30: =(buyback_payables_current_eur_m * (ABS(level_1y_p10_book)/100 + (curve_1y_p80_known/2/retained_1y_pooled * (1 - thin_share_of_book/100) + curve_1y_p80_unknown/2/retained_1y_pooled * thin_share_of_book/100))) * x18_joint_share_book/100 -> 92.471421 | C30: their joint p10, x18_joint_share_book of the sum of their separate p10s: the two are independent, and in Latvia the curve moved against the level (x18_lv_curve_level_corr_12m)
A31: Value at risk, leak 3, one year in ten (base level shock) | B31: =((buyback_payables_current_eur_m * (ABS(level_1y_p10_book)/100 + (curve_1y_p80_known/2/retained_1y_pooled * (1 - thin_share_of_book/100) + curve_1y_p80_unknown/2/retained_1y_pooled * thin_share_of_book/100))) * x18_joint_share_book/100 + buyback_payables_current_eur_m * (x17_days_cut * x17_day_cost_central/10000 + x17_share_routed/100 * x17_channel_gain_after_costs/100)) -> 117.28313 | C31: plus resale execution, at its expected value
A32: Value at risk, leak 3, one year in ten (stress level shock) | B32: =((buyback_payables_current_eur_m * (ABS(level_1y_p10_core)/100 + (curve_1y_p80_known/2/retained_1y_pooled * (1 - thin_share_of_book/100) + curve_1y_p80_unknown/2/retained_1y_pooled * thin_share_of_book/100))) * x18_joint_share_stress/100 + buyback_payables_current_eur_m * (x17_days_cut * x17_day_cost_central/10000 + x17_share_routed/100 * x17_channel_gain_after_costs/100)) -> 275.11027 | C32: the joint p10 is x18_joint_share_stress of the sum under the stress
A33: Upper end, in no total: the level and the curve at their p10s at once (base) | B33: =(buyback_payables_current_eur_m * (ABS(level_1y_p10_book)/100 + (curve_1y_p80_known/2/retained_1y_pooled * (1 - thin_share_of_book/100) + curve_1y_p80_unknown/2/retained_1y_pooled * thin_share_of_book/100)) + buyback_payables_current_eur_m * (x17_days_cut * x17_day_cost_central/10000 + x17_share_routed/100 * x17_channel_gain_after_costs/100)) -> 159.02277 | C33: both going wrong together: a year rarer than one in ten
A34: Upper end, in no total: the same under the stress | B34: =(buyback_payables_current_eur_m * (ABS(level_1y_p10_core)/100 + (curve_1y_p80_known/2/retained_1y_pooled * (1 - thin_share_of_book/100) + curve_1y_p80_unknown/2/retained_1y_pooled * thin_share_of_book/100)) + buyback_payables_current_eur_m * (x17_days_cut * x17_day_cost_central/10000 + x17_share_routed/100 * x17_channel_gain_after_costs/100)) -> 323.14134
A36: What the group books on these cars: scheduled depreciation, not a loss
A37: Decrease in value on assets sold with a buy-back commitment, 2023 | B37: =buyback_value_decrease_2023_eur_m -> 82
A38: Decrease in value on assets sold with a buy-back commitment, 2024 | B38: =buyback_value_decrease_2024_eur_m -> 179
A39: Decrease in value on assets sold with a buy-back commitment, 2025 | B39: =buyback_value_decrease_2025_eur_m -> 358 | C39: contracts of 12 months or less only
A40: Each car's cost less its estimated residual, depreciated over the contract (20-F FY2025 accounting policy): an expected cost, not a loss against the residual, so it cannot check the rows above. As a share of year-end buy-back assets it is about a year's ordinary depreciation (level_charge_report.md). The group discloses no gains or losses at disposal for this book; the ledger would record them car by car.
A42: For context: the whole book over a three-year lease (not a yearly figure)
A43: Base: the group's book over 36 months, spread across its markets (p10, -3.260%) | B43: =buyback_payables_eur_m * (ABS(level_3y_p10_book)/100 + (curve_p80_known/2/retained_3y_pooled * (1 - thin_share_of_book/100) + curve_p80_unknown/2/retained_3y_pooled * thin_share_of_book/100)) -> 517.5184 | C43: level plus curve over 36 months, on all 7,889m
A44: Stress: the whole book in a core market's bad three years (p10, -7.7%) | B44: =buyback_payables_eur_m * (ABS(level_3y_p10_core)/100 + (curve_p80_known/2/retained_3y_pooled * (1 - thin_share_of_book/100) + curve_p80_unknown/2/retained_3y_pooled * thin_share_of_book/100)) -> 867.79
A45: Reference, in no total: the worst three-year move in any market (-27.0%) | B45: =buyback_payables_eur_m * (ABS(level_3y_worst)/100 + (curve_p80_known/2/retained_3y_pooled * (1 - thin_share_of_book/100) + curve_p80_unknown/2/retained_3y_pooled * thin_share_of_book/100)) -> 2390.367
A47: What the programme actually buys
A48: Resale execution: days cut and in-house retail (above), a year | B48: =buyback_payables_current_eur_m * (x17_days_cut * x17_day_cost_central/10000 + x17_share_routed/100 * x17_channel_gain_after_costs/100) -> 24.81171 | C48: costs measured, reach assumed; the pilot measures both on the ledger
A49: Pooling the group's markets, on little-history cars only, a year | B49: =buyback_payables_current_eur_m * curve_1y_p80_unknown/2/retained_1y_pooled * thin_share_of_book/100 * pooling_gain_100/100 -> 1.6039935 | C49: lodo_report.md: 4.3% error cut at 100 local cars, 0.2% by 250
A50: Re-marking monthly instead of quarterly | B50: =buyback_payables_eur_m * (ABS(level_3m_p5)-ABS(level_1m_p5))/100 -> 134.113 | C50: exposure carried unseen between reviews on the whole book, not a loss avoided
A52: The level shock is not something the programme removes. No model forecasts the market level; the ledger's job there is to price it into the decision and re-mark it often. What the programme does remove is a share of the curve error, exactly where the book has little history, and the value lost in the sale itself: days a returned car waits and cars sold to the trade that the group's own retail would sell for more (X17).

Sheet Per car
A1: One car, and the book divided by it
A3: Lifetime profit and loss, euros for one car
A4: The worked example is a Vauxhall Corsa, entry trim, on a 48-month contract. Every line below is an ASSUMPTION with a stated basis and a range on the Assumptions sheet, except the list price and the two residual downsides, which are measured. A contribution figure, not an operating result.
A6: List price when new | B6: =new_car_price_eur -> 11969 | C6: MEASURED - one_car_report.md
A7: Sale margin | B7: =new_car_price_eur * pl_sale_margin_pct_list/100 -> 1196.9 | C7: share of list; bracketed by the group's own gross margin
A8: less incentives | B8: =-new_car_price_eur * pl_incentive_pct_list/100 -> -957.52 | C8: ASSUMPTION - a share of list (pl_incentive_pct_list); leak 1 uses the 20-F's claims ratio instead
A9: plus finance income | B9: =pl_finance_income_eur -> 450 | C9: net of rate support, an internal transfer
A10: less credit losses | B10: =pl_credit_loss_eur -> -66 | C10: a European captive's published cost of risk
A11: plus service and parts margin | B11: =pl_service_parts_eur -> 400
A12: less warranty cost | B12: =-new_car_price_eur * pl_warranty_pct_list/100 -> -299.225 | C12: share of list; bracketed by published accrual rates
A13: Residual outcome, central case | C13: realised resale equals the contractual residual, so nothing here
A14: less reconditioning, logistics and holding | B14: =pl_recon_logistics_eur -> -500
A15: plus remarketing margin | B15: =pl_remarketing_margin_eur -> 300
A16: Lifetime value per car | B16: =SUM(B7:B15) -> 524.155
A18: Residual downside - market level, p10 in the core markets | B18: =-new_car_price_eur * retained_4y_uk/100 * ABS(level_3y_p10_core)/100 -> -543.75167 | C18: MEASURED - the residual set at signing, times a bad three years
A19: Residual downside - curve error | B19: =-new_car_price_eur * curve_p80_known/100 -> -287.256 | C19: MEASURED - points of list price
A20: Lifetime value in a bad market | B20: =B16 + SUM(B18:B19) -> -306.85267
A23: Pricing the market level on one contract (X6), euros
A24: A group-typical car on a 48-month bank lease, residual right on average, core markets. Not in the headline: leak 3 is a one-in-ten year on the buy-back book, this is the price of one lease's level risk. Source: analysis/level_charge_report.md.
A25: Level charge: expected loss per 48-month contract | B25: =x6_loss_contract_group_48m -> 614 | C25: MEASURED - residual x the expected shortfall
A26: Level charge per month, set aside at the ECB rate | B26: =x6_charge_month_group_48m -> 12.19 | C26: MEASURED
A27: Capital cost of holding it (CRR Article 134(7)) | B27: =x6_capital_contract_group_48m -> 258 | C27: MEASURED - 8% + 2.5% of residual/t, at a 10% cost of equity net of the ECB rate
A28: Price to hold the level risk per contract | B28: =x6_price_contract_group_48m -> 873 | C28: MEASURED - the figure to set beside an insurer's quote
A29: Average loss in the worst tenth of windows | B29: =x6_worst_tenth_group_48m -> 2534 | C29: MEASURED - what a bad decile costs one contract; capital, not the charge, covers it
A30: Charge with the level below its 3-year average, % of residual | B30: =x6_charge_cold_48m -> 15.03 | C30: MEASURED - declines persisted: raise the charge when the level falls
A31: Charge in the middle tercile, % of residual | B31: =x6_charge_middle_48m -> 2.3 | C31: MEASURED - never cut the charge because the level runs hot
A32: Share of losses a charge set from past data covered | B32: =x6_oos_coverage_48m -> 0.63 | C32: MEASURED - out-of-sample back-test: a flat charge alone falls short
A33: Expected level loss on a battery-EV contract, if EV risk runs as on the US record | B33: =x6_loss_contract_group_48m * x9_us_ratio_48m_median -> 982.4 | C33: US DATA (X9): battery EVs' 48-month expected shortfall against the market's at the same strike (x9_us_ratio_48m_median; its 90% range in the register); Europe's evidence is one slump
A36: The book divided by the cars in it, euros a vehicle
A38: Enlarged Europe net revenue per vehicle, 2025 | B38: =eu_revenue_eur_m*1000000/eu_shipments -> 23202.008
A39: Operating result per vehicle, 2024 | B39: =eu_aoi_2024_eur_m*1000000/eu_shipments_2024 -> 939.0528
A40: Operating result per vehicle, 2025 | B40: =eu_aoi_eur_m*1000000/eu_shipments -> -261.44578
A41: Swing between the two years | B41: =B39-B40 -> 1200.4986 | C41: what one bad year cost, per vehicle
A43: Leak 1 at risk per vehicle | B43: =((eu_revenue_eur_m * x14_incentive_claims_central/100 * process_leak_pct/100 + eu_revenue_eur_m * x5_targeting_gain_central/100))*1000000/eu_shipments -> 57.053738
A44: Leak 2 at risk per vehicle | B44: =(sfse_eu_nv_contracts_2025 * upgrade_capture_uplift/100 * margin_per_repeat_sale / 1000000)*1000000/eu_shipments -> 15.56959
A45: Leak 3 at risk per vehicle, expected a year | B45: =((buyback_payables_current_eur_m * MAX(0, x18_exp_twosided_book)/100 + buyback_payables_current_eur_m * (x17_days_cut * x17_day_cost_central/10000 + x17_share_routed/100 * x17_channel_gain_after_costs/100)))*1000000/eu_shipments -> 9.9645422
A46: Leak 3 at risk per vehicle, one year in ten | B46: =(((buyback_payables_current_eur_m * (ABS(level_1y_p10_book)/100 + (curve_1y_p80_known/2/retained_1y_pooled * (1 - thin_share_of_book/100) + curve_1y_p80_unknown/2/retained_1y_pooled * thin_share_of_book/100))) * x18_joint_share_book/100 + buyback_payables_current_eur_m * (x17_days_cut * x17_day_cost_central/10000 + x17_share_routed/100 * x17_channel_gain_after_costs/100)))*1000000/eu_shipments -> 47.101659
A47: Total at risk per vehicle, expected a year | B47: =((eu_revenue_eur_m * x14_incentive_claims_central/100 * process_leak_pct/100 + eu_revenue_eur_m * x5_targeting_gain_central/100) + sfse_eu_nv_contracts_2025 * upgrade_capture_uplift/100 * margin_per_repeat_sale / 1000000 + (buyback_payables_current_eur_m * MAX(0, x18_exp_twosided_book)/100 + buyback_payables_current_eur_m * (x17_days_cut * x17_day_cost_central/10000 + x17_share_routed/100 * x17_channel_gain_after_costs/100)))*1000000/eu_shipments -> 82.58787 | C47: each leak spread over every car shipped; the leaks cover different cars (below)
A48: Total at risk per vehicle, one year in ten | B48: =((eu_revenue_eur_m * x14_incentive_claims_central/100 * process_leak_pct/100 + eu_revenue_eur_m * x5_targeting_gain_central/100) + sfse_eu_nv_contracts_2025 * upgrade_capture_uplift/100 * margin_per_repeat_sale / 1000000 + ((buyback_payables_current_eur_m * (ABS(level_1y_p10_book)/100 + (curve_1y_p80_known/2/retained_1y_pooled * (1 - thin_share_of_book/100) + curve_1y_p80_unknown/2/retained_1y_pooled * thin_share_of_book/100))) * x18_joint_share_book/100 + buyback_payables_current_eur_m * (x17_days_cut * x17_day_cost_central/10000 + x17_share_routed/100 * x17_channel_gain_after_costs/100)))*1000000/eu_shipments -> 119.72499 | C48: leak 3's level and curve at their joint one-in-ten (X18)
A49: Under the stress level shock | B49: =((eu_revenue_eur_m * x14_incentive_claims_central/100 * process_leak_pct/100 + eu_revenue_eur_m * x5_targeting_gain_central/100) + sfse_eu_nv_contracts_2025 * upgrade_capture_uplift/100 * margin_per_repeat_sale / 1000000 + ((buyback_payables_current_eur_m * (ABS(level_1y_p10_core)/100 + (curve_1y_p80_known/2/retained_1y_pooled * (1 - thin_share_of_book/100) + curve_1y_p80_unknown/2/retained_1y_pooled * thin_share_of_book/100))) * x18_joint_share_stress/100 + buyback_payables_current_eur_m * (x17_days_cut * x17_day_cost_central/10000 + x17_share_routed/100 * x17_channel_gain_after_costs/100)))*1000000/eu_shipments -> 183.10938 | C49: the whole book in a core market's bad year
A50: Leakage against the 2025 result per vehicle, expected a year | B50: =-B47/B40 -> 0.31588909 | C50: the expected yearly leakage is this many times the loss the group reported per vehicle
A51: Leak 2 at risk per financed contract | B51: =(sfse_eu_nv_contracts_2025 * upgrade_capture_uplift/100 * margin_per_repeat_sale / 1000000)*1000000/sfse_eu_nv_contracts_2025 -> 60 | C51: the cars leak 2 is about: the contracts SFSE wrote in Europe (sfse_eu_nv_contracts_2025)
A53: Which cars each leak covers (X14, skeptic B6). Leak 1: every car sold to a dealer with an incentive programme, in every channel. Leak 2: the contracts the group's finance arm writes, private and business, in joint ventures with Santander CF and BNP Paribas PF; Leasys's fleet leases are left out. Leak 3: cars sold with a repurchase commitment and due back within a year. The 20-F names no buyer except the group's own leasing and rental joint ventures (Leasys, and the Santander and BNP ventures, Note 29): part of their lease residuals comes back to the group this way. Most of the book is due within a year, the term of a rental fleet, but its mix is not published. No count of buy-back cars is disclosed, so leak 3 has no per-car divisor of its own.
A55: What the programme has to capture to pay for itself
A57: Value at risk a year, expected, EUR m | B57: =(eu_revenue_eur_m * x14_incentive_claims_central/100 * process_leak_pct/100 + eu_revenue_eur_m * x5_targeting_gain_central/100) + sfse_eu_nv_contracts_2025 * upgrade_capture_uplift/100 * margin_per_repeat_sale / 1000000 + (buyback_payables_current_eur_m * MAX(0, x18_exp_twosided_book)/100 + buyback_payables_current_eur_m * (x17_days_cut * x17_day_cost_central/10000 + x17_share_routed/100 * x17_channel_gain_after_costs/100)) -> 205.6438 | C57: a programme pays for itself out of the yearly expected cost, not out of a bad year (X18)
A58: Programme cost over 24 months, 1. In-house, no AI, EUR m | B58: ='Programme cost'!$F$18 -> 15.569603
A59: Share of it the programme must capture to break even, 1. In-house, no AI | B59: =B58/B57 -> 0.075711513
A60: Programme cost over 24 months, 2. Buy and outsource, EUR m | B60: ='Programme cost'!$F$19 -> 30.876957
A61: Share of it the programme must capture to break even, 2. Buy and outsource | B61: =B60/B57 -> 0.15014777
A62: Programme cost over 24 months, 3. In-house with AI, EUR m | B62: ='Programme cost'!$F$20 -> 15.245275
A63: Share of it the programme must capture to break even, 3. In-house with AI | B63: =B62/B57 -> 0.07413438
A64: Programme cost over 24 months, 4. Cheapest route per workstream, EUR m | B64: ='Programme cost'!$F$23 -> 15.245275
A65: Share of it the programme must capture to break even, 4. Cheapest route per workstream | B65: =B64/B57 -> 0.07413438
A66: Four build scenarios from the Programme cost sheet (X25), none chosen. Against what is at risk, not what the programme gets back: the Benefits sheet sizes that lever by lever, with payback for each scenario and switching values (X21).
A69: Why a better model cannot shrink the book's risk
A70: Per-car errors are roughly independent, so they average away as one over the square root of the number of cars. A level move is common to every car and does not average away at all.
A72: cars in the book | B72: average per-car model error, % | C72: market level move over 3 years, points of list
A73: 1 | B73: =engine_err_typical/SQRT(A73) -> 10.5 | C73: =level_points -> 26.5
A74: 10 | B74: =engine_err_typical/SQRT(A74) -> 3.3203915 | C74: =level_points -> 26.5
A75: 100 | B75: =engine_err_typical/SQRT(A75) -> 1.05 | C75: =level_points -> 26.5
A76: 1000 | B76: =engine_err_typical/SQRT(A76) -> 0.33203915 | C76: =level_points -> 26.5
A77: 10000 | B77: =engine_err_typical/SQRT(A77) -> 0.105 | C77: =level_points -> 26.5

Sheet Internal prices
A1: Internal prices: from seeing to deciding (X19)
A2: A ledger that shows lifetime cost changes no decision made by a business paid on its own P&L. These prices put each business's cost into the others' decisions, at the moment of sale. They are transfers inside the group, so no value-at-risk figure moves. The sample car is the Per car sheet's.
A4: 1. The discount's resale cost, charged to the business that gives it
B5: low (measured) | C5: high (published)
A6: Resale value lost per euro of incentive, EUR | B6: =new_car_price_eur * retained_4y_uk/100*(1 - (1 - pl_incentive_pct_list/100)^dpt_passthrough)/(new_car_price_eur * pl_incentive_pct_list/100) -> 0.18219357 | C6: =new_car_price_eur * retained_4y_uk/100*((hk_passthrough_36m + hk_passthrough_now)/100 * pl_incentive_pct_list/10)/(new_car_price_eur * pl_incentive_pct_list/100) -> 0.472
A7: On the sample car's incentive, EUR per car | B7: =new_car_price_eur * retained_4y_uk/100*(1 - (1 - pl_incentive_pct_list/100)^dpt_passthrough) -> 174.45399 | C7: =new_car_price_eur * retained_4y_uk/100*((hk_passthrough_36m + hk_passthrough_now)/100 * pl_incentive_pct_list/10) -> 451.94944
A8: What one more euro of discount costs the group, EUR | B8: =-(1 + new_car_price_eur * retained_4y_uk/100*(1 - (1 - pl_incentive_pct_list/100)^dpt_passthrough)/(new_car_price_eur * pl_incentive_pct_list/100)) -> -1.1821936 | C8: =-(1 + new_car_price_eur * retained_4y_uk/100*((hk_passthrough_36m + hk_passthrough_now)/100 * pl_incentive_pct_list/10)/(new_car_price_eur * pl_incentive_pct_list/100)) -> -1.472
A9: Charged at sale to the sales side, on cars the group will take back (the buy-back book and contracts where it carries the residual); on the rest the cost falls on the buyer, and through the brand's used prices on later residuals (unmeasured). Why it works: paid on a margin that includes this cost, the sales side's own best discount is the group's (weinberg_margin_commission). It extends a price that exists: the group already pays subvention to its leasing programmes and says a residual fall raises it (stellantis_subvention_residual). Subvention is already inside the incentive provision (stellantis_subvention_incentive), so charge the resale cost on the price the buyer pays, never twice. A range until the pilot calibrates it: the low end is an upper bound on our own data.
A11: 2. The market level, priced by book
A12: Customer-option contract, 48 months: price to hold, % of residual | B12: =x6_price_share_group_48m -> 6.38 | C12: X6: one-sided expected loss plus CRR 134(7) capital; bank leases and the joint ventures' residuals that come back through repurchase agreements
A13: on the sample car's 48-month residual, EUR | B13: =new_car_price_eur * retained_4y_uk/100 * x6_price_share_group_48m/100 -> 450.5371
A14: Buy-back contract, a year or less: expected level cost, both sides counted, % of residual | B14: =MAX(0, x19_core_all_two_12m) -> 0 | C14: the 20-F's contracts bring the cars back: on average a gain (x19_core_all_two_12m), so zero
A15: plus when the level starts in its cold third, % of residual | B15: =x19_core_cold_premium_12m -> 1.01 | C15: the core markets; the UK's long record agrees (x19_uk_cold_premium_12m). Never cut it when hot (X6)
A16: plus the cost of holding the tail, % of residual a year | B16: =(crr_total_capital_ratio + crd_conservation_buffer)/100 * (eba_bank_coe - ecb_deposit_rate) -> 0.7875 | C16: X6's capital rule, as if a bank held it: a residual of a year or less weighs 100%, 8% plus the 2.5% buffer, at banks' cost of equity net of the ECB rate. A convention: the book sits outside CRR
A17: the holding cost on the buy-back book due within a year, EUR m | B17: =buyback_payables_current_eur_m * (crr_total_capital_ratio + crd_conservation_buffer)/100 * (eba_bank_coe - ecb_deposit_rate)/100 -> 41.839875
A18: the cold premium on the same book, EUR m, in a year that starts cold | B18: =buyback_payables_current_eur_m * x19_core_cold_premium_12m/100 -> 53.6613
A19: The pricer's override band, cars 2-4 years, % | B19: =x13_tied_cap_young -> 3.4 | C19: X13: tied to the engine's calibrated band, ±5% on average
A20: cars 12 years and older, % | B20: =x13_tied_cap_old -> 8.2
A22: 3. One worked trade-off: pulling an upgrade forward (per customer, sample car)
B23: months at their low | C23: base | D23: months at their high
A24: Months pulled forward | B24: =Assumptions!$D$719 -> 6 | C24: =x19_pull_forward_months -> 12 | D24: =Assumptions!$E$719 -> 18
A25: Old contract's balance at the switch, EUR | B25: =INDEX('Leak 2 - Upgrade timing'!$B$18:$B$78,loan_term_months-Assumptions!$D$719+1)*new_car_price_eur/100 -> 1432.3389 | C25: =INDEX('Leak 2 - Upgrade timing'!$B$18:$B$78,loan_term_months-x19_pull_forward_months+1)*new_car_price_eur/100 -> 2815.5538 | D25: =INDEX('Leak 2 - Upgrade timing'!$B$18:$B$78,loan_term_months-Assumptions!$E$719+1)*new_car_price_eur/100 -> 4151.3295
A26: Car value at the switch, EUR | B26: =INDEX('Leak 2 - Upgrade timing'!$C$18:$C$78,loan_term_months-Assumptions!$D$719+1)*new_car_price_eur/100 -> 7480.625 | C26: =INDEX('Leak 2 - Upgrade timing'!$C$18:$C$78,loan_term_months-x19_pull_forward_months+1)*new_car_price_eur/100 -> 7899.54 | D26: =INDEX('Leak 2 - Upgrade timing'!$C$18:$C$78,loan_term_months-Assumptions!$E$719+1)*new_car_price_eur/100 -> 8617.68
A27: Customer's equity at the switch less the next deposit, EUR | B27: =(INDEX('Leak 2 - Upgrade timing'!$C$18:$C$78,loan_term_months-Assumptions!$D$719+1)-INDEX('Leak 2 - Upgrade timing'!$B$18:$B$78,loan_term_months-Assumptions!$D$719+1)-loan_deposit_pct)*new_car_price_eur/100 -> 4252.9361 | C27: =(INDEX('Leak 2 - Upgrade timing'!$C$18:$C$78,loan_term_months-x19_pull_forward_months+1)-INDEX('Leak 2 - Upgrade timing'!$B$18:$B$78,loan_term_months-x19_pull_forward_months+1)-loan_deposit_pct)*new_car_price_eur/100 -> 3288.6362 | D27: =(INDEX('Leak 2 - Upgrade timing'!$C$18:$C$78,loan_term_months-Assumptions!$E$719+1)-INDEX('Leak 2 - Upgrade timing'!$B$18:$B$78,loan_term_months-Assumptions!$E$719+1)-loan_deposit_pct)*new_car_price_eur/100 -> 2671.0005
A28: A younger car: value at the switch less at the contract's end, EUR | B28: =(INDEX('Leak 2 - Upgrade timing'!$C$18:$C$78,loan_term_months-Assumptions!$D$719+1)-INDEX('Leak 2 - Upgrade timing'!$C$18:$C$78,loan_term_months+1))*new_car_price_eur/100 -> 418.915 | C28: =(INDEX('Leak 2 - Upgrade timing'!$C$18:$C$78,loan_term_months-x19_pull_forward_months+1)-INDEX('Leak 2 - Upgrade timing'!$C$18:$C$78,loan_term_months+1))*new_car_price_eur/100 -> 837.83 | D28: =(INDEX('Leak 2 - Upgrade timing'!$C$18:$C$78,loan_term_months-Assumptions!$E$719+1)-INDEX('Leak 2 - Upgrade timing'!$C$18:$C$78,loan_term_months+1))*new_car_price_eur/100 -> 1555.97
A29: Finance arm's margin a year per euro outstanding, after credit losses | B29: =(sfse_pnb_ifrs8_2025_eur_m - sfse_cor_ifrs8_2025_eur_m)/(sfse_cor_ifrs8_2025_eur_m/(sfse_cor_pct_outstanding_2025/100)) -> 0.035953304 | C29: =(sfse_pnb_ifrs8_2025_eur_m - sfse_cor_ifrs8_2025_eur_m)/(sfse_cor_ifrs8_2025_eur_m/(sfse_cor_pct_outstanding_2025/100)) -> 0.035953304 | D29: =(sfse_pnb_ifrs8_2025_eur_m - sfse_cor_ifrs8_2025_eur_m)/(sfse_cor_ifrs8_2025_eur_m/(sfse_cor_pct_outstanding_2025/100)) -> 0.035953304
A30: Finance arm, taker refinances with the group: margin on the new balance less the old, EUR | B30: =(sfse_pnb_ifrs8_2025_eur_m - sfse_cor_ifrs8_2025_eur_m)/(sfse_cor_ifrs8_2025_eur_m/(sfse_cor_pct_outstanding_2025/100))*(AVERAGE(INDEX('Leak 2 - Upgrade timing'!$B$18:$B$78,1):INDEX('Leak 2 - Upgrade timing'!$B$18:$B$78,Assumptions!$D$719))-AVERAGE(INDEX('Leak 2 - Upgrade timing'!$B$18:$B$78,loan_term_months-Assumptions!$D$719+1):INDEX('Leak 2 - Upgrade timing'!$B$18:$B$78,loan_term_months)))/100*new_car_price_eur*Assumptions!$D$719/12 -> 159.44903 | C30: =(sfse_pnb_ifrs8_2025_eur_m - sfse_cor_ifrs8_2025_eur_m)/(sfse_cor_ifrs8_2025_eur_m/(sfse_cor_pct_outstanding_2025/100))*(AVERAGE(INDEX('Leak 2 - Upgrade timing'!$B$18:$B$78,1):INDEX('Leak 2 - Upgrade timing'!$B$18:$B$78,x19_pull_forward_months))-AVERAGE(INDEX('Leak 2 - Upgrade timing'!$B$18:$B$78,loan_term_months-x19_pull_forward_months+1):INDEX('Leak 2 - Upgrade timing'!$B$18:$B$78,loan_term_months)))/100*new_car_price_eur*x19_pull_forward_months/12 -> 273.20267 | D30: =(sfse_pnb_ifrs8_2025_eur_m - sfse_cor_ifrs8_2025_eur_m)/(sfse_cor_ifrs8_2025_eur_m/(sfse_cor_pct_outstanding_2025/100))*(AVERAGE(INDEX('Leak 2 - Upgrade timing'!$B$18:$B$78,1):INDEX('Leak 2 - Upgrade timing'!$B$18:$B$78,Assumptions!$E$719))-AVERAGE(INDEX('Leak 2 - Upgrade timing'!$B$18:$B$78,loan_term_months-Assumptions!$E$719+1):INDEX('Leak 2 - Upgrade timing'!$B$18:$B$78,loan_term_months)))/100*new_car_price_eur*Assumptions!$E$719/12 -> 341.39948
A31: Finance arm, taker finances elsewhere: margin given up on the old balance, EUR | B31: =-(sfse_pnb_ifrs8_2025_eur_m - sfse_cor_ifrs8_2025_eur_m)/(sfse_cor_ifrs8_2025_eur_m/(sfse_cor_pct_outstanding_2025/100))*AVERAGE(INDEX('Leak 2 - Upgrade timing'!$B$18:$B$78,loan_term_months-Assumptions!$D$719+1):INDEX('Leak 2 - Upgrade timing'!$B$18:$B$78,loan_term_months))/100*new_car_price_eur*Assumptions!$D$719/12 -> -15.092851 | C31: =-(sfse_pnb_ifrs8_2025_eur_m - sfse_cor_ifrs8_2025_eur_m)/(sfse_cor_ifrs8_2025_eur_m/(sfse_cor_pct_outstanding_2025/100))*AVERAGE(INDEX('Leak 2 - Upgrade timing'!$B$18:$B$78,loan_term_months-x19_pull_forward_months+1):INDEX('Leak 2 - Upgrade timing'!$B$18:$B$78,loan_term_months))/100*new_car_price_eur*x19_pull_forward_months/12 -> -55.416731 | D31: =-(sfse_pnb_ifrs8_2025_eur_m - sfse_cor_ifrs8_2025_eur_m)/(sfse_cor_ifrs8_2025_eur_m/(sfse_cor_pct_outstanding_2025/100))*AVERAGE(INDEX('Leak 2 - Upgrade timing'!$B$18:$B$78,loan_term_months-Assumptions!$E$719+1):INDEX('Leak 2 - Upgrade timing'!$B$18:$B$78,loan_term_months))/100*new_car_price_eur*Assumptions!$E$719/12 -> -120.10631
A32: most it may charge for early repayment from 20 November 2026, EUR | B32: =MIN(IF(Assumptions!$D$719>12,ccd2_early_repayment_cap_pct,ccd2_early_repayment_cap_last_year_pct)/100*INDEX('Leak 2 - Upgrade timing'!$B$18:$B$78,loan_term_months-Assumptions!$D$719+1),loan_apr/100*AVERAGE(INDEX('Leak 2 - Upgrade timing'!$B$18:$B$78,loan_term_months-Assumptions!$D$719+1):INDEX('Leak 2 - Upgrade timing'!$B$18:$B$78,loan_term_months))*Assumptions!$D$719/12)*new_car_price_eur/100 -> 7.1616947 | C32: =MIN(IF(x19_pull_forward_months>12,ccd2_early_repayment_cap_pct,ccd2_early_repayment_cap_last_year_pct)/100*INDEX('Leak 2 - Upgrade timing'!$B$18:$B$78,loan_term_months-x19_pull_forward_months+1),loan_apr/100*AVERAGE(INDEX('Leak 2 - Upgrade timing'!$B$18:$B$78,loan_term_months-x19_pull_forward_months+1):INDEX('Leak 2 - Upgrade timing'!$B$18:$B$78,loan_term_months))*x19_pull_forward_months/12)*new_car_price_eur/100 -> 14.077769 | D32: =MIN(IF(Assumptions!$E$719>12,ccd2_early_repayment_cap_pct,ccd2_early_repayment_cap_last_year_pct)/100*INDEX('Leak 2 - Upgrade timing'!$B$18:$B$78,loan_term_months-Assumptions!$E$719+1),loan_apr/100*AVERAGE(INDEX('Leak 2 - Upgrade timing'!$B$18:$B$78,loan_term_months-Assumptions!$E$719+1):INDEX('Leak 2 - Upgrade timing'!$B$18:$B$78,loan_term_months))*Assumptions!$E$719/12)*new_car_price_eur/100 -> 41.513295
A33: Retained sale: contribution per customer won, EUR | B33: =margin_per_repeat_sale -> 2000 | C33: =margin_per_repeat_sale -> 2000 | D33: =margin_per_repeat_sale -> 2000
A34: Retention gain per customer contacted, EUR | B34: =upgrade_capture_uplift/100*margin_per_repeat_sale -> 60 | C34: =upgrade_capture_uplift/100*margin_per_repeat_sale -> 60 | D34: =upgrade_capture_uplift/100*margin_per_repeat_sale -> 60
A35: What the trade-off says. Interest: a customer who refinances with the group replaces a nearly repaid balance with a new one, so the finance arm earns more over those months, not less; only a customer who finances elsewhere costs it the old margin, and from November 2026 it may recover little of that (Directive (EU) 2023/2225, Art. 29). The retained sale is worth far more than either. The customer's equity covers the next deposit, so no subsidy is needed to make the switch possible. The younger car's extra value is the customer's equity; what more young cars do to the market level is not measured. So the decision turns on one number: how many customers the offer wins that would not have come back anyway. Every euro paid to someone who would have upgraded regardless is lost, no model yet picks them out (X15), so the pilot's randomised holdout measures the uplift before any offer is set. Later contracts shift earlier too; this block counts only the months pulled forward.
A37: 4. The operating metric: predicted lifetime value at sale (sample car)
B38: low (measured) | C38: high (published)
A39: Lifetime value per car, the Per car sheet's P&L, EUR | B39: =new_car_price_eur*pl_sale_margin_pct_list/100 - new_car_price_eur*pl_incentive_pct_list/100 + pl_finance_income_eur + pl_credit_loss_eur + pl_service_parts_eur - new_car_price_eur*pl_warranty_pct_list/100 + pl_recon_logistics_eur + pl_remarketing_margin_eur -> 524.155 | C39: =new_car_price_eur*pl_sale_margin_pct_list/100 - new_car_price_eur*pl_incentive_pct_list/100 + pl_finance_income_eur + pl_credit_loss_eur + pl_service_parts_eur - new_car_price_eur*pl_warranty_pct_list/100 + pl_recon_logistics_eur + pl_remarketing_margin_eur -> 524.155
A40: less the incentive's resale cost, EUR | B40: =-new_car_price_eur * retained_4y_uk/100*(1 - (1 - pl_incentive_pct_list/100)^dpt_passthrough) -> -174.45399 | C40: =-new_car_price_eur * retained_4y_uk/100*((hk_passthrough_36m + hk_passthrough_now)/100 * pl_incentive_pct_list/10) -> -451.94944
A41: less the level's price to hold, customer-option contract, EUR | B41: =-new_car_price_eur * retained_4y_uk/100*x6_price_share_group_48m/100 -> -450.5371 | C41: =-new_car_price_eur * retained_4y_uk/100*x6_price_share_group_48m/100 -> -450.5371
A42: Predicted lifetime value at sale, EUR | B42: =new_car_price_eur*pl_sale_margin_pct_list/100 - new_car_price_eur*pl_incentive_pct_list/100 + pl_finance_income_eur + pl_credit_loss_eur + pl_service_parts_eur - new_car_price_eur*pl_warranty_pct_list/100 + pl_recon_logistics_eur + pl_remarketing_margin_eur - new_car_price_eur * retained_4y_uk/100*(1 - (1 - pl_incentive_pct_list/100)^dpt_passthrough) - new_car_price_eur * retained_4y_uk/100*x6_price_share_group_48m/100 -> -100.83609 | C42: =new_car_price_eur*pl_sale_margin_pct_list/100 - new_car_price_eur*pl_incentive_pct_list/100 + pl_finance_income_eur + pl_credit_loss_eur + pl_service_parts_eur - new_car_price_eur*pl_warranty_pct_list/100 + pl_recon_logistics_eur + pl_remarketing_margin_eur - new_car_price_eur * retained_4y_uk/100*((hk_passthrough_36m + hk_passthrough_now)/100 * pl_incentive_pct_list/10) - new_car_price_eur * retained_4y_uk/100*x6_price_share_group_48m/100 -> -378.33154
A43: Share of the buy-back book that comes back within a year | B43: =buyback_payables_current_eur_m/buyback_payables_eur_m -> 0.67346939 | C43: so realised values audit the metric within a year for most of the book, not 36-48 months later
A44: The metric is known at sale and set by the engines, not by the seller: the sale margin and incentive, the incentive's resale cost, the level's price for the contract's book, finance income and the rest of the Per car P&L. Realised value is the audit: the buy-back book comes back within a year for the most part, Aramis publishes realised prices every quarter (X10), leases come back in waves at 48 and 60 months (X3), and the engine's calibrated band sets how far a realised value may miss before the prediction counts as wrong (X15). A shadow scorecard runs it from Phase 2. Guard against gaming (Kerr, Goodhart): the seller sets no input the engines use, overrides stay inside the band, and every prediction is audited when the car comes back. Only the deal terms move it, which is the point: one more euro of discount lowers it by more than a euro (section 1).
A46: Why a price changes behaviour here
A47: Group brands' share of new cars registered in a month's last 3 days, % | B47: =selfreg_group_monthend_share -> 47.73 | C47: the Netherlands, before the agency model: target timing
A48: other brands, same period, % | B48: =selfreg_other_monthend_share -> 16.73
A49: Revenue gain when one firm removed its salespeople's gamed quotas, % | B49: =misra_nair_revenue_gain_pct -> 9 | C49: US data, one firm (Misra and Nair 2011): pay design moves a sales force a lot

Sheet Data reach
A1: Data reach: what each lever can work on, by source (X20)
A2: EUR millions a year, the expected column. Each cell is the part of a leak the programme can act on when a source is missing: reach, not a benefit (X21 sizes benefits on it). The map of sources, holders, routes and fallbacks is in analysis/data_reach_report.md.
A4: lever | B4: every source | C4: without the joint ventures' data | D4: without dealers' VIN-level evidence | E4: what limits it
A5: Leak 1, claims | B5: =eu_revenue_eur_m * x14_incentive_claims_central/100 * process_leak_pct/100 -> 77.99355 | C5: =eu_revenue_eur_m * x14_incentive_claims_central/100 * process_leak_pct/100 -> 77.99355 | D5: =eu_revenue_eur_m * x14_incentive_claims_central/100 * process_leak_pct/100 * x20_reg_route_any_2024/100 -> 29.013601 | E5: every claim passes through the group; without proof of sale, only markets whose register answers per car (NL, ES, IT: x20_reg_route_any_2024), and there by sampled spot checks
A6: Leak 1, targeting | B6: =eu_revenue_eur_m * x5_targeting_gain_central/100 * finance_penetration/100 -> 18.516304 | C6: =eu_revenue_eur_m * x5_targeting_gain_central/100 * x14_agency_share_2025p/100 -> 4.99748 | D6: =eu_revenue_eur_m * x5_targeting_gain_central/100 * finance_penetration/100 -> 18.516304 | E6: floors: buyers whose income the finance partner sees (finance_penetration), or, without it, buyers the group sells to itself (agency markets); a rebate claimed with income evidence could reach more
A7: Leak 2, upgrade moments | B7: =sfse_eu_nv_contracts_2025 * upgrade_capture_uplift/100 * margin_per_repeat_sale / 1000000 -> 38.76828 | C7: 0 | D7: =sfse_eu_nv_contracts_2025 * upgrade_capture_uplift/100 * margin_per_repeat_sale / 1000000 -> 38.76828 | E7: customer-level timing and contact sit with the joint ventures; without them, cohort-level timing only (X3's waves), whose conversion is unmeasured
A8: Leak 3, resale execution | B8: =buyback_payables_current_eur_m * (x17_days_cut * x17_day_cost_central/10000 + x17_share_routed/100 * x17_channel_gain_after_costs/100) -> 24.81171 | C8: =buyback_payables_current_eur_m * (x17_days_cut * x17_day_cost_central/10000 + x17_share_routed/100 * x17_channel_gain_after_costs/100) -> 24.81171 | D8: =buyback_payables_current_eur_m * (x17_days_cut * x17_day_cost_central/10000 + x17_share_routed/100 * x17_channel_gain_after_costs/100) -> 24.81171 | E8: the buy-back book is the group's own
A9: Leak 3, level and curve | B9: =buyback_payables_current_eur_m * MAX(0, x18_exp_twosided_book)/100 -> 0 | C9: =buyback_payables_current_eur_m * MAX(0, x18_exp_twosided_book)/100 -> 0 | D9: =buyback_payables_current_eur_m * MAX(0, x18_exp_twosided_book)/100 -> 0 | E9: zero in the expected column (X18); the one-in-ten line is the group's own book in every case
A10: Reachable, expected a year | B10: =SUM(B5:B9) -> 160.08984 | C10: =SUM(C5:C9) -> 107.80274 | D10: =SUM(D5:D9) -> 111.10989
A11: Share of the expected column | B11: =B10/((eu_revenue_eur_m * x14_incentive_claims_central/100 * process_leak_pct/100 + eu_revenue_eur_m * x5_targeting_gain_central/100) + sfse_eu_nv_contracts_2025 * upgrade_capture_uplift/100 * margin_per_repeat_sale / 1000000 + (buyback_payables_current_eur_m * MAX(0, x18_exp_twosided_book)/100 + buyback_payables_current_eur_m * (x17_days_cut * x17_day_cost_central/10000 + x17_share_routed/100 * x17_channel_gain_after_costs/100))) -> 0.77848127 | C11: =C10/((eu_revenue_eur_m * x14_incentive_claims_central/100 * process_leak_pct/100 + eu_revenue_eur_m * x5_targeting_gain_central/100) + sfse_eu_nv_contracts_2025 * upgrade_capture_uplift/100 * margin_per_repeat_sale / 1000000 + (buyback_payables_current_eur_m * MAX(0, x18_exp_twosided_book)/100 + buyback_payables_current_eur_m * (x17_days_cut * x17_day_cost_central/10000 + x17_share_routed/100 * x17_channel_gain_after_costs/100))) -> 0.52422072 | D11: =D10/((eu_revenue_eur_m * x14_incentive_claims_central/100 * process_leak_pct/100 + eu_revenue_eur_m * x5_targeting_gain_central/100) + sfse_eu_nv_contracts_2025 * upgrade_capture_uplift/100 * margin_per_repeat_sale / 1000000 + (buyback_payables_current_eur_m * MAX(0, x18_exp_twosided_book)/100 + buyback_payables_current_eur_m * (x17_days_cut * x17_day_cost_central/10000 + x17_share_routed/100 * x17_channel_gain_after_costs/100))) -> 0.54030268
A13: Read it with the map. Leak 3 needs no partner's permission: the buy-back commitments are the group's own, the price level is public, Aramis publishes realised prices, and a returned car's data can be read under the group's own contract with the rental firm or leasing company, which the Data Act treats as the car's user (data_act_user_owner_lessee). Leak 2 needs the joint ventures: the fallback is a division of labour, the group's timing and the partner's contact (its own soft opt-in covers a new finance contract, eprivacy_soft_optin), under an Art 26 arrangement for anything customer-level. Leak 1's claims control rests on what the group can require by contract, since the registers of its two largest markets are closed to it (x20_reg_no_route_2024).

Sheet Benefits
A1: Benefits: what the programme gets back, and whether it pays (X21)
A2: EUR millions. Each euro sits in one lever class: recovered and counted; an upper bound that needs a holdout (shown, never committed); the tail cut one year in ten. The level charge and the cold premium are priced, not recovered, and the transfer price, the metric and the band are how the counted levers happen, so none of them carries a euro of its own. Tested the Green Book's way: a reference class, a stress and switching values (analysis/benefits_case_report.md).
A4: The levers: yearly benefit at full coverage
A5: lever | B5: class | C5: earns from | D5: every source | E5: without the joint ventures' data | F5: without dealers' VIN-level evidence | G5: every source, our adverse ends | H5: measured by
A6: Claims controls | B6: recovered | C6: Phase 2 | D6: =eu_revenue_eur_m * x14_incentive_claims_central/100 * process_leak_pct/100 * recoverable_share/100 -> 23.398065 | E6: =eu_revenue_eur_m * x14_incentive_claims_central/100 * process_leak_pct/100 * recoverable_share/100 -> 23.398065 | F6: =eu_revenue_eur_m * x14_incentive_claims_central/100 * process_leak_pct/100 * recoverable_share/100 * x20_reg_route_any_2024/100 -> 8.7040802 | G6: =eu_revenue_eur_m * x14_incentive_claims_central/100 * Assumptions!$D$114/100 * Assumptions!$D$115/100 -> 1.9498388 | H6: Phase 1: duplicate precision and the leakage baseline Finance certifies
A7: Retention at the upgrade moment | B7: recovered | C7: Phase 3 | D7: =sfse_eu_nv_contracts_2025 * upgrade_capture_uplift/100 * margin_per_repeat_sale / 1000000 -> 38.76828 | E7: =0 -> 0 | F7: =sfse_eu_nv_contracts_2025 * upgrade_capture_uplift/100 * margin_per_repeat_sale / 1000000 -> 38.76828 | G7: =sfse_eu_nv_contracts_2025 * Assumptions!$D$134/100 * Assumptions!$D$135 / 1000000 -> 6.46138 | H7: Phase 2: uplift over a randomised control group
A8: Resale execution: days cut | B8: recovered | C8: Phase 3 | D8: =buyback_payables_current_eur_m * x17_days_cut * x17_day_cost_central/10000 -> 16.31091 | E8: =buyback_payables_current_eur_m * x17_days_cut * x17_day_cost_central/10000 -> 16.31091 | F8: =buyback_payables_current_eur_m * x17_days_cut * x17_day_cost_central/10000 -> 16.31091 | G8: =buyback_payables_current_eur_m * Assumptions!$D$685 * x17_day_cost_central/10000 -> 8.155455 | H8: Phase 3: days to sale on returns (X22)
A9: Resale execution: own retail | B9: recovered | C9: Phase 3 | D9: =buyback_payables_current_eur_m * x17_share_routed/100 * x17_channel_gain_after_costs/100 -> 8.5008 | E9: =buyback_payables_current_eur_m * x17_share_routed/100 * x17_channel_gain_after_costs/100 -> 8.5008 | F9: =buyback_payables_current_eur_m * x17_share_routed/100 * x17_channel_gain_after_costs/100 -> 8.5008 | G9: =buyback_payables_current_eur_m * Assumptions!$D$686/100 * x17_channel_gain_after_costs/100 -> 3.40032 | H9: Phase 3: margin per routed car (X22)
A10: Income targeting (X5) | B10: upper bound, needs a holdout | C10: Phase 4 | D10: =eu_revenue_eur_m * x5_targeting_gain_central/100 * finance_penetration/100 -> 18.516304 | E10: =eu_revenue_eur_m * x5_targeting_gain_central/100 * x14_agency_share_2025p/100 -> 4.99748 | F10: =eu_revenue_eur_m * x5_targeting_gain_central/100 * finance_penetration/100 -> 18.516304 | G10: =eu_revenue_eur_m * x5_targeting_gain_central/100 * finance_penetration/100 -> 18.516304 | H10: Phase 3: randomised incentive holdouts
A11: Little-history cars priced as known cars | B11: tail reduced, one year in ten | C11: Phase 3 | D11: =buyback_payables_current_eur_m * thin_share_of_book/100 * (curve_1y_p80_unknown - curve_1y_p80_known)/2/retained_1y_pooled * x18_joint_share_book/100 -> 20.661748 | E11: =buyback_payables_current_eur_m * thin_share_of_book/100 * (curve_1y_p80_unknown - curve_1y_p80_known)/2/retained_1y_pooled * x18_joint_share_book/100 -> 20.661748 | F11: =buyback_payables_current_eur_m * thin_share_of_book/100 * (curve_1y_p80_unknown - curve_1y_p80_known)/2/retained_1y_pooled * x18_joint_share_book/100 -> 20.661748 | G11: =buyback_payables_current_eur_m * thin_share_of_book/100 * (curve_1y_p80_unknown - curve_1y_p80_known)/2/retained_1y_pooled * x18_joint_share_book/100 -> 20.661748 | H11: Phase 3: little-history error
A12: Committed, expected a year | D12: =SUM(D6:D9) -> 86.978055 | E12: =SUM(E6:E9) -> 48.209775 | F12: =SUM(F6:F9) -> 72.28407 | G12: =SUM(G6:G9) -> 19.966994
A14: Coverage: the share of the group's volume live, by period
A15: period | B15: Phase 1 | C15: Phase 2 | D15: Phase 3 | E15: Phase 4 | F15: Year 1 after the exit | G15: Year 2 after the exit | H15: Year 3 after the exit | I15: Year 4 after the exit | J15: Year 5 after the exit | K15: Year 6 after the exit | L15: Year 7 after the exit | M15: Year 8 after the exit | N15: Year 9 after the exit
A16: share live (Phase 1: none; the pilot; the core markets; after the exit, all) | B16: 0 | C16: =x21_cov_pilot_2024/100 -> 0.281 | D16: =x21_cov_core_2024/100 -> 0.809 | E16: =x21_cov_core_2024/100 -> 0.809 | F16: 1 | G16: 1 | H16: 1 | I16: 1 | J16: 1 | K16: 1 | L16: 1 | M16: 1 | N16: 1
A17: Short horizon, months (the Green Book's five-year IT example) | B17: =gb_appraisal_it_example_years*12 -> 60
A18: Long horizon, months (the Green Book's ten-year default) | B18: =gb_appraisal_default_years*12 -> 120
A20: The cases
A21: case | B21: benefits realised | C21: build cost, share of plan | D21: months a phase | E21: source
A22: plan | B22: 1 | C22: 1 | D22: =x21_phase_months -> 6 | E22: the register
A23: reference class | B23: =1-mckox_sw_benefit_shortfall_pct/100 -> 0.83 | C23: =1+mckox_sw_cost_overrun_pct/100 -> 1.66 | D23: =x21_phase_months*(1+mckox_sw_schedule_overrun_pct/100) -> 7.98 | E23: McKinsey-Oxford, software projects
A24: stress, 25% of benefits | B24: =fb_stress_benefit_low_pct/100 -> 0.25 | C24: =1+fb_stress_cost_overrun_pct/100 -> 5 | D24: =D23 -> 7.98 | E24: Flyvbjerg-Budzier's stress test; phases as the reference class
A25: stress, 50% of benefits | B25: =fb_stress_benefit_high_pct/100 -> 0.5 | C25: =1+fb_stress_cost_overrun_pct/100 -> 5 | D25: =D23 -> 7.98 | E25: the same, its high end
A26: adverse ends | B26: =B23 -> 0.83 | C26: =C23 -> 1.66 | D26: =D23 -> 7.98 | E26: the reference class with every assumed rate at the end of its range that hurts the case, and the run cost at its high end
A28: Cash by period: 1. In-house, no AI, plan | B28: Phase 1 | C28: Phase 2 | D28: Phase 3 | E28: Phase 4 | F28: Year 1 after the exit | G28: Year 2 after the exit | H28: Year 3 after the exit | I28: Year 4 after the exit | J28: Year 5 after the exit | K28: Year 6 after the exit | L28: Year 7 after the exit | M28: Year 8 after the exit | N28: Year 9 after the exit
A29: start, month | B29: 0 | C29: =B29+B30 -> 6 | D29: =C29+C30 -> 12 | E29: =D29+D30 -> 18 | F29: =E29+E30 -> 24 | G29: =F29+F30 -> 36 | H29: =G29+G30 -> 48 | I29: =H29+H30 -> 60 | J29: =I29+I30 -> 72 | ... N29: =M29+M30 -> 120
A30: length, months | B30: =$D$22 -> 6 | C30: =$D$22 -> 6 | D30: =$D$22 -> 6 | E30: =$D$22 -> 6 | F30: =12 -> 12 | G30: =12 -> 12 | H30: =12 -> 12 | I30: =12 -> 12 | J30: =12 -> 12 | K30: =12 -> 12 | L30: =12 -> 12 | M30: =12 -> 12 | N30: =12 -> 12
A31: Claims controls | B31: 0 | C31: =$B$22*$D$6*C$16*C30/12 -> 3.2874281 | D31: =$B$22*$D$6*D$16*D30/12 -> 9.4645173 | E31: =$B$22*$D$6*E$16*E30/12 -> 9.4645173 | F31: =$B$22*$D$6*F$16*F30/12 -> 23.398065 | G31: =$B$22*$D$6*G$16*G30/12 -> 23.398065 | H31: =$B$22*$D$6*H$16*H30/12 -> 23.398065 | I31: =$B$22*$D$6*I$16*I30/12 -> 23.398065 | J31: =$B$22*$D$6*J$16*J30/12 -> 23.398065 | ... N31: =$B$22*$D$6*N$16*N30/12 -> 23.398065
A32: Retention at the upgrade moment | B32: 0 | C32: 0 | D32: =$B$22*$D$7*D$16*D30/12 -> 15.681769 | E32: =$B$22*$D$7*E$16*E30/12 -> 15.681769 | F32: =$B$22*$D$7*F$16*F30/12 -> 38.76828 | G32: =$B$22*$D$7*G$16*G30/12 -> 38.76828 | H32: =$B$22*$D$7*H$16*H30/12 -> 38.76828 | I32: =$B$22*$D$7*I$16*I30/12 -> 38.76828 | J32: =$B$22*$D$7*J$16*J30/12 -> 38.76828 | K32: =$B$22*$D$7*K$16*K30/12 -> 38.76828 | ... N32: =$B$22*$D$7*N$16*N30/12 -> 38.76828
A33: Resale execution: days cut | B33: 0 | C33: 0 | D33: =$B$22*$D$8*D$16*D30/12 -> 6.5977631 | E33: =$B$22*$D$8*E$16*E30/12 -> 6.5977631 | F33: =$B$22*$D$8*F$16*F30/12 -> 16.31091 | G33: =$B$22*$D$8*G$16*G30/12 -> 16.31091 | H33: =$B$22*$D$8*H$16*H30/12 -> 16.31091 | I33: =$B$22*$D$8*I$16*I30/12 -> 16.31091 | J33: =$B$22*$D$8*J$16*J30/12 -> 16.31091 | K33: =$B$22*$D$8*K$16*K30/12 -> 16.31091 | ... N33: =$B$22*$D$8*N$16*N30/12 -> 16.31091
A34: Resale execution: own retail | B34: 0 | C34: 0 | D34: =$B$22*$D$9*D$16*D30/12 -> 3.4385736 | E34: =$B$22*$D$9*E$16*E30/12 -> 3.4385736 | F34: =$B$22*$D$9*F$16*F30/12 -> 8.5008 | G34: =$B$22*$D$9*G$16*G30/12 -> 8.5008 | H34: =$B$22*$D$9*H$16*H30/12 -> 8.5008 | I34: =$B$22*$D$9*I$16*I30/12 -> 8.5008 | J34: =$B$22*$D$9*J$16*J30/12 -> 8.5008 | K34: =$B$22*$D$9*K$16*K30/12 -> 8.5008 | ... N34: =$B$22*$D$9*N$16*N30/12 -> 8.5008
A35: benefit | B35: =SUM(B31:B34) -> 0 | C35: =SUM(C31:C34) -> 3.2874281 | D35: =SUM(D31:D34) -> 35.182623 | E35: =SUM(E31:E34) -> 35.182623 | F35: =SUM(F31:F34) -> 86.978055 | G35: =SUM(G31:G34) -> 86.978055 | H35: =SUM(H31:H34) -> 86.978055 | I35: =SUM(I31:I34) -> 86.978055 | ... N35: =SUM(N31:N34) -> 86.978055
A36: build cost (the phase, at its overrun) | B36: =$C$22*'Programme cost'!$B$49 -> 4.0313856 | C36: =$C$22*'Programme cost'!$C$49 -> 4.0119738 | D36: =$C$22*'Programme cost'!$D$49 -> 4.3549488 | E36: =$C$22*'Programme cost'!$E$49 -> 3.1712947 | F36: 0 | G36: 0 | H36: 0 | I36: 0 | J36: 0 | K36: 0 | L36: 0 | M36: 0 | N36: 0
A37: run cost | B37: 0 | C37: 0 | D37: 0 | E37: 0 | F37: =run_cost_eur_m_year*F30/12 -> 5 | G37: =run_cost_eur_m_year*G30/12 -> 5 | H37: =run_cost_eur_m_year*H30/12 -> 5 | I37: =run_cost_eur_m_year*I30/12 -> 5 | J37: =run_cost_eur_m_year*J30/12 -> 5 | K37: =run_cost_eur_m_year*K30/12 -> 5 | L37: =run_cost_eur_m_year*L30/12 -> 5 | M37: =run_cost_eur_m_year*M30/12 -> 5 | N37: =run_cost_eur_m_year*N30/12 -> 5
A38: share inside the long horizon | B38: =MAX(0,MIN(1,($B$18-B29)/B30)) -> 1 | C38: =MAX(0,MIN(1,($B$18-C29)/C30)) -> 1 | D38: =MAX(0,MIN(1,($B$18-D29)/D30)) -> 1 | E38: =MAX(0,MIN(1,($B$18-E29)/E30)) -> 1 | F38: =MAX(0,MIN(1,($B$18-F29)/F30)) -> 1 | G38: =MAX(0,MIN(1,($B$18-G29)/G30)) -> 1 | H38: =MAX(0,MIN(1,($B$18-H29)/H30)) -> 1 | I38: =MAX(0,MIN(1,($B$18-I29)/I30)) -> 1 | ... N38: =MAX(0,MIN(1,($B$18-N29)/N30)) -> 0
A39: share inside the short horizon | B39: =MAX(0,MIN(1,($B$17-B29)/B30)) -> 1 | C39: =MAX(0,MIN(1,($B$17-C29)/C30)) -> 1 | D39: =MAX(0,MIN(1,($B$17-D29)/D30)) -> 1 | E39: =MAX(0,MIN(1,($B$17-E29)/E30)) -> 1 | F39: =MAX(0,MIN(1,($B$17-F29)/F30)) -> 1 | G39: =MAX(0,MIN(1,($B$17-G29)/G30)) -> 1 | H39: =MAX(0,MIN(1,($B$17-H29)/H30)) -> 1 | I39: =MAX(0,MIN(1,($B$17-I29)/I30)) -> 0 | ... N39: =MAX(0,MIN(1,($B$17-N29)/N30)) -> 0
A40: middle of the part inside the long horizon, month | B40: =B29+B30*B38/2 -> 3 | C40: =C29+C30*C38/2 -> 9 | D40: =D29+D30*D38/2 -> 15 | E40: =E29+E30*E38/2 -> 21 | F40: =F29+F30*F38/2 -> 30 | G40: =G29+G30*G38/2 -> 42 | H40: =H29+H30*H38/2 -> 54 | I40: =I29+I30*I38/2 -> 66 | ... N40: =N29+N30*N38/2 -> 120
A41: middle of the part inside the short horizon, month | B41: =B29+B30*B39/2 -> 3 | C41: =C29+C30*C39/2 -> 9 | D41: =D29+D30*D39/2 -> 15 | E41: =E29+E30*E39/2 -> 21 | F41: =F29+F30*F39/2 -> 30 | G41: =G29+G30*G39/2 -> 42 | H41: =H29+H30*H39/2 -> 54 | I41: =I29+I30*I39/2 -> 60 | ... N41: =N29+N30*N39/2 -> 120
A42: net cash within the long horizon | B42: =(B35-B37)*B38-B36*SIGN(B38) -> -4.0313856 | C42: =(C35-C37)*C38-C36*SIGN(C38) -> -0.72454571 | D42: =(D35-D37)*D38-D36*SIGN(D38) -> 30.827674 | E42: =(E35-E37)*E38-E36*SIGN(E38) -> 32.011329 | F42: =(F35-F37)*F38-F36*SIGN(F38) -> 81.978055 | G42: =(G35-G37)*G38-G36*SIGN(G38) -> 81.978055 | H42: =(H35-H37)*H38-H36*SIGN(H38) -> 81.978055 | I42: =(I35-I37)*I38-I36*SIGN(I38) -> 81.978055 | ... N42: =(N35-N37)*N38-N36*SIGN(N38) -> 0
A43: cumulative | B43: =B42 -> -4.0313856 | C43: =B43+C42 -> -4.7559313 | D43: =C43+D42 -> 26.071743 | E43: =D43+E42 -> 58.083072 | F43: =E43+F42 -> 140.06113 | G43: =F43+G42 -> 222.03918 | H43: =G43+H42 -> 304.01724 | I43: =H43+I42 -> 385.99529 | J43: =I43+J42 -> 467.97335 | ... N43: =M43+N42 -> 713.90751
A44: payback month, if in this period | B44: =IF(AND((-B36*SIGN(B38))<0,(-B36*SIGN(B38))+((B35-B37)*B38)>=0,((B35-B37)*B38)>0),B29+B30*B38*(-(-B36*SIGN(B38)))/((B35-B37)*B38),"-") -> - | C44: =IF(AND((B43-C36*SIGN(C38))<0,(B43-C36*SIGN(C38))+((C35-C37)*C38)>=0,((C35-C37)*C38)>0),C29+C30*C38*(-(B43-C36*SIGN(C38)))/((C35-C37)*C38),"-") -> - | D44: =IF(AND((C43-D36*SIGN(D38))<0,(C43-D36*SIGN(D38))+((D35-D37)*D38)>=0,((D35-D37)*D38)>0),D29+D30*D38*(-(C43-D36*SIGN(D38)))/((D35-D37)*D38),"-") -> 13.553758 | E44: =IF(AND((D43-E36*SIGN(E38))<0,(D43-E36*SIGN(E38))+((E35-E37)*E38)>=0,((E35-E37)*E38)>0),E29+E30*E38*(-(D43-E36*SIGN(E38)))/((E35-E37)*E38),"-") -> - | F44: =IF(AND((E43-F36*SIGN(F38))<0,(E43-F36*SIGN(F38))+((F35-F37)*F38)>=0,((F35-F37)*F38)>0),F29+F30*F38*(-(E43-F36*SIGN(F38)))/((F35-F37)*F38),"-") -> - | G44: =IF(AND((F43-G36*SIGN(G38))<0,(F43-G36*SIGN(G38))+((G35-G37)*G38)>=0,((G35-G37)*G38)>0),G29+G30*G38*(-(F43-G36*SIGN(G38)))/((G35-G37)*G38),"-") -> - | H44: =IF(AND((G43-H36*SIGN(H38))<0,(G43-H36*SIGN(H38))+((H35-H37)*H38)>=0,((H35-H37)*H38)>0),H29+H30*H38*(-(G43-H36*SIGN(H38)))/((H35-H37)*H38),"-") -> - | I44: =IF(AND((H43-I36*SIGN(I38))<0,(H43-I36*SIGN(I38))+((I35-I37)*I38)>=0,((I35-I37)*I38)>0),I29+I30*I38*(-(H43-I36*SIGN(I38)))/((I35-I37)*I38),"-") -> - | J44: =IF(AND((I43-J36*SIGN(J38))<0,(I43-J36*SIGN(J38))+((J35-J37)*J38)>=0,((J35-J37)*J38)>0),J29+J30*J38*(-(I43-J36*SIGN(J38)))/((J35-J37)*J38),"-") -> - | ... N44: =IF(AND((M43-N36*SIGN(N38))<0,(M43-N36*SIGN(N38))+((N35-N37)*N38)>=0,((N35-N37)*N38)>0),N29+N30*N38*(-(M43-N36*SIGN(N38)))/((N35-N37)*N38),"-") -> -
A45: Payback month | B45: =IF(COUNT($B$44:$N$44)=0,"none within ten years",MIN($B$44:$N$44)) -> 13.553758
A46: Loss if stopped at the Phase 1 gate (negative: a gain) | B46: =-B43 -> 4.0313856
A47: Loss if stopped at the Phase 2 gate (negative: a gain) | B47: =-C43 -> 4.7559313
A48: Loss if stopped at the Phase 3 gate (negative: a gain) | B48: =-D43 -> -26.071743
A49: Loss if stopped at the Phase 4 gate (negative: a gain) | B49: =-E43 -> -58.083072
A50: Value over the short horizon at the group's highest pre-tax WACC | B50: =SUMPRODUCT(($B$35:$N$35-$B$37:$N$37)*$B$39:$N$39/(1+stla_wacc_pretax_high_pct/100)^($B$41:$N$41/12))-SUMPRODUCT($B$36:$N$36*SIGN($B$39:$N$39)/(1+stla_wacc_pretax_high_pct/100)^($B$29:$N$29/12)) -> 178.4666
A51: Value over the short horizon at the group's lowest pre-tax WACC | B51: =SUMPRODUCT(($B$35:$N$35-$B$37:$N$37)*$B$39:$N$39/(1+stla_wacc_pretax_low_pct/100)^($B$41:$N$41/12))-SUMPRODUCT($B$36:$N$36*SIGN($B$39:$N$39)/(1+stla_wacc_pretax_low_pct/100)^($B$29:$N$29/12)) -> 229.38501
A52: Value over the long horizon at the group's highest pre-tax WACC | B52: =SUMPRODUCT(($B$35:$N$35-$B$37:$N$37)*$B$38:$N$38/(1+stla_wacc_pretax_high_pct/100)^($B$40:$N$40/12))-SUMPRODUCT($B$36:$N$36*SIGN($B$38:$N$38)/(1+stla_wacc_pretax_high_pct/100)^($B$29:$N$29/12)) -> 293.05005
A53: Value over the long horizon at the group's lowest pre-tax WACC | B53: =SUMPRODUCT(($B$35:$N$35-$B$37:$N$37)*$B$38:$N$38/(1+stla_wacc_pretax_low_pct/100)^($B$40:$N$40/12))-SUMPRODUCT($B$36:$N$36*SIGN($B$38:$N$38)/(1+stla_wacc_pretax_low_pct/100)^($B$29:$N$29/12)) -> 438.61906
A55: Cash by period: 1. In-house, no AI, reference class | B55: Phase 1 | C55: Phase 2 | D55: Phase 3 | E55: Phase 4 | F55: Year 1 after the exit | G55: Year 2 after the exit | H55: Year 3 after the exit | I55: Year 4 after the exit | J55: Year 5 after the exit | K55: Year 6 after the exit | L55: Year 7 after the exit | M55: Year 8 after the exit | N55: Year 9 after the exit
A56: start, month | B56: 0 | C56: =B56+B57 -> 7.98 | D56: =C56+C57 -> 15.96 | E56: =D56+D57 -> 23.94 | F56: =E56+E57 -> 31.92 | G56: =F56+F57 -> 43.92 | H56: =G56+G57 -> 55.92 | I56: =H56+H57 -> 67.92 | J56: =I56+I57 -> 79.92 | ... N56: =M56+M57 -> 127.92
A57: length, months | B57: =$D$23 -> 7.98 | C57: =$D$23 -> 7.98 | D57: =$D$23 -> 7.98 | E57: =$D$23 -> 7.98 | F57: =12 -> 12 | G57: =12 -> 12 | H57: =12 -> 12 | I57: =12 -> 12 | J57: =12 -> 12 | K57: =12 -> 12 | L57: =12 -> 12 | M57: =12 -> 12 | N57: =12 -> 12
A58: Claims controls | B58: 0 | C58: =$B$23*$D$6*C$16*C57/12 -> 3.6289919 | D58: =$B$23*$D$6*D$16*D57/12 -> 10.447881 | E58: =$B$23*$D$6*E$16*E57/12 -> 10.447881 | F58: =$B$23*$D$6*F$16*F57/12 -> 19.420394 | G58: =$B$23*$D$6*G$16*G57/12 -> 19.420394 | H58: =$B$23*$D$6*H$16*H57/12 -> 19.420394 | I58: =$B$23*$D$6*I$16*I57/12 -> 19.420394 | J58: =$B$23*$D$6*J$16*J57/12 -> 19.420394 | ... N58: =$B$23*$D$6*N$16*N57/12 -> 19.420394
A59: Retention at the upgrade moment | B59: 0 | C59: 0 | D59: =$B$23*$D$7*D$16*D57/12 -> 17.311105 | E59: =$B$23*$D$7*E$16*E57/12 -> 17.311105 | F59: =$B$23*$D$7*F$16*F57/12 -> 32.177672 | G59: =$B$23*$D$7*G$16*G57/12 -> 32.177672 | H59: =$B$23*$D$7*H$16*H57/12 -> 32.177672 | I59: =$B$23*$D$7*I$16*I57/12 -> 32.177672 | J59: =$B$23*$D$7*J$16*J57/12 -> 32.177672 | K59: =$B$23*$D$7*K$16*K57/12 -> 32.177672 | ... N59: =$B$23*$D$7*N$16*N57/12 -> 32.177672
A60: Resale execution: days cut | B60: 0 | C60: 0 | D60: =$B$23*$D$8*D$16*D57/12 -> 7.2832707 | E60: =$B$23*$D$8*E$16*E57/12 -> 7.2832707 | F60: =$B$23*$D$8*F$16*F57/12 -> 13.538055 | G60: =$B$23*$D$8*G$16*G57/12 -> 13.538055 | H60: =$B$23*$D$8*H$16*H57/12 -> 13.538055 | I60: =$B$23*$D$8*I$16*I57/12 -> 13.538055 | J60: =$B$23*$D$8*J$16*J57/12 -> 13.538055 | K60: =$B$23*$D$8*K$16*K57/12 -> 13.538055 | ... N60: =$B$23*$D$8*N$16*N57/12 -> 13.538055
A61: Resale execution: own retail | B61: 0 | C61: 0 | D61: =$B$23*$D$9*D$16*D57/12 -> 3.7958414 | E61: =$B$23*$D$9*E$16*E57/12 -> 3.7958414 | F61: =$B$23*$D$9*F$16*F57/12 -> 7.055664 | G61: =$B$23*$D$9*G$16*G57/12 -> 7.055664 | H61: =$B$23*$D$9*H$16*H57/12 -> 7.055664 | I61: =$B$23*$D$9*I$16*I57/12 -> 7.055664 | J61: =$B$23*$D$9*J$16*J57/12 -> 7.055664 | K61: =$B$23*$D$9*K$16*K57/12 -> 7.055664 | ... N61: =$B$23*$D$9*N$16*N57/12 -> 7.055664
A62: benefit | B62: =SUM(B58:B61) -> 0 | C62: =SUM(C58:C61) -> 3.6289919 | D62: =SUM(D58:D61) -> 38.838098 | E62: =SUM(E58:E61) -> 38.838098 | F62: =SUM(F58:F61) -> 72.191786 | G62: =SUM(G58:G61) -> 72.191786 | H62: =SUM(H58:H61) -> 72.191786 | I62: =SUM(I58:I61) -> 72.191786 | ... N62: =SUM(N58:N61) -> 72.191786
A63: build cost (the phase, at its overrun) | B63: =$C$23*'Programme cost'!$B$49 -> 6.6921002 | C63: =$C$23*'Programme cost'!$C$49 -> 6.6598766 | D63: =$C$23*'Programme cost'!$D$49 -> 7.229215 | E63: =$C$23*'Programme cost'!$E$49 -> 5.2643492 | F63: 0 | G63: 0 | H63: 0 | I63: 0 | J63: 0 | K63: 0 | L63: 0 | M63: 0 | N63: 0
A64: run cost | B64: 0 | C64: 0 | D64: 0 | E64: 0 | F64: =run_cost_eur_m_year*F57/12 -> 5 | G64: =run_cost_eur_m_year*G57/12 -> 5 | H64: =run_cost_eur_m_year*H57/12 -> 5 | I64: =run_cost_eur_m_year*I57/12 -> 5 | J64: =run_cost_eur_m_year*J57/12 -> 5 | K64: =run_cost_eur_m_year*K57/12 -> 5 | L64: =run_cost_eur_m_year*L57/12 -> 5 | M64: =run_cost_eur_m_year*M57/12 -> 5 | N64: =run_cost_eur_m_year*N57/12 -> 5
A65: share inside the long horizon | B65: =MAX(0,MIN(1,($B$18-B56)/B57)) -> 1 | C65: =MAX(0,MIN(1,($B$18-C56)/C57)) -> 1 | D65: =MAX(0,MIN(1,($B$18-D56)/D57)) -> 1 | E65: =MAX(0,MIN(1,($B$18-E56)/E57)) -> 1 | F65: =MAX(0,MIN(1,($B$18-F56)/F57)) -> 1 | G65: =MAX(0,MIN(1,($B$18-G56)/G57)) -> 1 | H65: =MAX(0,MIN(1,($B$18-H56)/H57)) -> 1 | I65: =MAX(0,MIN(1,($B$18-I56)/I57)) -> 1 | ... N65: =MAX(0,MIN(1,($B$18-N56)/N57)) -> 0
A66: share inside the short horizon | B66: =MAX(0,MIN(1,($B$17-B56)/B57)) -> 1 | C66: =MAX(0,MIN(1,($B$17-C56)/C57)) -> 1 | D66: =MAX(0,MIN(1,($B$17-D56)/D57)) -> 1 | E66: =MAX(0,MIN(1,($B$17-E56)/E57)) -> 1 | F66: =MAX(0,MIN(1,($B$17-F56)/F57)) -> 1 | G66: =MAX(0,MIN(1,($B$17-G56)/G57)) -> 1 | H66: =MAX(0,MIN(1,($B$17-H56)/H57)) -> 0.34 | I66: =MAX(0,MIN(1,($B$17-I56)/I57)) -> 0 | ... N66: =MAX(0,MIN(1,($B$17-N56)/N57)) -> 0
A67: middle of the part inside the long horizon, month | B67: =B56+B57*B65/2 -> 3.99 | C67: =C56+C57*C65/2 -> 11.97 | D67: =D56+D57*D65/2 -> 19.95 | E67: =E56+E57*E65/2 -> 27.93 | F67: =F56+F57*F65/2 -> 37.92 | G67: =G56+G57*G65/2 -> 49.92 | H67: =H56+H57*H65/2 -> 61.92 | I67: =I56+I57*I65/2 -> 73.92 | ... N67: =N56+N57*N65/2 -> 127.92
A68: middle of the part inside the short horizon, month | B68: =B56+B57*B66/2 -> 3.99 | C68: =C56+C57*C66/2 -> 11.97 | D68: =D56+D57*D66/2 -> 19.95 | E68: =E56+E57*E66/2 -> 27.93 | F68: =F56+F57*F66/2 -> 37.92 | G68: =G56+G57*G66/2 -> 49.92 | H68: =H56+H57*H66/2 -> 57.96 | I68: =I56+I57*I66/2 -> 67.92 | ... N68: =N56+N57*N66/2 -> 127.92
A69: net cash within the long horizon | B69: =(B62-B64)*B65-B63*SIGN(B65) -> -6.6921002 | C69: =(C62-C64)*C65-C63*SIGN(C65) -> -3.0308847 | D69: =(D62-D64)*D65-D63*SIGN(D65) -> 31.608883 | E69: =(E62-E64)*E65-E63*SIGN(E65) -> 33.573749 | F69: =(F62-F64)*F65-F63*SIGN(F65) -> 67.191786 | G69: =(G62-G64)*G65-G63*SIGN(G65) -> 67.191786 | H69: =(H62-H64)*H65-H63*SIGN(H65) -> 67.191786 | I69: =(I62-I64)*I65-I63*SIGN(I65) -> 67.191786 | ... N69: =(N62-N64)*N65-N63*SIGN(N65) -> 0
A70: cumulative | B70: =B69 -> -6.6921002 | C70: =B70+C69 -> -9.7229848 | D70: =C70+D69 -> 21.885898 | E70: =D70+E69 -> 55.459647 | F70: =E70+F69 -> 122.65143 | G70: =F70+G69 -> 189.84322 | H70: =G70+H69 -> 257.035 | I70: =H70+I69 -> 324.22679 | J70: =I70+J69 -> 391.41857 | ... N70: =M70+N69 -> 548.64735
A71: payback month, if in this period | B71: =IF(AND((-B63*SIGN(B65))<0,(-B63*SIGN(B65))+((B62-B64)*B65)>=0,((B62-B64)*B65)>0),B56+B57*B65*(-(-B63*SIGN(B65)))/((B62-B64)*B65),"-") -> - | C71: =IF(AND((B70-C63*SIGN(C65))<0,(B70-C63*SIGN(C65))+((C62-C64)*C65)>=0,((C62-C64)*C65)>0),C56+C57*C65*(-(B70-C63*SIGN(C65)))/((C62-C64)*C65),"-") -> - | D71: =IF(AND((C70-D63*SIGN(D65))<0,(C70-D63*SIGN(D65))+((D62-D64)*D65)>=0,((D62-D64)*D65)>0),D56+D57*D65*(-(C70-D63*SIGN(D65)))/((D62-D64)*D65),"-") -> 19.443141 | E71: =IF(AND((D70-E63*SIGN(E65))<0,(D70-E63*SIGN(E65))+((E62-E64)*E65)>=0,((E62-E64)*E65)>0),E56+E57*E65*(-(D70-E63*SIGN(E65)))/((E62-E64)*E65),"-") -> - | F71: =IF(AND((E70-F63*SIGN(F65))<0,(E70-F63*SIGN(F65))+((F62-F64)*F65)>=0,((F62-F64)*F65)>0),F56+F57*F65*(-(E70-F63*SIGN(F65)))/((F62-F64)*F65),"-") -> - | G71: =IF(AND((F70-G63*SIGN(G65))<0,(F70-G63*SIGN(G65))+((G62-G64)*G65)>=0,((G62-G64)*G65)>0),G56+G57*G65*(-(F70-G63*SIGN(G65)))/((G62-G64)*G65),"-") -> - | H71: =IF(AND((G70-H63*SIGN(H65))<0,(G70-H63*SIGN(H65))+((H62-H64)*H65)>=0,((H62-H64)*H65)>0),H56+H57*H65*(-(G70-H63*SIGN(H65)))/((H62-H64)*H65),"-") -> - | I71: =IF(AND((H70-I63*SIGN(I65))<0,(H70-I63*SIGN(I65))+((I62-I64)*I65)>=0,((I62-I64)*I65)>0),I56+I57*I65*(-(H70-I63*SIGN(I65)))/((I62-I64)*I65),"-") -> - | J71: =IF(AND((I70-J63*SIGN(J65))<0,(I70-J63*SIGN(J65))+((J62-J64)*J65)>=0,((J62-J64)*J65)>0),J56+J57*J65*(-(I70-J63*SIGN(J65)))/((J62-J64)*J65),"-") -> - | ... N71: =IF(AND((M70-N63*SIGN(N65))<0,(M70-N63*SIGN(N65))+((N62-N64)*N65)>=0,((N62-N64)*N65)>0),N56+N57*N65*(-(M70-N63*SIGN(N65)))/((N62-N64)*N65),"-") -> -
A72: Payback month | B72: =IF(COUNT($B$71:$N$71)=0,"none within ten years",MIN($B$71:$N$71)) -> 19.443141
A73: Loss if stopped at the Phase 1 gate (negative: a gain) | B73: =-B70 -> 6.6921002
A74: Loss if stopped at the Phase 2 gate (negative: a gain) | B74: =-C70 -> 9.7229848
A75: Loss if stopped at the Phase 3 gate (negative: a gain) | B75: =-D70 -> -21.885898
A76: Loss if stopped at the Phase 4 gate (negative: a gain) | B76: =-E70 -> -55.459647
A77: Value over the short horizon at the group's highest pre-tax WACC | B77: =SUMPRODUCT(($B$62:$N$62-$B$64:$N$64)*$B$66:$N$66/(1+stla_wacc_pretax_high_pct/100)^($B$68:$N$68/12))-SUMPRODUCT($B$63:$N$63*SIGN($B$66:$N$66)/(1+stla_wacc_pretax_high_pct/100)^($B$56:$N$56/12)) -> 117.18697
A78: Value over the short horizon at the group's lowest pre-tax WACC | B78: =SUMPRODUCT(($B$62:$N$62-$B$64:$N$64)*$B$66:$N$66/(1+stla_wacc_pretax_low_pct/100)^($B$68:$N$68/12))-SUMPRODUCT($B$63:$N$63*SIGN($B$66:$N$66)/(1+stla_wacc_pretax_low_pct/100)^($B$56:$N$56/12)) -> 155.63473
A79: Value over the long horizon at the group's highest pre-tax WACC | B79: =SUMPRODUCT(($B$62:$N$62-$B$64:$N$64)*$B$65:$N$65/(1+stla_wacc_pretax_high_pct/100)^($B$67:$N$67/12))-SUMPRODUCT($B$63:$N$63*SIGN($B$65:$N$65)/(1+stla_wacc_pretax_high_pct/100)^($B$56:$N$56/12)) -> 211.09679
A80: Value over the long horizon at the group's lowest pre-tax WACC | B80: =SUMPRODUCT(($B$62:$N$62-$B$64:$N$64)*$B$65:$N$65/(1+stla_wacc_pretax_low_pct/100)^($B$67:$N$67/12))-SUMPRODUCT($B$63:$N$63*SIGN($B$65:$N$65)/(1+stla_wacc_pretax_low_pct/100)^($B$56:$N$56/12)) -> 327.12789
A81: Present value, decision basis: Claims controls | B81: =SUMPRODUCT($B$58:$N$58*$B$66:$N$66/(1+stla_wacc_pretax_high_pct/100)^($B$68:$N$68/12)) -> 41.320862
A82: Present value, decision basis: Retention at the upgrade moment | B82: =SUMPRODUCT($B$59:$N$59*$B$66:$N$66/(1+stla_wacc_pretax_high_pct/100)^($B$68:$N$68/12)) -> 63.409544
A83: Present value, decision basis: Resale execution: days cut | B83: =SUMPRODUCT($B$60:$N$60*$B$66:$N$66/(1+stla_wacc_pretax_high_pct/100)^($B$68:$N$68/12)) -> 26.678186
A84: Present value, decision basis: Resale execution: own retail | B84: =SUMPRODUCT($B$61:$N$61*$B$66:$N$66/(1+stla_wacc_pretax_high_pct/100)^($B$68:$N$68/12)) -> 13.90394
A85: Present value, decision basis: build cost | B85: =SUMPRODUCT($B$63:$N$63*SIGN($B$66:$N$66)/(1+stla_wacc_pretax_high_pct/100)^($B$56:$N$56/12)) -> 22.081252
A86: Present value, decision basis: run cost | B86: =SUMPRODUCT($B$64:$N$64*$B$66:$N$66/(1+stla_wacc_pretax_high_pct/100)^($B$68:$N$68/12)) -> 6.0443061
A88: Cash by period: 1. In-house, no AI, stress, 25% of benefits | B88: Phase 1 | C88: Phase 2 | D88: Phase 3 | E88: Phase 4 | F88: Year 1 after the exit | G88: Year 2 after the exit | H88: Year 3 after the exit | I88: Year 4 after the exit | J88: Year 5 after the exit | K88: Year 6 after the exit | L88: Year 7 after the exit | M88: Year 8 after the exit | N88: Year 9 after the exit
A89: start, month | B89: 0 | C89: =B89+B90 -> 7.98 | D89: =C89+C90 -> 15.96 | E89: =D89+D90 -> 23.94 | F89: =E89+E90 -> 31.92 | G89: =F89+F90 -> 43.92 | H89: =G89+G90 -> 55.92 | I89: =H89+H90 -> 67.92 | J89: =I89+I90 -> 79.92 | ... N89: =M89+M90 -> 127.92
A90: length, months | B90: =$D$24 -> 7.98 | C90: =$D$24 -> 7.98 | D90: =$D$24 -> 7.98 | E90: =$D$24 -> 7.98 | F90: =12 -> 12 | G90: =12 -> 12 | H90: =12 -> 12 | I90: =12 -> 12 | J90: =12 -> 12 | K90: =12 -> 12 | L90: =12 -> 12 | M90: =12 -> 12 | N90: =12 -> 12
A91: Claims controls | B91: 0 | C91: =$B$24*$D$6*C$16*C90/12 -> 1.0930699 | D91: =$B$24*$D$6*D$16*D90/12 -> 3.146952 | E91: =$B$24*$D$6*E$16*E90/12 -> 3.146952 | F91: =$B$24*$D$6*F$16*F90/12 -> 5.8495162 | G91: =$B$24*$D$6*G$16*G90/12 -> 5.8495162 | H91: =$B$24*$D$6*H$16*H90/12 -> 5.8495162 | I91: =$B$24*$D$6*I$16*I90/12 -> 5.8495162 | J91: =$B$24*$D$6*J$16*J90/12 -> 5.8495162 | ... N91: =$B$24*$D$6*N$16*N90/12 -> 5.8495162
A92: Retention at the upgrade moment | B92: 0 | C92: 0 | D92: =$B$24*$D$7*D$16*D90/12 -> 5.2141883 | E92: =$B$24*$D$7*E$16*E90/12 -> 5.2141883 | F92: =$B$24*$D$7*F$16*F90/12 -> 9.69207 | G92: =$B$24*$D$7*G$16*G90/12 -> 9.69207 | H92: =$B$24*$D$7*H$16*H90/12 -> 9.69207 | I92: =$B$24*$D$7*I$16*I90/12 -> 9.69207 | J92: =$B$24*$D$7*J$16*J90/12 -> 9.69207 | K92: =$B$24*$D$7*K$16*K90/12 -> 9.69207 | ... N92: =$B$24*$D$7*N$16*N90/12 -> 9.69207
A93: Resale execution: days cut | B93: 0 | C93: 0 | D93: =$B$24*$D$8*D$16*D90/12 -> 2.1937562 | E93: =$B$24*$D$8*E$16*E90/12 -> 2.1937562 | F93: =$B$24*$D$8*F$16*F90/12 -> 4.0777275 | G93: =$B$24*$D$8*G$16*G90/12 -> 4.0777275 | H93: =$B$24*$D$8*H$16*H90/12 -> 4.0777275 | I93: =$B$24*$D$8*I$16*I90/12 -> 4.0777275 | J93: =$B$24*$D$8*J$16*J90/12 -> 4.0777275 | K93: =$B$24*$D$8*K$16*K90/12 -> 4.0777275 | ... N93: =$B$24*$D$8*N$16*N90/12 -> 4.0777275
A94: Resale execution: own retail | B94: 0 | C94: 0 | D94: =$B$24*$D$9*D$16*D90/12 -> 1.1433257 | E94: =$B$24*$D$9*E$16*E90/12 -> 1.1433257 | F94: =$B$24*$D$9*F$16*F90/12 -> 2.1252 | G94: =$B$24*$D$9*G$16*G90/12 -> 2.1252 | H94: =$B$24*$D$9*H$16*H90/12 -> 2.1252 | I94: =$B$24*$D$9*I$16*I90/12 -> 2.1252 | J94: =$B$24*$D$9*J$16*J90/12 -> 2.1252 | K94: =$B$24*$D$9*K$16*K90/12 -> 2.1252 | ... N94: =$B$24*$D$9*N$16*N90/12 -> 2.1252
A95: benefit | B95: =SUM(B91:B94) -> 0 | C95: =SUM(C91:C94) -> 1.0930699 | D95: =SUM(D91:D94) -> 11.698222 | E95: =SUM(E91:E94) -> 11.698222 | F95: =SUM(F91:F94) -> 21.744514 | G95: =SUM(G91:G94) -> 21.744514 | H95: =SUM(H91:H94) -> 21.744514 | I95: =SUM(I91:I94) -> 21.744514 | ... N95: =SUM(N91:N94) -> 21.744514
A96: build cost (the phase, at its overrun) | B96: =$C$24*'Programme cost'!$B$49 -> 20.156928 | C96: =$C$24*'Programme cost'!$C$49 -> 20.059869 | D96: =$C$24*'Programme cost'!$D$49 -> 21.774744 | E96: =$C$24*'Programme cost'!$E$49 -> 15.856473 | F96: 0 | G96: 0 | H96: 0 | I96: 0 | J96: 0 | K96: 0 | L96: 0 | M96: 0 | N96: 0
A97: run cost | B97: 0 | C97: 0 | D97: 0 | E97: 0 | F97: =run_cost_eur_m_year*F90/12 -> 5 | G97: =run_cost_eur_m_year*G90/12 -> 5 | H97: =run_cost_eur_m_year*H90/12 -> 5 | I97: =run_cost_eur_m_year*I90/12 -> 5 | J97: =run_cost_eur_m_year*J90/12 -> 5 | K97: =run_cost_eur_m_year*K90/12 -> 5 | L97: =run_cost_eur_m_year*L90/12 -> 5 | M97: =run_cost_eur_m_year*M90/12 -> 5 | N97: =run_cost_eur_m_year*N90/12 -> 5
A98: share inside the long horizon | B98: =MAX(0,MIN(1,($B$18-B89)/B90)) -> 1 | C98: =MAX(0,MIN(1,($B$18-C89)/C90)) -> 1 | D98: =MAX(0,MIN(1,($B$18-D89)/D90)) -> 1 | E98: =MAX(0,MIN(1,($B$18-E89)/E90)) -> 1 | F98: =MAX(0,MIN(1,($B$18-F89)/F90)) -> 1 | G98: =MAX(0,MIN(1,($B$18-G89)/G90)) -> 1 | H98: =MAX(0,MIN(1,($B$18-H89)/H90)) -> 1 | I98: =MAX(0,MIN(1,($B$18-I89)/I90)) -> 1 | ... N98: =MAX(0,MIN(1,($B$18-N89)/N90)) -> 0
A99: share inside the short horizon | B99: =MAX(0,MIN(1,($B$17-B89)/B90)) -> 1 | C99: =MAX(0,MIN(1,($B$17-C89)/C90)) -> 1 | D99: =MAX(0,MIN(1,($B$17-D89)/D90)) -> 1 | E99: =MAX(0,MIN(1,($B$17-E89)/E90)) -> 1 | F99: =MAX(0,MIN(1,($B$17-F89)/F90)) -> 1 | G99: =MAX(0,MIN(1,($B$17-G89)/G90)) -> 1 | H99: =MAX(0,MIN(1,($B$17-H89)/H90)) -> 0.34 | I99: =MAX(0,MIN(1,($B$17-I89)/I90)) -> 0 | ... N99: =MAX(0,MIN(1,($B$17-N89)/N90)) -> 0
A100: middle of the part inside the long horizon, month | B100: =B89+B90*B98/2 -> 3.99 | C100: =C89+C90*C98/2 -> 11.97 | D100: =D89+D90*D98/2 -> 19.95 | E100: =E89+E90*E98/2 -> 27.93 | F100: =F89+F90*F98/2 -> 37.92 | G100: =G89+G90*G98/2 -> 49.92 | H100: =H89+H90*H98/2 -> 61.92 | I100: =I89+I90*I98/2 -> 73.92 | ... N100: =N89+N90*N98/2 -> 127.92
A101: middle of the part inside the short horizon, month | B101: =B89+B90*B99/2 -> 3.99 | C101: =C89+C90*C99/2 -> 11.97 | D101: =D89+D90*D99/2 -> 19.95 | E101: =E89+E90*E99/2 -> 27.93 | F101: =F89+F90*F99/2 -> 37.92 | G101: =G89+G90*G99/2 -> 49.92 | H101: =H89+H90*H99/2 -> 57.96 | I101: =I89+I90*I99/2 -> 67.92 | ... N101: =N89+N90*N99/2 -> 127.92
A102: net cash within the long horizon | B102: =(B95-B97)*B98-B96*SIGN(B98) -> -20.156928 | C102: =(C95-C97)*C98-C96*SIGN(C98) -> -18.966799 | D102: =(D95-D97)*D98-D96*SIGN(D98) -> -10.076522 | E102: =(E95-E97)*E98-E96*SIGN(E98) -> -4.1582513 | F102: =(F95-F97)*F98-F96*SIGN(F98) -> 16.744514 | G102: =(G95-G97)*G98-G96*SIGN(G98) -> 16.744514 | H102: =(H95-H97)*H98-H96*SIGN(H98) -> 16.744514 | I102: =(I95-I97)*I98-I96*SIGN(I98) -> 16.744514 | ... N102: =(N95-N97)*N98-N96*SIGN(N98) -> 0
A103: cumulative | B103: =B102 -> -20.156928 | C103: =B103+C102 -> -39.123728 | D103: =C103+D102 -> -49.200249 | E103: =D103+E102 -> -53.3585 | F103: =E103+F102 -> -36.613987 | G103: =F103+G102 -> -19.869473 | H103: =G103+H102 -> -3.1249592 | I103: =H103+I102 -> 13.619555 | J103: =I103+J102 -> 30.364068 | ... N103: =M103+N102 -> 69.54623
A104: payback month, if in this period | B104: =IF(AND((-B96*SIGN(B98))<0,(-B96*SIGN(B98))+((B95-B97)*B98)>=0,((B95-B97)*B98)>0),B89+B90*B98*(-(-B96*SIGN(B98)))/((B95-B97)*B98),"-") -> - | C104: =IF(AND((B103-C96*SIGN(C98))<0,(B103-C96*SIGN(C98))+((C95-C97)*C98)>=0,((C95-C97)*C98)>0),C89+C90*C98*(-(B103-C96*SIGN(C98)))/((C95-C97)*C98),"-") -> - | D104: =IF(AND((C103-D96*SIGN(D98))<0,(C103-D96*SIGN(D98))+((D95-D97)*D98)>=0,((D95-D97)*D98)>0),D89+D90*D98*(-(C103-D96*SIGN(D98)))/((D95-D97)*D98),"-") -> - | E104: =IF(AND((D103-E96*SIGN(E98))<0,(D103-E96*SIGN(E98))+((E95-E97)*E98)>=0,((E95-E97)*E98)>0),E89+E90*E98*(-(D103-E96*SIGN(E98)))/((E95-E97)*E98),"-") -> - | F104: =IF(AND((E103-F96*SIGN(F98))<0,(E103-F96*SIGN(F98))+((F95-F97)*F98)>=0,((F95-F97)*F98)>0),F89+F90*F98*(-(E103-F96*SIGN(F98)))/((F95-F97)*F98),"-") -> - | G104: =IF(AND((F103-G96*SIGN(G98))<0,(F103-G96*SIGN(G98))+((G95-G97)*G98)>=0,((G95-G97)*G98)>0),G89+G90*G98*(-(F103-G96*SIGN(G98)))/((G95-G97)*G98),"-") -> - | H104: =IF(AND((G103-H96*SIGN(H98))<0,(G103-H96*SIGN(H98))+((H95-H97)*H98)>=0,((H95-H97)*H98)>0),H89+H90*H98*(-(G103-H96*SIGN(H98)))/((H95-H97)*H98),"-") -> - | I104: =IF(AND((H103-I96*SIGN(I98))<0,(H103-I96*SIGN(I98))+((I95-I97)*I98)>=0,((I95-I97)*I98)>0),I89+I90*I98*(-(H103-I96*SIGN(I98)))/((I95-I97)*I98),"-") -> 70.15951 | J104: =IF(AND((I103-J96*SIGN(J98))<0,(I103-J96*SIGN(J98))+((J95-J97)*J98)>=0,((J95-J97)*J98)>0),J89+J90*J98*(-(I103-J96*SIGN(J98)))/((J95-J97)*J98),"-") -> - | ... N104: =IF(AND((M103-N96*SIGN(N98))<0,(M103-N96*SIGN(N98))+((N95-N97)*N98)>=0,((N95-N97)*N98)>0),N89+N90*N98*(-(M103-N96*SIGN(N98)))/((N95-N97)*N98),"-") -> -
A105: Payback month | B105: =IF(COUNT($B$104:$N$104)=0,"none within ten years",MIN($B$104:$N$104)) -> 70.15951
A106: Loss if stopped at the Phase 1 gate (negative: a gain) | B106: =-B103 -> 20.156928
...

Sheet Prior discounting
A1: What a discount at the new sale costs when the car comes back
A3: Not a fourth leak. These euros are already counted - in leak 1 as spend and in leak 3 as residual exposure - and are cut here by cause instead of by business. The point of the cut is that this part is the group's own decision, and the market level is not.
A5: The two estimates, and what they rest on
A6: Share of a deeper deal still there at resale, measured | B6: =dpt_passthrough -> 0.3 | C6: MEASURED - 35,552 resales of cars also seen at their own new sale. An upper bound: no trim field
A7: Published: % of residual lost at 36 months, per 10% discount | B7: =hk_passthrough_36m -> 6.5 | C7: SOURCED - Holweg and Kattuman, UK auction prices 1999-2004
A8: Published: the same in the same month, per 10% discount | B8: =hk_passthrough_now -> 1.5 | C8: SOURCED - the smaller, substitution channel
A9: Discount assumed given, % of list | B9: =pl_incentive_pct_list -> 8 | C9: ASSUMPTION - the Per car sheet's incentive, a share of list (pl_incentive_pct_list)
A11: One car, euros
A12: List price when new | B12: =new_car_price_eur -> 11969
A13: Incentive given at the new sale | B13: =new_car_price_eur * pl_incentive_pct_list/100 -> 957.52
A14: Residual value when it comes back | B14: =new_car_price_eur * retained_4y_uk/100 -> 7061.71 | C14: the contractual residual on a 48-month contract
A15: Share of that residual lost, measured (low) | B15: =1-(1-pl_incentive_pct_list/100)^dpt_passthrough -> 0.024704213
A16: Share of that residual lost, published (high) | B16: =(hk_passthrough_36m + hk_passthrough_now)/100 * pl_incentive_pct_list/10 -> 0.064
A17: Residual lost to the discount, low | B17: =B14 * B15 -> 174.45399
A18: Residual lost to the discount, high | B18: =B14 * B16 -> 451.94944
A20: Cost at resale per euro of incentive given, low | B20: =B17 / B13 -> 0.18219357 | C20: every euro handed over at the new sale costs this much again at resale
A21: Cost at resale per euro of incentive given, high | B21: =B18 / B13 -> 0.472
A24: The book, EUR millions a year
A25: Buy-back residual falling due within a year | B25: =buyback_payables_current_eur_m -> 5313 | C25: SOURCED - the current portion of the buy-back payables, the same base leak 3 uses
A26: Of that, traceable to our own prior discounting - low | B26: =B25 * B15 -> 131.25348
A27: Of that, traceable to our own prior discounting - high | B27: =B25 * B16 -> 340.032
A30: How to read this sheet
A31: - The headline on the Summary sheet does not change. Nothing here is added to it.
A32: - The low end is measured per car on US electric and plug-in vehicles and is an upper bound in its own terms, because the source has no trim field and part of a cheap new price is a cheaper car. The high end is published, specification-normalised, and from UK auctions in 1999-2004. Quote the range, never one end.
A33: - The published coefficient is for a 36-month residual and is applied here to a 48-month contract.
A34: - A market-level pass-through could not be measured at all: see part 3 of analysis/discount_passthrough_report.md, where every European market in Eurostat's new-car and used-car indices gives nothing after the price move and more before it.
A35: - This is the line that joins leak 1 to leak 3. It is also the only line in the model the group can move by deciding to, which is why it belongs in the pitch.

Sheet Programme cost
A1: Programme cost: the build on four bases, from one work list (X25)
A2: EUR millions over the 24-month build unless stated. One work list (the Work list sheet, work_list.csv: every FTE an ASSUMPTION with its basis) priced four ways: 1 in-house at Eurostat's loaded cost of an employee in manufacturing plus overhead; 2 an integrator at a public rate card (Deloitte, G-Cloud 14, UK: a ceiling), the group keeping legal, Finance and model validation; 3 in-house with AI, saving only what the studies measured on the share of the week they touch, plus the tools' seats; 4 each workstream's cheapest route, the per-car store and the value engine always built. Platform and change delivery are the same in every base. analysis/programme_cost_report.md.
A4: role | B4: pay group | C4: in-house, central team (EUR a month) | D4: in-house, the four markets | E4: in-house, the lower-cost hub | F4: integrator at the rate card | G4: AI saving, central | H4: AI saving, upper | I4: AI saving, adverse | J4: AI seats (EUR a month)
A5: engineer | B5: OC2 | C5: =(x25_loc_fr_pct/100*x25_loaded_oc2_fr_eur+(1-x25_loc_fr_pct/100)*x25_loaded_oc2_it_eur)/12*(1+x25_overhead_pct/100) -> 10125.06 | D5: =(x25_loaded_oc2_fr_eur+x25_loaded_oc2_it_eur+x25_loaded_oc2_de_eur+x25_loaded_oc2_es_eur)/4/12*(1+x25_overhead_pct/100) -> 10177.9 | E5: =x25_loaded_oc2_pl_eur/12*(1+x25_overhead_pct/100) -> 3847.5 | F5: =dl_gc14_dev_l4_gbp_day/x25_gbp_per_eur*x25_days_per_fte_year/12 -> 27265.391 | G5: =(ai_timewarp_coding_pct+ai_timewarp_debugging_pct+ai_timewarp_review_pct)/100*(1-1/(1+ai_cui_tasks_pct/100)) -> 0.051713198 | H5: =(ai_timewarp_coding_pct+ai_timewarp_debugging_pct+ai_timewarp_review_pct)/100*ai_peng_faster_pct/100 -> 0.1395 | I5: =-(ai_timewarp_coding_pct+ai_timewarp_debugging_pct+ai_timewarp_review_pct)/100*ai_metr25_time_pct/100 -> -0.0475 | J5: =(gh_copilot_enterprise_usd_user_month+claude_team_std_usd_seat_month)/x25_usd_per_eur -> 50.695996
A6: data_scientist | B6: OC2 | C6: =(x25_loc_fr_pct/100*x25_loaded_oc2_fr_eur+(1-x25_loc_fr_pct/100)*x25_loaded_oc2_it_eur)/12*(1+x25_overhead_pct/100) -> 10125.06 | D6: =(x25_loaded_oc2_fr_eur+x25_loaded_oc2_it_eur+x25_loaded_oc2_de_eur+x25_loaded_oc2_es_eur)/4/12*(1+x25_overhead_pct/100) -> 10177.9 | E6: =x25_loaded_oc2_pl_eur/12*(1+x25_overhead_pct/100) -> 3847.5 | F6: =dl_gc14_dev_l5_gbp_day/x25_gbp_per_eur*x25_days_per_fte_year/12 -> 34874.337 | G6: =(ai_timewarp_coding_pct+ai_timewarp_debugging_pct+ai_timewarp_review_pct)/100*(1-1/(1+ai_cui_tasks_pct/100)) -> 0.051713198 | H6: =(ai_timewarp_coding_pct+ai_timewarp_debugging_pct+ai_timewarp_review_pct)/100*ai_peng_faster_pct/100 -> 0.1395 | I6: =-(ai_timewarp_coding_pct+ai_timewarp_debugging_pct+ai_timewarp_review_pct)/100*ai_metr25_time_pct/100 -> -0.0475 | J6: =(gh_copilot_enterprise_usd_user_month+claude_team_std_usd_seat_month)/x25_usd_per_eur -> 50.695996
A7: architect | B7: OC2 | C7: =(x25_loc_fr_pct/100*x25_loaded_oc2_fr_eur+(1-x25_loc_fr_pct/100)*x25_loaded_oc2_it_eur)/12*(1+x25_overhead_pct/100) -> 10125.06 | D7: =(x25_loaded_oc2_fr_eur+x25_loaded_oc2_it_eur+x25_loaded_oc2_de_eur+x25_loaded_oc2_es_eur)/4/12*(1+x25_overhead_pct/100) -> 10177.9 | E7: =x25_loaded_oc2_pl_eur/12*(1+x25_overhead_pct/100) -> 3847.5 | F7: =dl_gc14_arch_l5_gbp_day/x25_gbp_per_eur*x25_days_per_fte_year/12 -> 38573.13 | G7: =hv_time_savings_pct/100 -> 0.03 | H7: =hv_time_savings_pct/100 -> 0.03 | I7: =0 -> 0 | J7: =claude_team_std_usd_seat_month/x25_usd_per_eur -> 17.185083
A8: product_owner | B8: OC2 | C8: =(x25_loc_fr_pct/100*x25_loaded_oc2_fr_eur+(1-x25_loc_fr_pct/100)*x25_loaded_oc2_it_eur)/12*(1+x25_overhead_pct/100) -> 10125.06 | D8: =(x25_loaded_oc2_fr_eur+x25_loaded_oc2_it_eur+x25_loaded_oc2_de_eur+x25_loaded_oc2_es_eur)/4/12*(1+x25_overhead_pct/100) -> 10177.9 | E8: =x25_loaded_oc2_pl_eur/12*(1+x25_overhead_pct/100) -> 3847.5 | F8: =dl_gc14_arch_l4_gbp_day/x25_gbp_per_eur*x25_days_per_fte_year/12 -> 34874.337 | G8: =hv_time_savings_pct/100 -> 0.03 | H8: =hv_time_savings_pct/100 -> 0.03 | I8: =0 -> 0 | J8: =claude_team_std_usd_seat_month/x25_usd_per_eur -> 17.185083
A9: model_validator | B9: OC2 | C9: =(x25_loc_fr_pct/100*x25_loaded_oc2_fr_eur+(1-x25_loc_fr_pct/100)*x25_loaded_oc2_it_eur)/12*(1+x25_overhead_pct/100) -> 10125.06 | D9: =(x25_loaded_oc2_fr_eur+x25_loaded_oc2_it_eur+x25_loaded_oc2_de_eur+x25_loaded_oc2_es_eur)/4/12*(1+x25_overhead_pct/100) -> 10177.9 | E9: =x25_loaded_oc2_pl_eur/12*(1+x25_overhead_pct/100) -> 3847.5 | F9: kept in-house | G9: =hv_time_savings_pct/100 -> 0.03 | H9: =hv_time_savings_pct/100 -> 0.03 | I9: =0 -> 0 | J9: =claude_team_std_usd_seat_month/x25_usd_per_eur -> 17.185083
A10: legal_counsel | B10: OC2 | C10: =(x25_loc_fr_pct/100*x25_loaded_oc2_fr_eur+(1-x25_loc_fr_pct/100)*x25_loaded_oc2_it_eur)/12*(1+x25_overhead_pct/100) -> 10125.06 | D10: =(x25_loaded_oc2_fr_eur+x25_loaded_oc2_it_eur+x25_loaded_oc2_de_eur+x25_loaded_oc2_es_eur)/4/12*(1+x25_overhead_pct/100) -> 10177.9 | E10: =x25_loaded_oc2_pl_eur/12*(1+x25_overhead_pct/100) -> 3847.5 | F10: kept in-house | G10: =hv_time_savings_pct/100 -> 0.03 | H10: =hv_time_savings_pct/100 -> 0.03 | I10: =0 -> 0 | J10: =claude_team_std_usd_seat_month/x25_usd_per_eur -> 17.185083
A11: change_lead | B11: OC2 | C11: =(x25_loc_fr_pct/100*x25_loaded_oc2_fr_eur+(1-x25_loc_fr_pct/100)*x25_loaded_oc2_it_eur)/12*(1+x25_overhead_pct/100) -> 10125.06 | D11: =(x25_loaded_oc2_fr_eur+x25_loaded_oc2_it_eur+x25_loaded_oc2_de_eur+x25_loaded_oc2_es_eur)/4/12*(1+x25_overhead_pct/100) -> 10177.9 | E11: =x25_loaded_oc2_pl_eur/12*(1+x25_overhead_pct/100) -> 3847.5 | F11: =dl_gc14_arch_l4_gbp_day/x25_gbp_per_eur*x25_days_per_fte_year/12 -> 34874.337 | G11: =hv_time_savings_pct/100 -> 0.03 | H11: =hv_time_savings_pct/100 -> 0.03 | I11: =0 -> 0 | J11: =claude_team_std_usd_seat_month/x25_usd_per_eur -> 17.185083
A12: finance_analyst | B12: OC2 | C12: =(x25_loc_fr_pct/100*x25_loaded_oc2_fr_eur+(1-x25_loc_fr_pct/100)*x25_loaded_oc2_it_eur)/12*(1+x25_overhead_pct/100) -> 10125.06 | D12: =(x25_loaded_oc2_fr_eur+x25_loaded_oc2_it_eur+x25_loaded_oc2_de_eur+x25_loaded_oc2_es_eur)/4/12*(1+x25_overhead_pct/100) -> 10177.9 | E12: =x25_loaded_oc2_pl_eur/12*(1+x25_overhead_pct/100) -> 3847.5 | F12: kept in-house | G12: =hv_time_savings_pct/100 -> 0.03 | H12: =hv_time_savings_pct/100 -> 0.03 | I12: =0 -> 0 | J12: =claude_team_std_usd_seat_month/x25_usd_per_eur -> 17.185083
A13: programme_manager | B13: OC1 | C13: =(x25_loc_fr_pct/100*x25_loaded_oc1_fr_eur+(1-x25_loc_fr_pct/100)*x25_loaded_oc1_it_eur)/12*(1+x25_overhead_pct/100) -> 19607.1 | D13: =(x25_loaded_oc1_fr_eur+x25_loaded_oc1_it_eur+x25_loaded_oc1_de_eur+x25_loaded_oc1_es_eur)/4/12*(1+x25_overhead_pct/100) -> 17897.45 | E13: =x25_loaded_oc1_pl_eur/12*(1+x25_overhead_pct/100) -> 5979.5 | F13: =dl_gc14_arch_l6_gbp_day/x25_gbp_per_eur*x25_days_per_fte_year/12 -> 44385.52 | G13: =hv_time_savings_pct/100 -> 0.03 | H13: =hv_time_savings_pct/100 -> 0.03 | I13: =0 -> 0 | J13: =claude_team_std_usd_seat_month/x25_usd_per_eur -> 17.185083
A14: data_steward | B14: OC3 | C14: =(x25_loc_fr_pct/100*x25_loaded_oc3_fr_eur+(1-x25_loc_fr_pct/100)*x25_loaded_oc3_it_eur)/12*(1+x25_overhead_pct/100) -> 6889.76 | D14: =(x25_loaded_oc3_fr_eur+x25_loaded_oc3_it_eur+x25_loaded_oc3_de_eur+x25_loaded_oc3_es_eur)/4/12*(1+x25_overhead_pct/100) -> 7598.35 | E14: =x25_loaded_oc3_pl_eur/12*(1+x25_overhead_pct/100) -> 3161.9 | F14: =dl_gc14_dev_l3_gbp_day/x25_gbp_per_eur*x25_days_per_fte_year/12 -> 23038.198 | G14: =hv_time_savings_pct/100 -> 0.03 | H14: =hv_time_savings_pct/100 -> 0.03 | I14: =0 -> 0 | J14: =claude_team_std_usd_seat_month/x25_usd_per_eur -> 17.185083
A16: The four bases, EUR m over the build
A17: base | B17: people | C17: AI tools | D17: platform, data and licences | E17: change delivery | F17: total
A18: 1. In-house, no AI | B18: =SUM('Work list'!$H$2:$H$91) -> 8.569603 | C18: =0 -> 0 | D18: =inv_platform_eur_m -> 4 | E18: =inv_change_eur_m -> 3 | F18: =SUM(B18:E18) -> 15.569603
A19: 2. Buy and outsource (rate card) | B19: =SUM('Work list'!$I$2:$I$91) -> 23.876957 | C19: =0 -> 0 | D19: =inv_platform_eur_m -> 4 | E19: =inv_change_eur_m -> 3 | F19: =SUM(B19:E19) -> 30.876957
A20: 3. In-house with AI, central | B20: =SUM('Work list'!$J$2:$J$91) -> 8.2182003 | C20: =SUM('Work list'!$K$2:$K$91) -> 0.027075002 | D20: =inv_platform_eur_m -> 4 | E20: =inv_change_eur_m -> 3 | F20: =SUM(B20:E20) -> 15.245275
A21: 3. In-house with AI, upper gain | B21: =SUM('Work list'!$L$2:$L$91) -> 7.8368851 | C21: =SUM('Work list'!$M$2:$M$91) -> 0.025165763 | D21: =inv_platform_eur_m -> 4 | E21: =inv_change_eur_m -> 3 | F21: =SUM(B21:E21) -> 14.862051
A22: 3. In-house with AI, adverse | B22: =SUM('Work list'!$N$2:$N$91) -> 8.7759264 | C22: =SUM('Work list'!$O$2:$O$91) -> 0.029432267 | D22: =inv_platform_eur_m -> 4 | E22: =inv_change_eur_m -> 3 | F22: =SUM(B22:E22) -> 15.805359
A23: 4. Cheapest route per workstream | B23: =SUM(G29:G39) -> 8.2452753 | C23: =0 -> 0 | D23: =inv_platform_eur_m -> 4 | E23: =inv_change_eur_m -> 3 | F23: =SUM(B23:E23) -> 15.245275
